Workbook
Name \A: #REF!
Name \B: #REF!
Name \E: #REF!
Name \H: #REF!
Name \L: #REF!
Name \M: #REF!
Name \O: #REF!
Name \S: #REF!
Name \V: #REF!
Name \W: #REF!
Name a: #REF!
Name ABC: #REF!
Name adjfasl: #REF!
Name adjfasl: #REF!
Name adjfasl: #REF!
Name adjfasl: #REF!
Name adjfasl: #REF!
Name adjfasl: #REF!
Name adjfasl: #REF!
Name admin_3_2: #REF!
Name admin_cross: #REF!
Name AU_329: #REF!
Name b: #REF!
Name C_: #REF!
Name CF: #REF!
Name cogos: #REF!
Name cogos_cross: #REF!
Name cogos_detail: #REF!
Name cogs: #REF!
Name consumer: #REF!
Name COST: #REF!
Name d: #REF!
Name DETAILS: #REF!
Name discount: #REF!
Name DME: #REF!
Name DRAWB: #REF!
Name DRSUP: #REF!
Name ER: #REF!
Name EXCH: #REF!
Name f: #REF!
Name financialcharges: #REF!
Name g: #REF!
Name gratuity: #REF!
Name hffix: #REF!
Name L: #REF!
Name LACHM: #REF!
Name LACHMN: #REF!
Name List_LevelAssurance: #REF!
Name List_TypeProcedure: #REF!
Name LMR: #REF!
Name m: #REF!
Name MENU: #REF!
Name n: #REF!
Name nid: #REF!
Name nnumb: #REF!
Name nnumb1: #REF!
Name nokia206: #REF!
Name nokia206: #REF!
Name NUMB: #REF!
Name numbers: #REF!

Sheet Con BS
A1: PAKISTAN INSTITUTE OF LABOUR EDUCATION AND RESEARCH
A2: STATEMENT OF FINANCIAL POSITION
A3: AS AT JUNE 30, 2026
I6: 2026 | L6: 2025 | N6: 2024
G7: Note | I7: Rupees | K7: Note | L7: Rupees | N7: Rupees
A8: ASSETS
A9: Non - Current Assets
A10: Property and equipment | G10: ='PPE-Note-4'!A1 -> 5 | I10: ='PPE-Note-4'!O116 -> 14035031 | K10: =+'PPE-Note-4'!A1 -> 5 | L10: ='PPE-Note-4'!O59 -> 15295085 | N10: ='PPE-Note-4'!O42 -> 16140069 | Q10: =N10-L10 -> 844984 | Z10: 20916309 | AA10: =+Z10-N10 -> 4776240
A11: Intangible assets | G11: ='Con 5-18'!A2 -> 6 | K11: =+'Con 5-18'!A2 -> 6 | L11: ='Con 5-18'!M9 -> 5815 | N11: ='Con 5-18'!O15 -> 8722 | Q11: =N11-L11 -> 2907
A12: Security deposits | L12: 0 | N12: 0 | Q12: =N12-L12 -> 0
I13: =SUM(I10:I12) -> 14035031 | L13: =SUM(L10:L12) -> 15300900 | N13: =SUM(N10:N12) -> 16148791
A15: Current Assets
A16: Advances, deposits and other receivables | G16: ='Con 5-18'!A36 -> 7 | K16: =+'Con 5-18'!A36 -> 7 | L16: =ROUND('Con 5-18'!M47, 0) -> #REF! | N16: ='Con 5-18'!O47 -> 1710587 | Q16: =N16-L16 -> #REF!
A17: Bank balances | G17: ='Con 5-18'!A49 -> 8 | K17: =+'Con 5-18'!A49 -> 8 | L17: =ROUND('Con 5-18'!M54, 0) -> #REF! | N17: ='Con 5-18'!O54 -> 2725572.5 | Q17: =N17-L17 -> #REF!
I18: =SUM(I16:I17) -> 0 | L18: =SUM(L16:L17) -> #REF! | N18: =SUM(N16:N17) -> 4436159.5 | Y18: =#REF!-N18 -> #REF!
A20: TOTAL ASSETS | I20: =SUM(I13,I18) -> 14035031 | L20: =SUM(L13,L18) -> #REF! | N20: =SUM(N13,N18) -> 20584951
A22: FUNDS AND LIABILITIES
A23: Fund balance | L23: =ROUND(SOCE!M32,0) -> -27233980 | N23: =+SOCE!M28 -> -30425260 | Q23: =L23-N23 -> 3191280.5
A25: Non - Current Liabilities
A26: Lease liabilities | L26: 0 | N26: 0 | Q26: =L26-N26 -> 0 | Z26: =+N26-#REF! -> #REF!
A28: Current Liabilities
A29: Current portion of lease liabilities | L29: 0 | N29: 0 | Q29: =L29-N29 -> 0 | Z29: =+N29-#REF! -> #REF!
A30: Accrued and other liabilities | G30: ='Con 5-18'!A70 -> 9 | K30: =+'Con 5-18'!A70 -> 9 | L30: =ROUND('Con 5-18'!M76,0) -> 9804523 | N30: ='Con 5-18'!O76 -> 10219196 | Q30: =L30-N30 -> -414673 | Z30: =+N30-#REF! -> #REF!
A31: Taxation - net | L31: =-ROUND(GETPIVOTDATA("Sum of Amount",'Pivot 2025'!$A$3,"FSL1","Profit and Loss","FSL2","Taxation","FSL3","Income Tax Expenses","FSL 4","Income Tax Expenses"),0)+'Adjustments 2025'!F78 -> 186605 | N31: 0
A32: Short term liabilities | G32: ='Con 5-18'!A78 -> 10 | K32: =+'Con 5-18'!A78 -> 10 | L32: =ROUND('Con 5-18'!M82,0) -> #REF! | N32: ='Con 5-18'!O82 -> 40791015 | Q32: =L32-N32 -> #REF! | S32: =L32-39791015 -> #REF! | Z32: =+N32-#REF! -> #REF!
I33: =SUM(I29:I32) -> 0 | L33: =SUM(L29:L32) -> #REF! | N33: =N30+N32+N29 -> 51010211
A35: TOTAL FUNDS AND LIABILITIES | I35: =+I23+I26+I33 -> 0 | L35: =+L23+L26+L33 -> #REF! | N35: =+N23+N26+N33 -> 20584951
L37: =L35-L20 -> #REF! | Q37: =+L35-L20 -> #REF! | R37: =N35-N20 -> 0
A38: ="The annexed notes form an integral part of these financial statements." -> The annexed notes form an integral part of these financial statements.
Q39: =+GETPIVOTDATA("Sum of Amount",'Pivot 2025'!$A$3,"FSL1","-","FSL2","Inter Project Balances") -> 0.47 | R39: Difference of inter project balance
Q40: =-GETPIVOTDATA("Sum of Amount",'Pivot 2025'!$A$3) -> -0.85163715 | R40: Difference of TB
Q41: =+SOCE!AL25 -> 5815.06 | R41: Difference of fund balance - opening
Q43: =SUM(Q39:Q42) -> 5814.6784
Q45: =+Q37-Q43 -> #REF!
B61: Chief Executive Officer | G61: Director
G350: 9788859 | K350: 9788859 | M350: 9788859
C351: Short term Liabilities | G351: 39791015 | K351: 39791015 | M351: 39791015
P401: 0

Sheet Con I EX
A1: PAKISTAN INSTITUTE OF LABOUR EDUCATION AND RESEARCH
A2: STATEMENT OF INCOME AND EXPENDITURE
A3: FOR THE YEAR ENDED JUNE 30, 2025
I6: 2026 | K6: 2025 | M6: 2024
G7: Note | I7: Rupees | K7: Rupees | M7: Rupees | N7: Chief Executive Officer | S7: Director
A9: Income from donations | K9: =+-ROUND(GETPIVOTDATA("Sum of Amount",'Pivot 2025'!$A$3,"FSL1","Profit and Loss","FSL2","Income From Donations","FSL3","Income From Donations"),0) -> 36461449 | M9: 19036148 | N9: 46013529 | P9: #REF! | S9: 70923139
A11: Operating cost | G11: =+'Con 5-18'!A107 -> 11 | K11: =-GETPIVOTDATA("Sum of Amount",'Pivot 2025'!$A$3,"FSL1","Profit and Loss","FSL2","Operating Costs") -> -25789481 | M11: =-'Con 5-18'!O138 -> -15852917 | N11: =+-'Con 5-18'!P138 -> #REF! | P11: =+-'Con 5-18'!R138 -> #REF! | S11: =+-'Con 5-18'!T138 -> #REF!
A12: Administrative and general expenses | G12: =+'Con 5-18'!A140 -> 12 | K12: =-ROUND('Con 5-18'!M168,0) -> -7605812 | M12: =-'Con 5-18'!O168 -> -4463948 | N12: =+-'Con 5-18'!P168 -> #REF! | P12: =+-'Con 5-18'!R168 -> #REF! | S12: =+-'Con 5-18'!T168 -> -29875202
K13: =SUM(K11:K12) -> -33395293 | M13: =SUM(M11:M12) -> -20316865 | N13: =SUM(N11:N12) -> #REF! | P13: =SUM(P11:P12) -> #REF! | S13: =S11+S12 -> #REF!
A15: Surplus / (deficit) from operating activities | K15: =K9+K13 -> 3066156 | M15: =M9+M13 -> -1280717 | N15: =N9+N13 -> #REF! | P15: =P9+P13 -> #REF! | S15: =S9+S13 -> #REF!
A17: Other income | G17: =+'Con 5-18'!A188 -> 13 | K17: =ROUND('Con 5-18'!M196,0) -> 821846 | M17: ='Con 5-18'!O196 -> 1640088.5 | N17: =+'Con 5-18'!P196 -> 786976.53 | P17: =+'Con 5-18'!R196 -> #REF! | S17: =+'Con 5-18'!T196 -> 1363912.1
A18: Financial charges | G18: =+'Con 5-18'!A204 -> 14 | K18: =-ROUND('Con 5-18'!M209,0) -> -17863 | M18: =-'Con 5-18'!O209 -> -365187 | N18: =-'Con 5-18'!P209 -> #REF! | P18: #REF! | S18: 0
A20: Surplus / (deficit) before income tax | K20: =K15+K17+K18 -> 3870139 | M20: =M15+M17+M18 -> -5815.4515 | N20: =N15+N17+N18 -> #REF! | P20: =P15+P17+P18 -> #REF! | S20: =S15+S17+S18 -> #REF!
A22: Minimum tax differential | K22: 0 | M22: 0
A24: Deficit before income tax | K24: =SUM(K20:K23) -> 3870139 | M24: =SUM(M20:M23) -> -5815.4515
A26: Taxation
A27: - | B27: Current tax | K27: =-'Adjustments 2025'!E77 -> -678859 | M27: 0
A29: Surplus / (deficit) for the year | K29: =+K20+K27 -> 3191280 | M29: =+M20+M27 -> -5815.4515 | N29: =+N20+#REF! -> #REF! | P29: =+P20+#REF! -> #REF! | S29: =+S20+#REF! -> #REF! | Z29: =+N29+3049662 -> #REF!
A32: ='Con BS'!A38 -> The annexed notes form an integral part of these financial statements.
V38: f
B60: Chief Executive Officer | G60: Director
F350: 9788859 | G350: 9788859 | L350: 9788859
C351: Short term Liabilities | F351: 39791015 | G351: 39791015 | L351: 39791015
O401: 0

Sheet SOCE
A1: PAKISTAN INSTITUTE OF LABOUR EDUCATION AND RESEARCH
A2: STATEMENT OF CHANGES IN NET ASSETS
A3: ='Con I EX'!A3 -> FOR THE YEAR ENDED JUNE 30, 2025
H6: Accumulated deficit | J6: Total fund balance | M6: Accumulated deficit | O6: Total fund balance
AL8: `
H10: ---------------- Rupees -------------- | M10: ---------------- Rupees -------------- | AL10: `
A12: Balance as at June 30, 2014 | I12: 50097736 | N12: 50097736 | P12: =N12 -> 50097736
A14: Restatement - Note 3.10 | I14: 0 | N14: 0 | P14: =N14 -> 0
R15: 43840937
A16: Balance as at July 01, 2018 | H16: 8021729.1 | J16: =H16 -> 8021729.1 | M16: 8021729.1 | O16: =M16 -> 8021729.1
A18: (Deficit) for the year ended June 30, 2018 | H18: -12489404 | J18: =H18 -> -12489404 | M18: -12489404 | O18: =M18 -> -12489404
A20: Balance as at July 01, 2022 | H20: -22020234 | J20: =+H20 -> -22020234 | M20: -22020234 | O20: =+M20 -> -22020234
A22: Surplus for the year ended June 30, 2023 | H22: 22288181 | J22: =H22 -> 22288181 | M22: 22288181 | O22: =M22 -> 22288181
A24: Balance as at July 01, 2023 | H24: -30419445 | J24: =+H24 -> -30419445 | M24: -30419445 | O24: =+M24 -> -30419445 | AL24: =+GETPIVOTDATA("Sum of Amount",'Pivot 2025'!$A$3,"FSL1","Balance Sheet","FSL2","Fund Balance") -> 30425260
AL25: =+AL24+M24 -> 5815.06
A26: Deficit for the year ended June 30, 2024 | H26: =+'Con I EX'!H29 -> 0 | J26: =+H26 -> 0 | M26: =+'Con I EX'!M29 -> -5815.4515 | O26: =+M26 -> -5815.4515
A28: Balance as at June 30, 2024 | H28: =+H24+H26 -> -30419445 | J28: =+J24+J26 -> -30419445 | M28: =+M24+M26 -> -30425260 | O28: =+O24+O26 -> -30425260
A30: Surplus for the year ended June 30, 2025 | H30: ='Con I EX'!F29 -> 0 | J30: =+H30 -> 0 | M30: ='Con I EX'!K29 -> 3191280 | O30: =+M30 -> 3191280
A32: Balance as at June 30, 2025 | H32: =+H28+H30 -> -30419445 | J32: =+J28+J30 -> -30419445 | M32: =+M28+M30 -> -27233980 | O32: =+O28+O30 -> -27233980
A35: ='Con BS'!A38 -> The annexed notes form an integral part of these financial statements.
S36: =#REF!-#REF! -> #REF!
B68: Chief Executive Officer | G68: Director
F350: 9788859 | G350: 9788859 | N350: 9788859
C351: Short term Liabilities | F351: 39791015 | G351: 39791015 | N351: 39791015
Q401: 0

Sheet CFS
A1: PAKISTAN INSTITUTE OF LABOUR EDUCATION AND RESEARCH
A2: STATEMENT OF CASH FLOWS
A3: =+SOCE!A3 -> FOR THE YEAR ENDED JUNE 30, 2025
H6: 2025 | J6: 2024 | L6: 2016
G7: Note | H7: Rupees | J7: Rupees | L7: Rupees
A8: CASH FLOW FROM OPERATING ACTIVITIES
A9: =+'Con I EX'!A20 -> Surplus / (deficit) before income tax | H9: ='Con I EX'!K20 -> 3870139 | J9: -5815 | L9: =+'Con I EX'!P20 -> #REF! | O9: =ROUND(J9,0) -> -5815
A10: Adjustment for non cash items : | O10: =ROUND(J10,0) -> 0
A11: Depreciation | H11: =-'PPE-Note-4'!O51 -> 869984 | J11: 935314 | L11: =+#REF! -> #REF! | O11: =ROUND(J11,0) -> 935314
A12: Amortization of intangible assets | H12: =-'Con 5-18'!M7 -> 2907 | J12: 4361 | L12: 0
A13: (Gain) on disposal of property and equipment | H13: 0 | J13: 0 | L13: 0
A14: Provision for gratuity | H14: 0 | J14: 0 | L14: =-2898650-L23 -> 1959879 | O14: =ROUND(J14,0) -> 0
A15: Gain on disposal of property and equipment | H15: =+-'Con 5-18'!M193 -> 0 | J15: 0
A16: Financial charges | H16: ='Con 5-18'!M209 -> 17863 | J16: 365187 | L16: 248810 | O16: =ROUND(J16,0) -> 365187
A17: Operating surplus before working capital changes | H17: =SUM(H9:H16) -> 4760893 | J17: 1299047 | L17: =SUM(L8:L16) -> #REF! | O17: =SUM(O9:O16) -> 1294686 | Q17: -17602669
O18: =ROUND(J18,0) -> 0 | Q18: 196453
A19: Decrease in current assets | H19: =(+'Con BS'!N16-'Con BS'!L16)+('Con BS'!N12-'Con BS'!L12) -> #REF! | J19: 300198 | L19: 196453 | O19: =ROUND(J19,0) -> 300198 | Q19: 553358
A20: Increase in current liabilities | H20: =+'Con 5-18'!M72-'Con 5-18'!O72+'Con 5-18'!M73-'Con 5-18'!O73+('Con BS'!L26-'Con BS'!N26)+('Con BS'!L29-'Con BS'!N29) -> -414673 | J20: -683288 | L20: 553358 | O20: =ROUND(J20,0) -> -683288 | Q20: -248810
O21: =ROUND(J21,0) -> 0 | Q21: =+Q17+Q18+Q19+Q20 -> -17101668
A22: Taxes paid | H22: 0 | J22: 0
A23: Staff gratuity paid | H23: 0 | J23: 0 | L23: -4858529 | N23: -14596848
A24: Financial charges paid | H24: =-H16 -> -17863 | J24: -365187 | L24: =-L16 -> -248810 | O24: =ROUND(J24,0) -> -365187 | Q24: 11793034
A25: Taxes paid | H25: =+'Con I EX'!K27+'Con BS'!L31 -> -492254 | J25: 0
A27: Net cash inflow from operating activities | H27: =SUM(H17:H26) -> #REF! | J27: =SUM(J17:J26) -> 550770 | L27: =SUM(L17:L24) -> #REF! | O27: =SUM(O17:O24) -> 546409 | Q27: 6817000
O28: =ROUND(J28,0) -> 0 | Q28: =+Q21+Q24+Q27 -> 1508366
A29: CASH FLOW FROM INVESTING ACTIVITIES | O29: =ROUND(J29,0) -> 0
A30: Sale proceeds of property and equipment | H30: 0 | J30: 0
A31: Capital expenditure | H31: 0 | J31: 0 | L31: =+-#REF! -> #REF! | O31: =ROUND(J31,0) -> 0
A32: Additions in intangible assets | H32: =-'Con 5-18'!M6 -> 0 | J32: 0 | L32: 0
A33: Sale proceeds of property and equipment | H33: 0 | J33: 0 | L33: 0
A34: Net cash inflow from investing activities | H34: =SUM(H30) -> 0 | J34: 0
O35: =ROUND(J35,0) -> 0
A36: CASH FLOW FROM FINANCING ACTIVITIES | O36: =ROUND(J36,0) -> 0
A37: Capital expenditure inccured | H37: =-'PPE-Note-4'!O46 -> -25000 | J37: 0
A38: Short term liabilities - net | H38: =+'Con BS'!L32-'Con BS'!N32 -> #REF! | J38: 1000000 | L38: 11796035 | O38: =ROUND(J38,0) -> 1000000
A39: Lease liabilities - net | H39: 0 | J39: 0 | L39: 6850000 | O39: =ROUND(J39,0) -> 0
A40: Net cash (used in) / inflow from financing activities | H40: =+H38+H39+H37 -> #REF! | J40: 1000000 | L40: =SUM(L38) -> 11796035 | O40: =ROUND(J40,0) -> 1000000
O41: =ROUND(J41,0) -> 0
A42: Net increase in cash and cash equivalent | H42: =SUM(H27,H34,H40) -> #REF! | J42: 1550770 | L42: =SUM(L27,L34,L40) -> #REF! | O42: =SUM(O27,O34,O40) -> 1546409
O43: =ROUND(J43,0) -> 0
A44: Cash and cash equivalent at the beginning of the year | H44: =ROUND(+J46,0) -> 2725573 | J44: 1174803 | L44: 15627734 | O44: =ROUND(J44,0) -> 1174803
O45: =ROUND(J45,0) -> 0
A46: Cash and cash equivalent at the end of the year | G46: =+'Con BS'!K17 -> 8 | H46: =SUM(H42:H44) -> #REF! | J46: 2725573 | L46: =SUM(L42:L44) -> #REF! | N46: 19483597 | O46: =SUM(O42:O44) -> 2721212 | P46: 9704849 | S46: ='Con BS'!L17 -> #REF! | T46: =+H46-S46 -> #REF!
AF47: =+'Con BS'!N17 -> 2725572.5 | AH47: =+'Con BS'!#REF! -> #REF!
AF48: =+AF47-H46 -> #REF! | AH48: =+AH47-J46 -> #REF!
A49: ='Con BS'!A38 -> The annexed notes form an integral part of these financial statements. | N49: =J46-N46 -> -16758024 | P49: =L46-P46 -> #REF!
B69: Chief Executive Officer | G69: Director
F346: 9788859 | G346: 9788859 | I346: 9788859
C347: Short term Liabilities | F347: 39791015 | G347: 39791015 | I347: 39791015
L397: 0

Sheet Con 1-3 (New)
A1: PAKISTAN INSTITUTE OF LABOUR EDUCATION AND RESEARCH
A2: NOTES TO THE FINANCIAL STATEMENTS
A3: =CFS!A3 -> FOR THE YEAR ENDED JUNE 30, 2025
A6: 1. | B6: THE INSTITUTE AND ITS ACTIVITIES
B8: =+A6+0.1 -> 1.1 | C8: Pakistan Institute of Labour Education and Research (hereinafter referred to as the Institute or PILER), is a non-government and not for profit organization. It was established in the year 1982 and was registered under the Voluntary Social Welfare Agencies Ordinance 1961. The Institute has now incorporated as company limited by guarantee on 5th September 2012 under section 42 of the Companies Ordinance, 1984 (repealed by Companies Act, 2017). The Institute has been engaged in education, research, training and advocacy in the areas of labour rights and labour legislation, social justice and human development, regional solidarity and peace. The registered office of Pakistan Institute of Labour Education and Research is 24GF+3HG, Sector X-6 Sector X Gulshan-e-Maymar, Karachi.
M16: 2025 | O16: 2024 | Q16: =+"During the year, the company incurred a deficit after tax of Rs. "&M20&" million (2024: Rs. "&O20&" million) which resulted in negative fund balance of Rs. "&M21&" million (2024: Rs. "&O21&" million) as of the date of financial position." -> During the year, the company incurred a deficit after tax of Rs. -3.19 million (2024: Rs. 0.01 million) which resulted in negative fund balance of Rs. 27.23 million (2024: Rs. 30.43 million) as of the date of financial position.
B17: =+B8+0.1 -> 1.2 | C17: =CONCATENATE(Q16," ",Q17," ",Q18) -> During the year, the company incurred a deficit after tax of Rs. -3.19 million (2024: Rs. 0.01 million) which resulted in negative fund balance of Rs. 27.23 million (2024: Rs. 30.43 million) as of the date of financial position. However, the management believes that the adverse financial position will not affect the primary objectives of the company. Further, the major lender, who is also a related party due to common directorship, has also confirmed its financial commitment for future needs of the company. Accordingly, the company will be able to continue its operations in the foreseeable future. | Q17: However, the management believes that the adverse financial position will not affect the primary objectives of the company. Further, the major lender, who is also a related party due to common directorship, has also confirmed its financial commitment for future needs of the company.
M18: =+'Con I EX'!K29 -> 3191280 | O18: =+'Con I EX'!M29 -> -5815.4515 | Q18: Accordingly, the company will be able to continue its operations in the foreseeable future.
M19: =+'Con BS'!L23 -> -27233980 | O19: =+'Con BS'!N23 -> -30425260
M20: =ROUND(-M18/1000000, 2) -> -3.19 | O20: =ROUND(-O18/1000000, 2) -> 0.01
M21: =ROUND(-M19/1000000, 2) -> 27.23 | O21: =ROUND(-O19/1000000, 2) -> 30.43
A24: =+A6+1 -> 2 | B24: BASIS OF PREPARATION
B26: =+A24+0.1 -> 2.1 | C26: Statement of compliance
C28: These financial statements have been prepared in accordance with approved accounting standards, as applicable in Pakistan. Approved accounting standards comprise of Revised Accounting and Financial Reporting Standard for Small-sized Entities (AFRS for SSEs) and Accounting Standard for Not for Profit Organisations (NPOs) issued by Institute of Chartered Accountants of Pakistan (ICAP).
C33: These financial statements have been prepared in accordance with the accounting and reporting standards as applicable in Pakistan. The accounting and reporting standards as applicable in Pakistan comprise of:
C36: - | D36: Revised Accounting and Financial Reporting Standard for Small-sized Entities (AFRS for SSEs) issued by ICAP in 2015 and Accounting Standard for Not for Profit Organization (Accounting standards for NPOs) issued by the Institute of Chartered Accountants of Pakistan as notified under Companies Act, 2017; and
C40: - | D40: Provisions of and directives issued under the Companies Act, 2017.
C42: Where the provisions of and directives issued under the Companies Act, 2017 differ, the provisions of and directives issued under the Companies Act, 2017 have been followed.
B51: =+B26+0.1 -> 2.2 | C51: Critical accounting estimates and judgements
C53: The preparation of these financial statements is in conformity with approved accounting standards requires the use of certain critical accounting estimates. It also requires management to exercise its judgement in the process of applying the company's accounting policies.
C57: Estimates and judgements are continually evaluated and are based on historical experience and other factors, including expectations of future events that are believed to be reasonable under the circumstances.
C60: The estimates and underlying assumptions are reviewed on an ongoing basis. Revisions to accounting estimates are recognized in the period in which the estimate is revised if the revision affects only that period of the revision and future periods if the revision affects both current and future periods.
C64: Judgements are made by management in the application of approved accounting standards, that have significant effect on the financial statements and estimates with a significant risk of material adjustment in the next year.
A67: =+A24+1 -> 3 | B67: CHANGE IN ACCOUNTING POLICY
B69: During the year, the company transitioned its accounting policy from International Financial Reporting Standards (IFRS) to the Accounting and Financial Reporting framework for Small-Sized Entities (AFRS for SSE).
A78: =+A67+1 -> 4 | B78: MATERIAL ACCOUNTING POLICIES INFORMATION
B80: =+A78+0.1 -> 4.1 | C80: Property and equipment
C82: Property and equipment are stated at cost less accumulated depreciation.
C84: Whenever project agreement requires, capital items are expensed out in the period in which it was acquired.
C86: Depreciation is computed applying the straight line method at the rates given in note 5 to the financial statements. The residual values of the assets are considered zero while calculating depreciation.
C89: Depreciation on additions is charged from the month in which the asset is put to use and on disposals up to the month of disposal.
C92: Maintenance and normal repairs are charged to statement of income and expenditure as and when incurred. Major renewals and improvements are capitalized. Gain or loss on disposal of assets, if any, is included in statement of income and expenditure.
B96: =B80+0.1 -> 4.2 | C96: Intangibles
C98: An intangible asset is recognised if it is probable that the future economic benefits that are attributable to the asset will flow to the Company and that the cost of such asset can also be measured reliably.
C101: Generally, costs associated with developing or maintaining computer software programmes are recognised as an expense as incurred. However, costs that are directly associated with identifiable software and have probable economic benefits exceeding one year, are recognised as an intangible asset. Direct costs include the purchase cost of software and related overhead cost. Intangible assets acquired separately are measured on initial recognition at cost. Following initial recognition, intangible assets are carried at cost less accumulated amortisation and accumulated impairment losses, if any.
C108: Amortisation is charged to the statement of income and expenditure applying the reducing balance method, whereby, the cost of intangible asset is written off over its useful economic life. The amortization rate of the intangible assets are stated in note 6 to these financial statements. Full month's amortisation is charged in the month of addition, whereas, amortisation on disposals is charged up to the preceding month of derecognition.
C113: Gains or losses arising from derecognition of an intangible asset are measured as the difference between the net disposal proceeds and the carrying amount of the asset and are recognised in the statement of income and expenditure when the asset is derecognized.
B117: =+B96+0.1 -> 4.3 | C117: Trade and other payables
C119: Liabilities for trade and other payables are carried at cost which is the fair value of the consideration to be paid in the future for goods and services received, whether or not billed to the Company.
B122: =+B117+0.1 -> 4.4 | C122: Taxation
C124: Income tax expense comprises current, prior and deferred tax. Income tax expense is recognized in the statement of profit or loss except to the extent that it relates to item recognized directly in other comprehensive income in which case it is recognized in other comprehensive income.
C128: Current tax
C129: Provision for current tax is based on the taxable income for the year determined in accordance with the prevailing law for taxation of income. The charge for current tax is calculated using prevailing tax rates or tax rates expected to apply to the profit for the year if enacted.
C137: Prior tax
C138: The charge for prior tax includes adjustments where considered necessary, to provision for tax made in previous years arising from assessments framed during the year for such years.
B141: =+B122+0.1 -> 4.5 | C141: Revenue recognition
C143: Donations from sponsors / co - partners is recognized on receipt basis. Wherever amount received pertain to next project period the same is taken into its relevant period.
C146: Reimbursements on account of project activities from sponsors are based on agreed rates is recognized on receipt basis, which generally coincide with the billing and collection in the project period.
C149: Hostel activities and auditorium operations income are recognized on accrual basis which are generally charged to relevant project activities.
B152: =+B141+0.1 -> 4.6 | C152: Off - setting
C154: A financial asset and a financial liability is offset and the net amount is reported in the statement of financial position if the Company has a legally enforceable right to set-off the recognised amounts and intends either to settle on net basis or to realize the assets and settle the liability simultaneously.
B158: =+B152+0.1 -> 4.7 | C158: Cash and cash equivalents
C160: Cash and cash equivalents comprise of balances with banks and cash in hand (if any).
A162: =+A78+1 -> 5 | B162: RESTATEMENT
I163: As previously reported | J163: Restatements | K163: As restated
I166: ---------------------- Rupees ---------------------
B167: Impact on statement of financial position
B168: As at June 30, 2023
B170: Fund balance | I170: 267947 | J170: =L170-I170 -> -30687392 | L170: -30419445
B171: Short term liabilities | I171: 0 | J171: 39791015 | L171: =J171 -> 39791015
B172: Accrued and other liabilities | I172: 18892482 | J172: =(I172-L172)*-1 -> -9103623 | L172: 9788859
B174: Impact on statement of Income and Expenditure
B175: For the year ended June 30, 2023
B177: Other income | I177: 40579772 | J177: =(I177-L177)*-1 -> -39791015 | L177: 788757
B178: Taxation | I178: 9103623 | J178: =-I178 -> -9103623 | L178: 0 | N178: =+J178+J177 -> -48894638
B180: Impact on statement of Changes in Net Assets
B181: For the year ended June 30, 2023
B183: Surplus / (deficit) for the year ended June 30, 2023 | I183: 22288181 | J183: =I183-L183 -> 30687392 | L183: -8399210.8
B185: Impact on statement of Cash Flows
B186: For the year ended June 30, 2023
B188: Surplus / (deficit) before taxation | I188: 31391804 | J188: =(I188-L188)*-1 -> -39791015 | L188: -8399210.8
B189: Short term liabilities - net | I189: -36271802 | J189: =(I189-L189)*-1 -> 39791015 | L189: 3519213
A191: =+A162+0.1 -> 5.1 | B191: This restatement occurred due to error from management in the previous year, where the liability of Pakistan Labour Trust amounting to Rs. 39,791,015 was mistakenly written-off.

Sheet PPE-Note-4
A1: =+'Con 1-3 (New)'!A78+1 -> 5 | B1: PROPERTY AND EQUIPMENT
E3: Owned | N3: Right of use | O3: Total
E4: Leasehold land | F4: Building on leasehold land | G4: Generator | H4: Electrical installations | I4: Other equipments | J4: Furniture and fixture | K4: Computer equipment | L4: Vehicles | M4: Books | N4: Electrical installations
E7: ----------------------------------------------------------------------------------- Rupees --------------------------------------------------------------------------
B8: At June 30, 2016
B9: Cost | E9: 7171000 | F9: 22763815 | G9: 1244075 | H9: 1389085 | I9: 879714 | J9: 781677 | K9: 2761634 | L9: 3141295 | M9: 308439 | O9: =SUM(E9:M9) -> 40440734
B10: Accumulated depreciation | E10: 0 | F10: -5989140 | G10: -685771 | H10: -1146911 | I10: -688169 | J10: -705720 | K10: -2658747 | L10: -3141295 | M10: -308439 | O10: =(SUM(E10:M10)) -> -15324192
B12: Net book value | E12: =E9+E10 -> 7171000 | F12: =F9+F10 -> 16774675 | G12: =G9+G10 -> 558304 | H12: =H9+H10 -> 242174 | I12: =I9+I10 -> 191545 | J12: =J9+J10 -> 75957 | K12: =K9+K10 -> 102887 | L12: =L9+L10 -> 0 | M12: =M9+M10 -> 0 | O12: =O9+O10 -> 25116542
B14: Year ended June 30, 2017
B15: Opening net book value | E15: =E12 -> 7171000 | F15: =F12 -> 16774675 | G15: =G12 -> 558304 | H15: =H12 -> 242174 | I15: =I12 -> 191545 | J15: =J12 -> 75957 | K15: =K12 -> 102887 | L15: =L12 -> 0 | M15: =M12 -> 0 | N15: 0 | O15: =SUM(E15:M15) -> 25116542
B16: Additions (at cost) | E16: 0 | F16: 0 | G16: 0 | H16: 274200 | I16: 0 | J16: 86700 | K16: 5500 | L16: 0 | M16: 0 | N16: 0 | O16: =SUM(E16:N16) -> 366400
B17: Disposals
B18: Cost | E18: -5450000 | F18: 0 | G18: 0 | H18: 0 | I18: 0 | J18: 0 | K18: 0 | L18: 0 | M18: 0 | N18: 0 | O18: =SUM(E18:N18) -> -5450000
B19: Accumulated depreciation | E19: 0 | F19: 0 | G19: 0 | H19: 0 | I19: 0 | J19: 0 | K19: 0 | L19: 0 | M19: 0 | N19: 0 | O19: =SUM(E19:N19) -> 0
E20: =SUM(E18:E19) -> -5450000 | F20: =SUM(F18:F19) -> 0 | G20: =SUM(G18:G19) -> 0 | H20: =SUM(H18:H19) -> 0 | I20: =SUM(I18:I19) -> 0 | J20: =SUM(J18:J19) -> 0 | K20: =SUM(K18:K19) -> 0 | L20: =SUM(L18:L19) -> 0 | ... O20: =SUM(O18:O19) -> -5450000
B21: Depreciation charge for the year | E21: 0 | F21: -455276 | G21: -62204 | H21: -54435 | I21: -35696 | J21: -26920 | K21: -40420 | L21: 0 | M21: 0 | N21: 0 | O21: =SUM(E21:N21) -> -674951
B23: Net book value | E23: =+E15+E16+E20+E21 -> 1721000 | F23: =+F15+F16+F20+F21 -> 16319399 | G23: =+G15+G16+G20+G21 -> 496100 | H23: =+H15+H16+H20+H21 -> 461939 | I23: =+I15+I16+I20+I21 -> 155849 | J23: =+J15+J16+J20+J21 -> 135737 | K23: =+K15+K16+K20+K21 -> 67967 | L23: =+L15+L16+L20+L21 -> 0 | ... O23: =+O15+O16+O20+O21 -> 19357991
B25: At June 30, 2020
B26: Cost | E26: 1721000 | F26: 22763815 | G26: 1244075 | H26: 1789708 | I26: 911914 | J26: 868377 | K26: 2767134 | L26: 2534605 | M26: 308439 | N26: 3155750 | O26: =SUM(E26:N26) -> 38064817
B27: Accumulated depreciation | E27: 0 | F27: -7810244 | G27: -934587 | H27: -1434256 | I27: -806290 | J27: -785920 | K27: -2767134 | L27: -1915760 | M27: -308439 | N27: -858537 | O27: =SUM(E27:N27) -> -17621167
B28: Net book value | E28: =E26+E27 -> 1721000 | F28: =F26+F27 -> 14953571 | G28: =G26+G27 -> 309488 | H28: =H26+H27 -> 355452 | I28: =I26+I27 -> 105624 | J28: =J26+J27 -> 82457 | K28: =K26+K27 -> 0 | L28: =L26+L27 -> 618845 | ... O28: =O26+O27 -> 20443650
B30: Year ended June 30, 2024
B31: Opening net book value | E31: 1721000 | F31: 13587743 | G31: 122876 | H31: 171296 | I31: 46163 | J31: 40695 | K31: 35122 | L31: 0 | M31: 0 | N31: 1350488 | O31: 17075383
B32: Additions (at cost) | E32: 0 | F32: 0 | G32: 0 | H32: 0 | I32: 0 | J32: 0 | K32: 0 | L32: 0 | M32: 0 | N32: 0 | O32: 0
B33: Disposals | E33: 0 | F33: 0 | G33: 0 | H33: 0 | I33: 0 | J33: 0 | K33: 0 | L33: 0 | M33: 0 | N33: 0 | O33: 0
B34: Depreciation charge for the year | E34: 0 | F34: -455276 | G34: -62204 | H34: -41558 | I34: -15659 | J34: -9920 | K34: -35122 | L34: 0 | M34: 0 | N34: -315575 | O34: -935314
B36: Net book value | E36: 1721000 | F36: 13132467 | G36: 60672 | H36: 129738 | I36: 30504 | J36: 30775 | K36: 0 | L36: 0 | M36: 0 | N36: 1034913 | O36: 16140069
B38: At June 30, 2024
B39: Cost | E39: 1721000 | F39: 22763815 | G39: 1244075 | H39: 1789708 | I39: 911914 | J39: 868377 | K39: 2903533 | L39: 1108605 | M39: 308439 | N39: 3155750 | O39: 36775216
B40: Accumulated depreciation | E40: 0 | F40: -9631348 | G40: -1183403 | H40: -1659970 | I40: -881410 | J40: -837602 | K40: -2903533 | L40: -1108605 | M40: -308439 | N40: -2120837 | O40: -20635147
B42: Net book value | E42: 1721000 | F42: 13132467 | G42: 60672 | H42: 129738 | I42: 30504 | J42: 30775 | K42: 0 | L42: 0 | M42: 0 | N42: 1034913 | O42: 16140069
B44: Year ended June 30, 2025
B45: Opening net book value | E45: =E42 -> 1721000 | F45: =F42 -> 13132467 | G45: =G42 -> 60672 | H45: =H42 -> 129738 | I45: =I42 -> 30504 | J45: =J42 -> 30775 | K45: =K42 -> 0 | L45: =L42 -> 0 | ... N45: =N42 -> 1034913 | O45: =+SUM(E45:N45) -> 16140069
B46: Additions (at cost) | E46: 0 | F46: 0 | G46: 0 | H46: 25000 | I46: 0 | J46: 0 | L46: 0 | M46: 0 | N46: 0 | O46: =+SUM(E46:N46) -> 25000
B47: Transfer
B48: Cost | E48: 0 | F48: 0 | G48: 0 | H48: =-N48 -> 3155750 | I48: 0 | J48: 0 | K48: 0 | L48: 0 | M48: 0 | N48: -3155750 | O48: =+SUM(E48:N48) -> 0
B49: Accumulated depreciation | E49: 0 | F49: 0 | G49: 0 | H49: =-N49 -> -2120837 | I49: 0 | J49: 0 | K49: 0 | L49: 0 | M49: 0 | N49: 2120837 | O49: =+SUM(E49:N49) -> 0
E50: =SUM(E48:E49) -> 0 | F50: =SUM(F48:F49) -> 0 | G50: =SUM(G48:G49) -> 0 | H50: =SUM(H48:H49) -> 1034913 | I50: =SUM(I48:I49) -> 0 | J50: =SUM(J48:J49) -> 0 | K50: =SUM(K48:K49) -> 0 | L50: =SUM(L48:L49) -> 0 | ... N50: =SUM(N48:N49) -> -1034913 | O50: =+SUM(E50:N50) -> 0
B51: Depreciation charge for the year | E51: 0 | F51: -455276 | G51: -42323 | H51: =-40062-315575 -> -355637 | I51: -7068 | J51: -9680 | L51: 0 | M51: 0 | N51: 0 | O51: =+SUM(E51:N51) -> -869984
B53: Net book value | E53: =+E45+E46+E50+E51 -> 1721000 | F53: =+F45+F46+F50+F51 -> 12677191 | G53: =+G45+G46+G50+G51 -> 18349 | H53: =+H45+H46+H50+H51 -> 834014 | I53: =+I45+I46+I50+I51 -> 23436 | J53: =+J45+J46+J50+J51 -> 21095 | K53: =+K45+K46+K50+K51 -> 0 | L53: =+L45+L46+L50+L51 -> 0 | ... N53: =+N45+N46+N50+N51 -> 0 | O53: =+SUM(E53:N53) -> 15295085
B55: At June 30, 2025
B56: Cost | E56: =+E39+E46+E48 -> 1721000 | F56: =+F39+F46+F48 -> 22763815 | G56: =+G39+G46+G48 -> 1244075 | H56: =+H39+H46+H48 -> 4970458 | I56: =+I39+I46+I48 -> 911914 | J56: =+J39+J46+J48 -> 868377 | K56: =+K39+K46+K48 -> 2903533 | L56: =+L39+L46+L48 -> 1108605 | M56: =+M39+M46+M48 -> 308439 | N56: 0 | O56: =SUM(E56:N56) -> 36800216
B57: Accumulated depreciation | E57: =+E40+E49+E51 -> 0 | F57: =+F40+F49+F51 -> -10086624 | G57: =+G40+G49+G51 -> -1225726 | H57: =+H40+H49+H51 -> -4136444 | I57: =+I40+I49+I51 -> -888478 | J57: =+J40+J49+J51 -> -847282 | K57: =+K40+K49+K51 -> -2903533 | L57: =+L40+L49+L51 -> -1108605 | ... N57: =+N40+N49+N51 -> 0 | O57: =SUM(E57:N57) -> -21505131
B59: Net book value | E59: =E56+E57 -> 1721000 | F59: =F56+F57 -> 12677191 | G59: =G56+G57 -> 18349 | H59: =H56+H57 -> 834014 | I59: =I56+I57 -> 23436 | J59: =J56+J57 -> 21095 | K59: =K56+K57 -> 0 | L59: =L56+L57 -> 0 | ... O59: =O56+O57 -> 15295085
E63: Leasehold Land | F63: Building on Leasehold Land | G63: Generator | H63: Electrical Installations | I63: Other Equipments | J63: Furniture and Fixture | K63: Computer Equipment | L63: Vehicles | M63: Books | O63: Total 2017
E66: ----------------------------------------------------------------------------------- Rupees --------------------------------------------------------------------------
B67: Cost
B68: As at July 01, 2016 | E68: 7171000 | F68: 22763815 | G68: 1244075 | H68: 1389085 | I68: 879714 | J68: 781677 | K68: 2761634 | L68: 3141295 | M68: 308439 | O68: =SUM(E68:M68) -> 40440734
B69: Additions | E69: 0 | F69: 0 | G69: 0 | H69: =214200+60000 -> 274200 | I69: 0 | J69: 86700 | K69: 5500 | L69: 0 | M69: 0 | O69: =SUM(E69:M69) -> 366400
B70: Deletions | E70: -5450000 | F70: 0 | G70: 0 | H70: 0 | I70: 0 | J70: 0 | K70: 0 | L70: 0 | M70: 0 | O70: =SUM(E70:M70) -> -5450000
B72: As at June 30, 2017 | E72: =SUM(E68:E70) -> 1721000 | F72: =SUM(F68:F70) -> 22763815 | G72: =SUM(G68:G70) -> 1244075 | H72: =SUM(H68:H70) -> 1663285 | I72: =SUM(I68:I70) -> 879714 | J72: =SUM(J68:J70) -> 868377 | K72: =SUM(K68:K70) -> 2767134 | L72: =SUM(L68:L70) -> 3141295 | M72: =SUM(M68:M70) -> 308439 | O72: =SUM(O68:O70) -> 35357134
B74: Depreciation
B75: As at July 01, 2016 | E75: 0 | F75: =+#REF! -> #REF! | G75: =+#REF! -> #REF! | H75: =+#REF! -> #REF! | I75: =+#REF! -> #REF! | J75: =+#REF! -> #REF! | K75: =+#REF! -> #REF! | L75: =+#REF! -> #REF! | M75: =+#REF! -> #REF! | O75: =SUM(E75:M75) -> #REF!
B76: On additions | E76: 0 | F76: 0 | G76: 0 | H76: =10998+2668 -> 13666 | I76: 0 | J76: 7577 | K76: 1288 | L76: 0 | M76: 0 | O76: =SUM(E76:M76) -> 22531
B77: On opening balance | E77: 0 | F77: #REF! | G77: #REF! | H77: 40769 | I77: 35696 | J77: 19343 | K77: 39132 | L77: 0 | M77: 0 | O77: =SUM(E77:M77) -> #REF!
E78: 0 | F78: =SUM(F76:F77) -> #REF! | G78: =SUM(G76:G77) -> #REF! | H78: =SUM(H76:H77) -> 54435 | I78: =SUM(I76:I77) -> 35696 | J78: =SUM(J76:J77) -> 26920 | K78: =SUM(K76:K77) -> 40420 | L78: =SUM(L76:L77) -> 0 | M78: =SUM(M76:M77) -> 0 | O78: =SUM(O76:O77) -> #REF!
B80: As at June 30, 2017 | E80: =E75+E78 -> 0 | F80: =SUM(F75:F77) -> #REF! | G80: =SUM(G75:G77) -> #REF! | H80: =SUM(H75:H77) -> #REF! | I80: =SUM(I75:I77) -> #REF! | J80: =SUM(J75:J77) -> #REF! | K80: =SUM(K75:K77) -> #REF! | L80: =SUM(L75:L77) -> #REF! | M80: =SUM(M75:M77) -> #REF! | O80: =O75+O78 -> #REF!
B82: WDV as at June 30, 2017 | E82: =E72-E80 -> 1721000 | F82: =F72-F80 -> #REF! | G82: =G72-G80 -> #REF! | H82: =H72-H80 -> #REF! | I82: =I72-I80 -> #REF! | J82: =J72-J80 -> #REF! | K82: =K72-K80 -> #REF! | L82: =L72-L80 -> #REF! | M82: =M72-M80 -> #REF! | O82: =O72-O80 -> #REF!
B84: Rate of depreciation (%) | F84: 0.02 | G84: 0.05 | H84: 0.1 | I84: 0.1 | J84: 0.1 | K84: 0.33 | L84: 0.2 | M84: 0.15 | N84: 0.1
B86: Cost
B87: As at July 01, 2018 | E87: =+E71 -> 0 | F87: =+F71 -> 0 | G87: =+G71 -> 0 | H87: =+H71 -> 0 | I87: =+I71 -> 0 | J87: =+J71 -> 0 | K87: =+K71 -> 0 | L87: =+L71 -> 0 | M87: =+M71 -> 0 | N87: =SUM(E87:M87) -> 0
B88: Additions | E88: 0 | F88: 0 | G88: 0 | H88: 0 | I88: 32200 | J88: 0 | K88: 0 | M88: 0 | N88: =SUM(E88:M88) -> 32200
B89: Deletions | F89: 0 | G89: 0 | H89: 0 | I89: 0 | J89: 0 | K89: 0 | M89: 0 | N89: =SUM(E89:M89) -> 0
B91: As at June 30, 2019 | E91: =SUM(E87:E89) -> 0 | F91: =SUM(F87:F89) -> 0 | G91: =SUM(G87:G89) -> 0 | H91: =SUM(H87:H89) -> 0 | I91: =SUM(I87:I89) -> 32200 | J91: =SUM(J87:J89) -> 0 | K91: =SUM(K87:K89) -> 0 | L91: =SUM(L87:L89) -> 0 | ... N91: =SUM(N87:N89) -> 32200
B93: Depreciation
B94: As at July 01, 2018 | E94: =+E80 -> 0 | F94: =+F80 -> #REF! | G94: =+G80 -> #REF! | H94: =+H80 -> #REF! | I94: =+I80 -> #REF! | J94: =+J80 -> #REF! | K94: =+K80 -> #REF! | L94: =+L80 -> #REF! | M94: =+M80 -> #REF! | N94: =SUM(E94:M94) -> #REF!
B95: On additions | I95: 1342 | N95: =SUM(E95:M95) -> 1342
B96: On deletion | N96: =SUM(E96:M96) -> 0
B97: On opening balance | E97: 0 | F97: 455276 | G97: 62204 | H97: 392729 | I97: 27096 | J97: 21108 | K97: 21409 | L97: 285200 | M97: 0 | N97: =SUM(E97:M97) -> 1265022
E98: =SUM(E95:E97) -> 0 | F98: =SUM(F95:F97) -> 455276 | G98: =SUM(G95:G97) -> 62204 | H98: =SUM(H95:H97) -> 392729 | I98: =SUM(I95:I97) -> 28438 | J98: =SUM(J95:J97) -> 21108 | K98: =SUM(K95:K97) -> 21409 | L98: =SUM(L95:L97) -> 285200 | ... N98: =SUM(N95:N97) -> 1266364
B100: As at June 30, 2019 | E100: =E94+E98 -> 0 | F100: =F94+F98 -> #REF! | G100: =G94+G98 -> #REF! | H100: =H94+H98 -> #REF! | I100: =I94+I98 -> #REF! | J100: =J94+J98 -> #REF! | K100: =K94+K98 -> #REF! | L100: =L94+L98 -> #REF! | ... N100: =N94+N98 -> #REF!
B102: WDV as at June 30, 2019 | E102: =+E91-E100 -> 0 | F102: =+F91-F100 -> #REF! | G102: =+G91-G100 -> #REF! | H102: =+H91-H100 -> #REF! | I102: =+I91-I100 -> #REF! | J102: =+J91-J100 -> #REF! | K102: =+K91-K100 -> #REF! | L102: =+L91-L100 -> #REF! | M102: =+M91-M100 -> #REF! | N102: =N91-N100 -> #REF!
B104: Rate of depreciation (%) | F104: 0.02 | G104: 0.05 | H104: 0.1 | I104: 0.1 | J104: 0.1 | K104: 0.33 | L104: 0.2 | M104: 0.15 | N104: 0.1
B110: Opening Balance July-2025
B111: Opening net book value | E111: 1721000 | F111: 12677191 | G111: 18349 | H111: 834014 | I111: 23436 | J111: 21095 | K111: 0 | L111: 0 | M111: 0 | N111: =N50 -> -1034913 | O111: =SUM(E111:N111) -> 14260172
B112: Additions (at cost) | E112: 0 | F112: 0 | G112: 0 | I112: 0 | J112: 0 | L112: 0 | M112: 0 | N112: 0 | O112: =SUM(E112:N112) -> 0
B113: Transfer
B114: Depreciation charge for the year | E114: 0 | F114: -455276 | G114: -18349 | H114: =-42562 -> -42562 | I114: -23436 | J114: -1093 | L114: 0 | M114: 0 | N114: -315575 | O114: =+SUM(E114:N114) -> -856291
B116: Net book value as on June-2026 | E116: =+E111+E112-E114 -> 1721000 | F116: =+F111+F112+F114 -> 12221915 | G116: =+G111+G112+G114 -> 0 | H116: =+H111+H112+H114 -> 791452 | I116: =+I111+I112+I114 -> 0 | J116: =+J111+J112+J114 -> 20002 | K116: =+K111+K112+K114 -> 0 | L116: =+L111+L112+L114 -> 0 | M116: =+M111+M112+M114 -> 0 | N116: =N111-N114 -> -719338 | O116: =+SUM(E116:N116) -> 14035031
B119: At June 30, 2026
B120: Cost | E120: 1721000 | F120: 22763815 | G120: 1244075 | H120: 4970458 | I120: 911914 | J120: 868377 | K120: 2903533 | L120: 1108605 | M120: 308439 | N120: 3155750 | O120: =SUM(E120:N120) -> 39955966
B121: Accumulated depreciation | E121: =+E106+E114 -> 0 | F121: =+F57+F106+F114 -> -10541900 | G121: =+G57+G106+G114 -> -1244075 | H121: =+H57+H106+H114 -> -4179006 | I121: =+I57+I106+I114 -> -911914 | J121: =+J57+J106+J114 -> -848375 | K121: =+K57+K106+K114 -> -2903533 | L121: =+L57+L106+L114 -> -1108605 | M121: =+M57+M106+M114 -> -308439 | N121: =N49-N114 -> 2436412 | O121: =SUM(E121:N121) -> -19609435
B123: Net book value | E123: =E120+E121 -> 1721000 | F123: =F120+F121 -> 12221915 | G123: =G120+G121 -> 0 | H123: =H120+H121 -> 791452 | I123: =I120+I121 -> 0 | J123: =J120+J121 -> 20002 | K123: =K120+K121 -> 0 | L123: =L120+L121 -> 0 | ... O123: =O120+O121 -> 20346531
B125: Rate of depreciation (%) | F125: 0.02 | G125: 0.05 | H125: 0.1 | I125: 0.1 | J125: 0.1 | K125: 0.33 | L125: 0.2 | M125: 0.15 | N125: 0.1
F129: 9788859 | G129: 9788859 | I129: 9788859
C130: Short term Liabilities | F130: 39791015 | G130: 39791015 | I130: 39791015
L180: 0

Sheet Con 5-18
K1: 2026 | M1: 2025 | O1: 2024 | P1: 2017
A2: =+'PPE-Note-4'!A1+1 -> 6 | B2: INTANGIBLE ASSETS | I2: Note | K2: Rupees | M2: Rupees | O2: Rupees | P2: Rupees
B4: Net carrying value basis
B5: Opening net book value | K5: 5815 | M5: =O9 -> 8722 | O5: 13083 | P5: 0
B6: Add: | C6: Additions during the year | M6: 0 | O6: 0 | P6: 170118
B7: Less: | C7: Amortization for the year | K7: -2907 | M7: -2907 | O7: -4361 | P7: -37800
B9: Closing net book value | K9: =K5+K7 -> 2908 | M9: =M5+M6+M7 -> 5815 | O9: 8722 | P9: =P5+P6+P7 -> 132318
B11: Gross carrying value
B12: Cost | K12: 460096 | M12: =+O12+M6 -> 460096 | O12: 460096 | P12: 386398 | AB12: 797386
B13: Accumulated amortization | K13: =+K7+M13 -> -457188 | M13: =+O13+M7 -> -454281 | O13: -451374 | P13: -254080 | AB13: 566700
B15: Net book value | K15: =K12+K13 -> 2908 | M15: =M12+M13 -> 5815 | O15: 8722 | P15: =P12+P13 -> 132318
B17: Amortization rate | K17: 0.3333 | M17: 0.3333 | O17: 0.3333 | P17: 3
B19: INTANGIBLES ASSETS | R19: Rupees | T19: Rupees
B21: Cost | N21: #REF! | P21: #REF! | R21: #REF! | T21: 216280 | V21: =+T21/3 -> 72093.333
B22: Accumulated amortisation | K22: 5.1 | N22: #REF! | P22: #REF! | R22: #REF! | T22: -216280 | V22: =+V21*2 -> 144186.67 | W22: =+#REF! -> #REF!
V23: =+V21+V22 -> 216280
N24: =SUM(N21:N22) -> #REF! | P24: =SUM(P21:P22) -> #REF! | R24: =SUM(R21:R22) -> #REF! | T24: =SUM(T21:T22) -> 0 | W24: =+W22*3 -> #REF!
B25: 5.1 | C25: Computer software amortized at 3 years.
A26: =+A2+1 -> 7 | B26: INVESTMENTS (Held to maturity)
B28: Investment in term deposit receipt | K28: =+B32 -> 7.1 | M28: 0 | O28: 0 | P28: #REF! | R28: #REF! | T28: 6850000
P30: =SUM(P28:P28) -> #REF! | R30: =SUM(R28:R28) -> #REF! | T30: =SUM(T28:T28) -> 6850000
B32: =+A26+0.1 -> 7.1 | C32: Investment represents term deposit receipt of Bank Al-Habib for a period of one year at fixed rate of 5.8% per annum.
M35: 2020 | O35: 2019 | P35: 2017 | R35: 2016 | T35: 2015
A36: =+A2+1 -> 7 | B36: ADVANCES, DEPOSITS AND OTHER RECEIVABLES | P36: Rupees | R36: Rupees | T36: Rupees
B38: Staff loan | M38: =ROUND(GETPIVOTDATA("Sum of Amount",'Pivot 2025'!$A$3,"FSL1","Balance Sheet","FSL2","Current Assets","FSL3","Loans, Advances, Deposits, Prepayments And Receivables","FSL 4","Staff Loan"),0) -> #REF! | O38: 0 | P38: #REF! | R38: #REF! | T38: 1474046
B39: Advance against activities | M39: =ROUND(GETPIVOTDATA("Sum of Amount",'Pivot 2025'!$A$3,"FSL1","Balance Sheet","FSL2","Current Assets","FSL3","Loans, Advances, Deposits, Prepayments And Receivables","FSL 4","Advance Against Activities"),0) -> #REF! | O39: 602497 | P39: 699641 | R39: #REF! | T39: 3020380 | AA39: =M47-M39 -> #REF!
B40: Advance against salary | M40: =ROUND(GETPIVOTDATA("Sum of Amount",'Pivot 2025'!$A$3,"FSL1","Balance Sheet","FSL2","Current Assets","FSL3","Loans, Advances, Deposits, Prepayments And Receivables","FSL 4","Advance Against Salaries"),0) -> #REF! | O40: 30000
B41: Advance tax | M41: 0 | O41: 0
B42: Security deposit | M42: =ROUND(GETPIVOTDATA("Sum of Amount",'Pivot 2025'!$A$3,"FSL1","Balance Sheet","FSL2","Current Assets","FSL3","Loans, Advances, Deposits, Prepayments And Receivables","FSL 4","Security Depopsit"),0) -> #REF! | O42: 119700 | P42: #REF! | R42: #REF! | T42: 91500
B43: Prepaid insurance | M43: =ROUND(GETPIVOTDATA("Sum of Amount",'Pivot 2025'!$A$3,"FSL1","Balance Sheet","FSL2","Current Assets","FSL3","Loans, Advances, Deposits, Prepayments And Receivables","FSL 4","Prepaid Insurance"),0) -> #REF! | O43: 0 | P43: #REF! | R43: 0 | T43: 13375
B44: Prepayments | M44: 0 | O44: 0 | P44: #REF! | R44: #REF!
B45: Other receivables | M45: =ROUND(GETPIVOTDATA("Sum of Amount",'Pivot 2025'!$A$3,"FSL1","Balance Sheet","FSL2","Current Assets","FSL3","Loans, Advances, Deposits, Prepayments And Receivables","FSL 4","Other Receivables")+GETPIVOTDATA("Sum of Amount",'Pivot 2025'!$A$3,"FSL1","Balance Sheet","FSL2","Current Assets","FSL3","Loans, Advances, Deposits, Prepayments And Receivables","FSL 4","Others Receivable"),0) -> #REF! | O45: 958390 | P45: 746204 | R45: #REF! | T45: 1016122.8 | W45: =+#REF!-#REF! -> #REF! | AA45: =O45-M45 -> #REF!
M47: =SUM(M38:M45) -> #REF! | O47: =SUM(O38:O46) -> 1710587 | P47: =SUM(P38:P46) -> #REF! | R47: =SUM(R38:R46) -> #REF! | T47: =#REF!+T42 -> #REF! | W47: =R47-T47 -> #REF! | X47: =#REF!-#REF! -> #REF!
A49: =A36+1 -> 8 | B49: BANK BALANCES
B51: Current accounts | M51: =ROUND(GETPIVOTDATA("Sum of Amount",'Pivot 2025'!$A$3,"FSL1","Balance Sheet","FSL2","Current Assets","FSL3","Cash And Bank Balances","FSL 4","Cash With Banks In Current/Pls Accounts"),0) -> #REF! | O51: 2707493 | P51: 16766572 | R51: #REF!
B52: Savings account | M52: 0 | O52: 18079.549 | P52: 6246 | R52: 0 | AB52: =6262+7180 -> 13442
M54: =+M51+M52 -> #REF! | O54: =+O51+O52 -> 2725572.5 | P54: =+P51+P52 -> 16772818 | R54: =+R51+R52 -> #REF! | T54: =#REF!+#REF! -> #REF! | AB54: 2713755
A70: =+A49+1 -> 9 | B70: ACCRUED AND OTHER LIABILITIES | P70: Rupees | T70: Rupees
B72: Accrued expenses | M72: =-ROUND(GETPIVOTDATA("Sum of Amount",'Pivot 2025'!$A$3,"FSL1","Balance Sheet","FSL2","Current Liabilities","FSL3","Accrued, Payables And Other Liabilities","FSL 4","Accrued Expenses"),0) -> 6101653 | O72: 6523065 | P72: 1944840 | R72: #REF! | T72: 1166169 | AA72: =O72-M72 -> 421412
B73: Other liabilities | M73: =-ROUND(GETPIVOTDATA("Sum of Amount",'Pivot 2025'!$A$3,"FSL1","Balance Sheet","FSL2","Current Liabilities","FSL3","Accrued, Payables And Other Liabilities","FSL 4","Other Liabilities"),0)+510000 -> 3702870 | O73: =3186131+510000 -> 3696131 | P73: #REF! | R73: #REF! | T73: 45225 | AA73: =O73-M73 -> -6739
B74: Provision for taxation | M74: =GETPIVOTDATA("Sum of Debit5",'Pivot 2025'!$A$3,"FSL1","Balance Sheet","FSL2","Current Liabilities","FSL3","Accrued, Payables And Other Liabilities","FSL 4","Provision for taxation") -> 0 | O74: 0 | AA74: =O74-M74 -> 0 | AD74: 9103623
M76: =SUM(M72:M75) -> 9804523 | O76: =SUM(O72:O75) -> 10219196 | P76: =SUM(P72:P75) -> #REF! | R76: =SUM(R72:R75) -> #REF! | T76: =SUM(T72:T75) -> 1211394 | W76: =R76-T76 -> #REF!
A78: =+A70+1 -> 10 | B78: SHORT TERM LIABILITIES
B80: Pakistan Labour Trust | I80: =+B84 -> 10.1 | M80: =-GETPIVOTDATA("Sum of Amount",'Pivot 2025'!$A$3,"FSL1","Balance Sheet","FSL2","Current Liabilities","FSL3","Short Term Liabilities","FSL 4","Pakistan Labour Trust") -> #REF! | O80: 40791015 | P80: 27543494 | R80: #REF! | T80: 8838057.8 | W80: =R80-T80 -> #REF!
M82: =SUM(M80:M81) -> #REF! | O82: =SUM(O80:O81) -> 40791015 | P82: =SUM(P80:P81) -> 27543494 | R82: =SUM(R80:R81) -> #REF! | T82: =SUM(T80:T80) -> 8838057.8
B84: =A78+0.1 -> 10.1 | C84: This represents balance of funds borrowed by PILER from Pakistan Labour Trust.
X90: 126.63
X91: 121.3
K106: 2026 | M106: 2025 | O106: 2024
A107: =+A78+1 -> 11 | B107: OPERATING COST | I107: Note | K107: Rupees | M107: Rupees | O107: Rupees | P107: Rupees | R107: Rupees | T107: Rupees | X107: 115.3
X108: 118.5
B109: Project activities / output | X109: =SUM(X90:X108) -> 481.73 | Y109: =X109/12 -> 40.144167 | AD109: GLJ-ILRF: Women Leadership committee meeting | AE109: 417356 | AF109: 0 | AG109: 417356
B110: PILER program activities : Peace / Labor related seminars & Conferences activities | AD110: GLJ-ILRF:OBS-National AFWA Convening(Sep-2023) | AE110: 464334 | AF110: 0 | AG110: 464334
M111: =ROUND(GETPIVOTDATA("Sum of Amount",'Pivot 2025'!$A$3,"FSL1","Profit and Loss","FSL2","Operating Costs","FSL3","Peace Seminar Activities")+GETPIVOTDATA("Sum of Amount",'Pivot 2025'!$A$3,"FSL1","Profit and Loss","FSL2","Operating Costs","FSL3","Piler Program Activities : Peace / Labor Related Seminars & Conferences Activities"),0) -> 2095879 | O111: 188000 | P111: 1085203 | R111: =SUM(#REF!) -> #REF! | T111: =SUM(#REF!) -> #REF! | U111: + | AA111: =176380+1919499 -> 2095879 | AD111: GLJ-ILRF:GDW-Lawyer-Legal Brief | AE111: 100000 | AF111: 0 | AG111: 100000
B112: Memorial programmes | M112: =ROUND(GETPIVOTDATA("Sum of Amount",'Pivot 2025'!$A$3,"FSL1","Profit and Loss","FSL2","Operating Costs","FSL3","Memorial Programmes"),0) -> 76100 | O112: 0 | P112: 0 | AD112: GLJ-ILRF : Field Coordinator | AE112: 1100000 | AF112: 0 | AG112: 1100000
B113: National Labour Council | M113: =ROUND(GETPIVOTDATA("Sum of Amount",'Pivot 2025'!$A$3,"FSL1","Profit and Loss","FSL2","Operating Costs","FSL3","National Labour Council."),0) -> 0 | O113: 0 | AD113: GLJ-ILRF : Wage struggle working group - 2 | AE113: 88433 | AF113: 0 | AG113: 88433
B114: Project: GLJ-ILRF: Women Leadership committee meeting | M114: =GETPIVOTDATA("Sum of Amount",'Pivot 2025'!$A$3,"FSL1","Profit and Loss","FSL2","Operating Costs","FSL3","GLJ-ILRF:Women Leadership committee meeting","FSL 4","GLJ-ILRF:Women Leadership committee meeting") -> 65000 | O114: 417356 | P114: 0
B115: Project: GLJ-ILRF: OBS-National AFWA Convening | M115: =+GETPIVOTDATA("Sum of Amount",'Pivot 2025'!$A$3,"FSL1","Profit and Loss","FSL2","Operating Costs","FSL3","GLJ-ILRF : AFWA National Convenings - 1") -> 54230 | O115: 464334 | P115: 0
B116: Project: GLJ-ILRF: GDW-Lawyer-Legal Brief | M116: =+GETPIVOTDATA("Sum of Amount",'Pivot 2025'!$A$3,"FSL1","Profit and Loss","FSL2","Operating Costs","FSL3","GLJ-ILRF:GDW-Lawyer-Legal Breif") -> 0 | O116: 100000
B117: Project: GLJ-ILRF: Consumption survey | M117: =GETPIVOTDATA("Sum of Amount",'Pivot 2025'!$A$3,"FSL1","Profit and Loss","FSL2","Operating Costs","FSL3","Glj-Ilrf: Consumption Survey")+GETPIVOTDATA("Sum of Amount",'Pivot 2025'!$A$3,"FSL1","Profit and Loss","FSL2","Operating Costs","FSL3","Glj-Ilrf:Meetings")+GETPIVOTDATA("Sum of Amount",'Pivot 2025'!$A$3,"FSL1","Profit and Loss","FSL2","Operating Costs","FSL3","Peace Seminar Activities") -> 1602706 | O117: 0
B118: Project: GLJ-ILRF : Field Coordinator | M118: =+GETPIVOTDATA("Sum of Amount",'Pivot 2025'!$A$3,"FSL1","Profit and Loss","FSL2","Operating Costs","FSL3","GLJ-ILRF : Field Cordinator") -> 1320000 | O118: 1100000
B119: Project: GLJ-ILRF : Wage struggle working group - 2 | M119: =+GETPIVOTDATA("Sum of Amount",'Pivot 2025'!$A$3,"FSL1","Profit and Loss","FSL2","Operating Costs","FSL3","GLJ-ILRF : Wage struggle working group - 2") -> 349175 | O119: 88433 | AD119: GLJ-ILRF : Wage struggle working group - 2 | AE119: 88433 | AF119: 0 | AG119: 88433
B120: Project: GRC-8.1.2 Advocacy material development and distribution | M120: =GETPIVOTDATA("Sum of Amount",'Pivot 2025'!$A$3,"FSL1","Profit and Loss","FSL2","Operating Costs","FSL3","GRC-H.1.2#Advocacy material development and distribution")+GETPIVOTDATA("Sum of Amount",'Pivot 2025'!$A$3,"FSL1","Profit and Loss","FSL2","Operating Costs","FSL3","GRC-Data Analyst-Quantitative")+GETPIVOTDATA("Sum of Amount",'Pivot 2025'!$A$3,"FSL1","Profit and Loss","FSL2","Operating Costs","FSL3","GRC- Project Management Cost","FSL 4","GRC- Project Management Cost") -> 1931001 | O120: 1396500 | AD120: GRC-8.1.2 # Advocacy material development and distribution | AE120: 1396500 | AF120: 0 | AG120: 1396500
B121: Project: GRC-8.1.3 Training workshops | M121: =+GETPIVOTDATA("Sum of Amount",'Pivot 2025'!$A$3,"FSL1","Profit and Loss","FSL2","Operating Costs","FSL3","GRC-8.1.3 # Training workshops ") -> 330784 | O121: 2229049
B122: Project: GRC-8.2.4 National travel for participants | M122: =+GETPIVOTDATA("Sum of Amount",'Pivot 2025'!$A$3,"FSL1","Profit and Loss","FSL2","Operating Costs","FSL3","GRC-8.2.4 # National travel for participants") -> 1161050 | O122: 22000 | AD122: GRC-8.1.3 # Training workshops | AE122: 2857940 | AF122: 0 | AG122: 2857940
B123: Project: GRC-8.2.5 Stationary & material | M123: =+GETPIVOTDATA("Sum of Amount",'Pivot 2025'!$A$3,"FSL1","Profit and Loss","FSL2","Operating Costs","FSL3","GRC-8.2.5 # Stationary & material")+GETPIVOTDATA("Sum of Amount",'Pivot 2025'!$A$3,"FSL1","Profit and Loss","FSL2","Operating Costs","FSL3","GLJ-ILRF : FTH Campaign","FSL 4","GLJ-ILRF : FTH Campaign")+GETPIVOTDATA("Sum of Amount",'Pivot 2025'!$A$3,"FSL1","Profit and Loss","FSL2","Operating Costs","FSL3","GLJ-ILRF : OBS-B.5.16-all program") -> 336440 | O123: 48590
B124: Project: GRC-Total Direct Costs | M124: =+GETPIVOTDATA("Sum of Amount",'Pivot 2025'!$A$3,"FSL1","Profit and Loss","FSL2","Operating Costs","FSL3","GRC-Total Direct Costs")+GETPIVOTDATA("Sum of Amount",'Pivot 2025'!$A$3,"FSL1","Profit and Loss","FSL2","Operating Costs","FSL3","GLJ-ILRF : FTH Campaign")+GETPIVOTDATA("Sum of Amount",'Pivot 2025'!$A$3,"FSL1","Profit and Loss","FSL2","Operating Costs","FSL3","GLJ-ILRF : OBS-B.5.16-all program") -> 425572 | O124: 1419458
B125: Project: Global Labor Justice - International Labor Rights Forum-AFW | M125: =ROUND(+GETPIVOTDATA("Sum of Amount",'Pivot 2025'!$A$3,"FSL1","Profit and Loss","FSL2","Operating Costs","FSL3","Glj-Ilrf: Consumption Survey")+GETPIVOTDATA("Sum of Amount",'Pivot 2025'!$A$3,"FSL1","Profit and Loss","FSL2","Operating Costs","FSL3","Glj-Ilrf: Translation Of Interview Guide In Urdu")+GETPIVOTDATA("Sum of Amount",'Pivot 2025'!$A$3,"FSL1","Profit and Loss","FSL2","Operating Costs","FSL3","Glj-Ilrf:Meetings")+GETPIVOTDATA("Sum of Amount",'Pivot 2025'!$A$3,"FSL1","Profit and Loss","FSL2","Operating Costs","FSL3","Ngo Overhead","FSL 4","Glj-Ilrf:"),0)+GETPIVOTDATA("Sum of Amount",'Pivot 2025'!$A$3,"FSL1","Profit and Loss","FSL2","Operating Costs","FSL3","GLJ-ILRF:Global event interpreter")+GETPIVOTDATA("Sum of Amount",'Pivot 2025'!$A$3,"FSL1","Profit and Loss","FSL2","Operating Costs","FSL3","GLJ-ILRF: JEL trainings & Natl seminars etc")+GETPIVOTDATA("Sum of Amount",'Pivot 2025'!$A$3,"FSL1","Profit and Loss","FSL2","Operating Costs","FSL3","GLJ-ILRF: GBVH campaign") -> 1426326 | O125: 48847
B126: Project: Global Rights Compliance | M126: =GETPIVOTDATA("Sum of Amount",'Pivot 2025'!$A$3,"FSL1","Profit and Loss","FSL2","Operating Costs","FSL3","GRC- Project Management Cost","FSL 4","GRC- Project Management Cost")+GETPIVOTDATA("Sum of Amount",'Pivot 2025'!$A$3,"FSL1","Profit and Loss","FSL2","Operating Costs","FSL3","GRC-B.1.1#EOBI Contribution")+GETPIVOTDATA("Sum of Amount",'Pivot 2025'!$A$3,"FSL1","Profit and Loss","FSL2","Operating Costs","FSL3","GRC-8.2.4 # Facilitators fee")+GETPIVOTDATA("Sum of Amount",'Pivot 2025'!$A$3,"FSL1","Profit and Loss","FSL2","Operating Costs","FSL3","GRC-8.2.1 # Venue, including food and drinks")+GETPIVOTDATA("Sum of Amount",'Pivot 2025'!$A$3,"FSL1","Profit and Loss","FSL2","Operating Costs","FSL3","GRC-8.2.3 # Accommodation for participants")+GETPIVOTDATA("Sum of Amount",'Pivot 2025'!$A$3,"FSL1","Profit and Loss","FSL2","Operating Costs","FSL3","GRC-8.1.3 # Training workshops ")+GETPIVOTDATA("Sum of Amount",'Pivot 2025'!$A$3,"FSL1","Profit and Loss","FSL2","Operating Costs","FSL3","GRC-Total Direct Costs")+1558 -> 4398349 | O126: 2691092.6
B127: Project: Impact of Covid-19 on Textile Workers | M127: 0 | O127: 0
B128: Project: Increased advocacy to reduce impact of COVID-19 on vulnerable workers in Pakistan | M128: 0 | O128: 0
B129: Project: GSP+ Platform | M129: 0 | O129: 0
B130: Project: Labour behind the label | M130: =GETPIVOTDATA("Sum of Amount",'Pivot 2025'!$A$3,"FSL1","Profit and Loss","FSL2","Operating Costs","FSL3","LBL#1-Surveyor Cost","FSL 4","LBL#1-Surveyor Cost")+GETPIVOTDATA("Sum of Amount",'Pivot 2025'!$A$3,"FSL1","Profit and Loss","FSL2","Operating Costs","FSL3","Software expense","FSL 4","Software expense") -> 572290 | O130: 0
B131: Project: American bar association | M131: =GETPIVOTDATA("Sum of Amount",'Pivot 2025'!$A$3,"FSL1","Profit and Loss","FSL2","Operating Costs","FSL3","ABA-2.1-(a)#Campaign Help Prevent Child-Ground transport for Staff")+GETPIVOTDATA("Sum of Amount",'Pivot 2025'!$A$3,"FSL1","Profit and Loss","FSL2","Operating Costs","FSL3","ABA-2.1-(e)#Campaign Help Prevent Child-Refreshment")+GETPIVOTDATA("Sum of Amount",'Pivot 2025'!$A$3,"FSL1","Profit and Loss","FSL2","Operating Costs","FSL3","ABA#Transport Expenses")+GETPIVOTDATA("Sum of Amount",'Pivot 2025'!$A$3,"FSL1","Profit and Loss","FSL2","Operating Costs","FSL3","ABA#Printing & Stationery Expenses")+GETPIVOTDATA("Sum of Amount",'Pivot 2025'!$A$3,"FSL1","Profit and Loss","FSL2","Operating Costs","FSL3","ABA#Food/Refreshment Expenses")+GETPIVOTDATA("Sum of Amount",'Pivot 2025'!$A$3,"FSL1","Profit and Loss","FSL2","Operating Costs","FSL3","ABA#1.1-Identify Law and Policy Proposals through Legal Mapping of Traffficking,Child Protection & L")+GETPIVOTDATA("Sum of Amount",'Pivot 2025'!$A$3,"FSL1","Profit and Loss","FSL2","Operating Costs","FSL3","ABA# Child safeguarding Policy by reviewing relevant laws & UN guiding principles")+GETPIVOTDATA("Sum of Amount",'Pivot 2025'!$A$3,"FSL1","Profit and Loss","FSL2","Operating Costs","FSL3","ABA# Child safeguarding Policy by reviewing relevant laws & UN guiding principles","FSL 4","ABA# Child safeguarding Policy by reviewing relevant laws & UN guiding principles")+GETPIVOTDATA("Sum of Amount",'Pivot 2025'!$A$3,"FSL1","Profit and Loss","FSL2","Operating Costs","FSL3","LBL#1-Surveyor Cost","FSL 4","LBL#1-Surveyor Cost") -> 797972 | O131: 0
K132: =ROUND(SUM(K110:L131),0) -> 0 | M132: =ROUND(SUM(M110:N131),0) -> 16942874 | O132: 10213660 | P132: =+#REF!+#REF!+#REF!+#REF!+#REF!+#REF!+P111+#REF!+#REF!+#REF!+#REF!+#REF!+#REF!+#REF!+#REF!+#REF!+#REF!+#REF!+#REF!+#REF!+#REF!+#REF!+#REF! -> #REF! | R132: =+#REF!+#REF!+#REF!+#REF!+#REF!+R111+#REF!+#REF!+#REF!+#REF!+#REF!+#REF!+#REF!+#REF!+#REF!+#REF!+#REF!+#REF!+#REF!+#REF!+#REF! -> #REF! | T132: =+#REF!+#REF!+#REF!+#REF!+#REF!+#REF!+T111+#REF!+#REF!+#REF!+#REF!+#REF!+#REF!+#REF!+#REF!+#REF!+#REF!+#REF!+#REF! -> #REF! | U132: 31628147 | V132: =U132-T132 -> #REF!
B133: Salary, wages and benefits: | AA133: =SUM(AA134:AA138) -> 5328329
B134: Research, education and training | M134: =ROUND(GETPIVOTDATA("Sum of Amount",'Pivot 2025'!$A$3,"FSL1","Profit and Loss","FSL2","Operating Costs","FSL3","Salary, Wages And Benefits")+GETPIVOTDATA("Sum of Amount",'Pivot 2025'!$A$3,"FSL1","Profit and Loss","FSL2","Operating Costs","FSL3","Staff Overtime"),0)+GETPIVOTDATA("Sum of Amount",'Pivot 2025'!$A$3,"FSL1","Profit and Loss","FSL2","Operating Costs","FSL3","Salary, Wages And Benefits:") -> 8343587 | O134: 5328329 | P134: 17530283 | R134: #REF! | T134: 15234820 | U134: =+R134-T134 -> #REF! | W134: Consolidation adjustment | AA134: 315120
B135: Staff welfare | M135: =ROUND(GETPIVOTDATA("Sum of Amount",'Pivot 2025'!$A$3,"FSL1","Profit and Loss","FSL2","Operating Costs","FSL3","Salary, Wages And Benefits: Staff Welfare"),0) -> 352519 | O135: 310928 | P135: 469217 | R135: #REF! | T135: 840096 | AA135: 4999709
K136: =SUM(K134:K135) -> 0 | M136: =SUM(M134:M135) -> 8696106 | O136: =SUM(O134:O135) -> 5639257 | P136: =SUM(P134:P135) -> 17999500 | R136: =SUM(R134:R135) -> #REF! | T136: =SUM(T134:T135) -> 16074916 | W136: balance transfer to PILER | Z136: =#REF! -> #REF! | AA136: 13500
X137: Staff cost
K138: =K136+K132 -> 0 | M138: =M136+M132 -> 25638980 | O138: =O136+O132 -> 15852917 | P138: =P136+P132 -> #REF! | R138: =R136+R132 -> #REF! | T138: =T136+T132 -> #REF! | W138: (Inter project transfer of funds eliminated)
A140: =A107+1 -> 12 | B140: ADMINISTRATIVE AND GENERAL EXPENSES | P140: Rupees | R140: Rupees | T140: Rupees
B142: Salary, wages and benefits | I142: =+B170 -> 12.1 | M142: =ROUND(GETPIVOTDATA("Sum of Amount",'Pivot 2025'!$A$3,"FSL1","Profit and Loss","FSL2","Administrative And General Expenses","FSL3","Salary, Wages And Benefits","FSL 4","Salary, Wages And Benefits"),0) -> 1991332 | O142: 1453502 | P142: 7749170 | R142: #REF! | T142: 19768945 | V142: =+R142+R136 -> #REF! | W142: =T136+T142 -> 35843861 | X142: =#REF! -> #REF!
B143: Electricity, gas and water | M143: =ROUND(GETPIVOTDATA("Sum of Amount",'Pivot 2025'!$A$3,"FSL1","Profit and Loss","FSL2","Administrative And General Expenses","FSL3","Electricity, Gas And Water","FSL 4","Electricity, Gas And Water"),0) -> 970951 | O143: 380573 | P143: #REF! | R143: #REF! | T143: 1281477 | V143: =+V142*W143 -> #REF! | W143: =+#REF!/W142 -> #REF!
B144: Telephone | M144: =ROUND(GETPIVOTDATA("Sum of Amount",'Pivot 2025'!$A$3,"FSL1","Profit and Loss","FSL2","Administrative And General Expenses","FSL3","Telephone","FSL 4","Telephone"),0) -> 211040 | O144: 29690 | P144: #REF! | R144: #REF! | T144: 590475 | W144: =R142-T142 -> #REF!
B145: Travelling, vehicle and generator fuel | M145: =ROUND(GETPIVOTDATA("Sum of Amount",'Pivot 2025'!$A$3,"FSL1","Profit and Loss","FSL2","Administrative And General Expenses","FSL3","Travelling, Vehicle And Generator Fuel","FSL 4","Travelling, Vehicle And Generator Fuel"),0) -> 509508 | O145: 595112 | P145: #REF! | R145: #REF! | T145: 3110163.9 | V145: 424219.79
B146: Vehicle insurance | M146: =ROUND(GETPIVOTDATA("Sum of Amount",'Pivot 2025'!$A$3,"FSL1","Profit and Loss","FSL2","Administrative And General Expenses","FSL3","Vehicle Insurance","FSL 4","Vehicle Insurance"),0) -> 1239 | O146: 2113 | P146: #REF! | R146: #REF! | T146: 218876
B147: Bedding and linen | M147: 0 | O147: 0 | P147: 0 | R147: #REF! | T147: 0
B148: Vehicle maintenance | M148: =ROUND(GETPIVOTDATA("Sum of Amount",'Pivot 2025'!$A$3,"FSL1","Profit and Loss","FSL2","Administrative And General Expenses","FSL3","Vehicle Maintenance","FSL 4","Vehicle Maintenance"),0) -> 149345 | O148: 122860 | P148: #REF! | R148: #REF! | T148: 389471
B149: Equipment repair and maintenance | M149: =ROUND(GETPIVOTDATA("Sum of Amount",'Pivot 2025'!$A$3,"FSL1","Profit and Loss","FSL2","Administrative And General Expenses","FSL3","Equipment Repair Maintenance","FSL 4","Equipment Repair Maintenance"),0) -> 901515 | O149: 97847 | P149: #REF! | R149: #REF! | T149: 266613
B150: Postage and internet | M150: =ROUND(GETPIVOTDATA("Sum of Amount",'Pivot 2025'!$A$3,"FSL1","Profit and Loss","FSL2","Administrative And General Expenses","FSL3","Postage And Internet","FSL 4","Postage And Internet"),0) -> 7540 | O150: 3030 | P150: #REF! | R150: #REF! | T150: 96507
B151: Legal and professional charges | M151: =ROUND(GETPIVOTDATA("Sum of Amount",'Pivot 2025'!$A$3,"FSL1","Profit and Loss","FSL2","Administrative And General Expenses","FSL3","Legal And Professional Charges","FSL 4","Legal And Professional Charges"),0) -> 397896 | O151: 222338 | P151: #REF! | R151: #REF! | T151: 292227
B152: Auditors' remuneration | I152: =+B173 -> 12.2 | M152: =+GETPIVOTDATA("Sum of Amount",'Pivot 2025'!$A$3,"FSL1","Profit and Loss","FSL2","Administrative And General Expenses","FSL3","Auditors' Remuneration") -> 432000 | O152: =+O181 -> 432000 | P152: #REF! | R152: #REF! | T152: 481000
B153: Consultancy charges | M153: 0 | O153: 0 | P153: #REF! | R153: #REF! | T153: 81000
B154: Stationery, photocopies and materials | M154: =ROUND(GETPIVOTDATA("Sum of Amount",'Pivot 2025'!$A$3,"FSL1","Profit and Loss","FSL2","Administrative And General Expenses","FSL3","Stationery, Photocopies And Materials","FSL 4","Stationery, Photocopies And Materials"),0) -> 216278 | O154: 26364 | P154: #REF! | R154: #REF! | T154: 267096.25
B155: Generator maintenance | M155: 0 | O155: 0 | P155: #REF! | R155: #REF! | T155: 121179
B156: General maintenance | M156: =ROUND(GETPIVOTDATA("Sum of Amount",'Pivot 2025'!$A$3,"FSL1","Profit and Loss","FSL2","Administrative And General Expenses","FSL3","General Maintenance","FSL 4","General Maintenance"),0)+GETPIVOTDATA("Sum of Amount",'Pivot 2025'!$A$3,"FSL1","Profit and Loss","FSL2","Administrative And General Expenses","FSL3","Administrative And General Expenses") -> 376210 | O156: 20469 | P156: #REF! | R156: #REF! | T156: 62751
B157: Miscellaneous | M157: =ROUND(GETPIVOTDATA("Sum of Amount",'Pivot 2025'!$A$3,"FSL1","Profit and Loss","FSL2","Administrative And General Expenses","FSL3","Miscellaneous"),0) -> 568067 | O157: =140374-32000 -> 108374 | P157: #REF! | R157: #REF! | T157: 623636
B158: Membership and subscription | M158: 0 | O158: 0 | P158: #REF! | R158: #REF! | T158: 286032
B159: SECP registration | M159: 0 | O159: 0 | P159: 31785 | R159: #REF! | T159: 2705
...

Sheet Note 16
A1: 16 | B1: FINANCIAL ASSETS AND LIABILITIES
E3: Markup bearing | H3: Non-Markup bearing | K3: 2015 | M3: 2014
E4: Maturity | F4: Maturity | G4: Sub-Total | H4: Closing | I4: Maturity | J4: Sub-Total
E5: upto one | F5: after one | H5: upto one | I5: after one
E6: year | F6: year | H6: year | I6: year | K6: Total | M6: Total
E7: ---------------------------------------------------------Rupees ------------------------------------------------------------
B9: Financial Assets
B10: Long term investments | E10: 6000000 | F10: 850000 | G10: =SUM(E10:F10) -> 6850000 | H10: 0 | I10: 0 | J10: =SUM(H10:I10) -> 0 | K10: =(G10+J10) -> 6850000 | M10: 6850000
B11: Advances and other receivables | E11: 0 | F11: =SUM(E11:E11) -> 0 | G11: =SUM(E11:F11) -> 0 | H11: 5523923.8 | I11: 0 | J11: =SUM(H11:I11) -> 5523923.8 | K11: =(G11+J11) -> 5523923.8 | M11: 6162964.8
B12: Cash and bank balances | E12: 0 | F12: =SUM(E12:E12) -> 0 | G12: =SUM(E12:F12) -> 0 | H12: 16227738 | I12: 0 | J12: =SUM(H12:I12) -> 16227738 | K12: =(G12+J12) -> 16227738 | M12: 16227738
E14: =+SUM(E10:E13) -> 6000000 | F14: =+SUM(F10:F13) -> 850000 | G14: =+SUM(G10:G13) -> 6850000 | H14: =+SUM(H10:H13) -> 21751662 | I14: =+SUM(I10:I13) -> 0 | J14: =+J10+J11+J12 -> 21751662 | K14: =SUM(K10:K12) -> 28601662 | M14: =SUM(M10:M12) -> 29240703
B16: Financial Liabilities
B17: Deferred liability - staff retirement gratuity | E17: 0 | F17: 0 | G17: 0 | H17: 0 | I17: 16377485 | J17: =SUM(H17:I17) -> 16377485 | K17: =(G17+J17) -> 16377485 | M17: 11681206
B18: Accrued, payables and other liabilities | E18: 0 | F18: 0 | G18: =SUM(E18:F18) -> 0 | H18: 1211394 | I18: 0 | J18: =SUM(H18:I18) -> 1211394 | K18: =(G18+J18) -> 1211394 | M18: 1111394
B19: Short term liabilities | E19: 0 | F19: 0 | G19: =SUM(E19:F19) -> 0 | H19: 8838057.8 | I19: 0 | J19: =SUM(H19:I19) -> 8838057.8 | K19: =(G19+J19) -> 8838057.8 | M19: 8838057.8
B20: Running finance | E20: 600004 | H20: 600004 | I20: 0 | J20: =SUM(H20:I20) -> 600004 | K20: =(G20+J20) -> 600004 | M20: 0
E21: =SUM(E17:E20) -> 600004 | F21: =SUM(F17:F19) -> 0 | G21: =SUM(G17:G19) -> 0 | H21: =SUM(H17:H19) -> 10049452 | I21: =SUM(I17:I19) -> 16377485 | J21: =SUM(J17:J19) -> 26426937 | K21: =SUM(K17:K19) -> 26426937 | M21: =SUM(M17:M20) -> 21630658
C87: Chief Executive Officer | H87: Director

Sheet Sheet9
A1: Account Code | B1: Account Description | C1: Title | D1: FSL1 | E1: FSL2 | F1: FSL3 | G1: FSL 4 | H1: Cost center | I1: Debit | J1: Credit | K1: Debit2 | L1: Credit2 | M1: Debit3 | N1: Credit3 | O1: Debit4 | P1: Credit4 | Q1: Debit5 | R1: Credit5 | S1: Amount
A2: 1-02-02-09-002 | B2: ACCUMULTED DEPRECIATION BOOKS | C2: 1-02-02-09-002-ACCUMULTED DEPRECIATION BOOKSPILER | D2: Balance Sheet | E2: Non Current Assets | F2: Tangible | G2: Acc Dep - Books | H2: PILER | I2: 0 | J2: 308439 | K2: 0 | L2: 0 | M2: 0 | N2: 308439 | Q2: 0 | R2: 308439 | S2: -308439
A3: 1-02-02-02-002 | B3: ACCUMULATED DEPRECIATION BUILD | C3: 1-02-02-02-002-ACCUMULATED DEPRECIATION BUILDPILER | D3: Balance Sheet | E3: Non Current Assets | F3: Tangible | G3: Acc Dep - Building On Leasehold Land | H3: PILER | I3: 0 | J3: 9631348 | K3: 0 | L3: 455276 | M3: 0 | N3: 10086624 | Q3: 0 | R3: 10086624 | S3: -10086624
A4: 1-02-02-07-002 | B4: ACCUMULATED DEPRECIATION COMPU | C4: 1-02-02-07-002-ACCUMULATED DEPRECIATION COMPUPILER | D4: Balance Sheet | E4: Non Current Assets | F4: Tangible | G4: Acc Dep - Computer Equipments | H4: PILER | I4: 5854 | J4: 2909388 | K4: 0 | L4: 0 | M4: 5854 | N4: 2909388 | P4: 0 | Q4: 5854 | R4: 2909388 | S4: -2903534
A5: 1-02-02-04-002 | B5: ACCUMULATED DEPRECIATION ELECT | C5: 1-02-02-04-002-ACCUMULATED DEPRECIATION ELECTPILER | D5: Balance Sheet | E5: Non Current Assets | F5: Tangible | G5: Acc Dep - Electrical Installations | H5: PILER | I5: 68126 | J5: 3848932 | K5: 0 | L5: 355637 | M5: 68126 | N5: 4204569 | Q5: 68126 | R5: 4204569 | S5: -4136443
A6: 1-02-02-06-002 | B6: ACCUMULATED DEPRECIATION F & F | C6: 1-02-02-06-002-ACCUMULATED DEPRECIATION F & FPILER | D6: Balance Sheet | E6: Non Current Assets | F6: Tangible | G6: Acc Dep - Furniture And Fixture | H6: PILER | I6: 45012 | J6: 882613 | K6: 0 | L6: 9680 | M6: 45012 | N6: 892293 | Q6: 45012 | R6: 892293 | S6: -847281
A7: 1-02-02-03-002 | B7: ACCUMULATED DEPRECIATION GENER | C7: 1-02-02-03-002-ACCUMULATED DEPRECIATION GENERPILER | D7: Balance Sheet | E7: Non Current Assets | F7: Tangible | G7: Acc Dep - Generator | H7: PILER | I7: 10368 | J7: 1193771 | K7: 0 | L7: 62204 | M7: 10368 | N7: 1255975 | O7: 19881 | Q7: 30249 | R7: 1255975 | S7: -1225726
A8: 1-02-02-05-002 | B8: ACCUMULATED DEPRECIATION OTHER | C8: 1-02-02-05-002-ACCUMULATED DEPRECIATION OTHERPILER | D8: Balance Sheet | E8: Non Current Assets | F8: Tangible | G8: Acc Dep - Other Equipments | H8: PILER | I8: 77185 | J8: 958595 | K8: 0 | L8: 7068 | M8: 77185 | N8: 965663 | Q8: 77185 | R8: 965663 | S8: -888478
A9: 1-02-02-08-002 | B9: ACCUMULTED DEPRECIATION MOTORS | C9: 1-02-02-08-002-ACCUMULTED DEPRECIATION MOTORSPILER | D9: Balance Sheet | E9: Non Current Assets | F9: Tangible | G9: Acc Dep - Vehicles | H9: PILER | I9: 1384994 | J9: 2493599 | K9: 0 | L9: 0 | M9: 1384994 | N9: 2493599 | Q9: 1384994 | R9: 2493599 | S9: -1108605
A10: 2-01-01-01-010 | B10: AUDIT FEE PAYABLE | C10: 2-01-01-01-010-AUDIT FEE PAYABLEPILER | D10: Balance Sheet | E10: Current Liabilities | F10: Accrued, Payables And Other Liabilities | G10: Accrued Expenses | H10: PILER | I10: 2133440 | J10: 2825362 | K10: 432000 | L10: 432000 | M10: 2565440 | N10: 3257362 | Q10: 2565440 | R10: 3257362 | S10: -691922
A11: 2-01-02-01-001 | B11: SALARIES PAYABLE | C11: 2-01-02-01-001-SALARIES PAYABLEPILER | D11: Balance Sheet | E11: Current Liabilities | F11: Accrued, Payables And Other Liabilities | G11: Accrued Expenses | H11: PILER | I11: 19048421 | J11: 18997551 | K11: 3551215 | L11: 3548477 | M11: 22599636 | N11: 22546028 | Q11: 22599636 | R11: 22546028 | S11: 53608
A12: 2-01-02-01-001 | B12: SALARIES PAYABLE | C12: 2-01-02-01-001-SALARIES PAYABLEUNICEF-3 | D12: Balance Sheet | E12: Current Liabilities | F12: Accrued, Payables And Other Liabilities | G12: Accrued Expenses | H12: UNICEF-3 | I12: 0 | J12: 3 | K12: 0 | L12: 0 | M12: 0 | N12: 3 | Q12: 0 | R12: 3 | S12: -3
A13: 2-01-02-01-001 | B13: SALARIES PAYABLE | C13: 2-01-02-01-001-SALARIES PAYABLEDAI | D13: Balance Sheet | E13: Current Liabilities | F13: Accrued, Payables And Other Liabilities | G13: Accrued Expenses | H13: DAI | I13: 3 | J13: 0 | K13: 0 | L13: 0 | M13: 3 | N13: 0 | Q13: 3 | R13: 0 | S13: 3
A14: 2-01-02-01-001 | B14: SALARIES PAYABLE | C14: 2-01-02-01-001-SALARIES PAYABLEGRC | D14: Balance Sheet | E14: Current Liabilities | F14: Accrued, Payables And Other Liabilities | G14: Accrued Expenses | H14: GRC | I14: 818916 | J14: 819916 | K14: 4805155 | L14: 4952509 | M14: 5624071 | N14: 5772425 | Q14: 5624071 | R14: 5772425 | S14: -148354
A15: 2-01-02-01-009 | B15: ACCRUED LIABILITIES - 2010 | C15: 2-01-02-01-009-ACCRUED LIABILITIES - 2010PILER | D15: Balance Sheet | E15: Current Liabilities | F15: Accrued, Payables And Other Liabilities | G15: Accrued Expenses | H15: PILER | I15: 0 | J15: 0 | K15: 0 | L15: 0 | M15: 0 | N15: 0 | Q15: 0 | R15: 0 | S15: 0
A16: 2-01-02-01-011 | B16: ACCURED EXPENSES | C16: 2-01-02-01-011-ACCURED EXPENSESTrocaire | D16: Balance Sheet | E16: Current Liabilities | F16: Accrued, Payables And Other Liabilities | G16: Accrued Expenses | H16: Trocaire | I16: 5519251 | J16: 4760392.3 | K16: 0 | L16: 0 | M16: 5519251 | N16: 4760392.3 | Q16: 5519251 | R16: 4760392.3 | S16: 758858.7
A17: 2-01-02-01-011 | B17: ACCURED EXPENSES | C17: 2-01-02-01-011-ACCURED EXPENSESPILER | D17: Balance Sheet | E17: Current Liabilities | F17: Accrued, Payables And Other Liabilities | G17: Accrued Expenses | H17: PILER | I17: 365378 | J17: 3507751.9 | K17: 0 | L17: 0 | M17: 365378 | N17: 3507751.9 | Q17: 365378 | R17: 3507751.9 | S17: -3142373.9
A18: 2-01-02-01-011 | B18: ACCURED EXPENSES | C18: 2-01-02-01-011-ACCURED EXPENSESDAI | D18: Balance Sheet | E18: Current Liabilities | F18: Accrued, Payables And Other Liabilities | G18: Accrued Expenses | H18: DAI | I18: 16420 | J18: 16420 | K18: 0 | L18: 0 | M18: 16420 | N18: 16420 | Q18: 16420 | R18: 16420 | S18: 0
A19: 2-01-02-01-011 | B19: ACCURED EXPENSES | C19: 2-01-02-01-011-ACCURED EXPENSESSHORT PROJECTS | D19: Balance Sheet | E19: Current Liabilities | F19: Accrued, Payables And Other Liabilities | G19: Accrued Expenses | H19: SHORT PROJECTS | I19: 200000 | J19: 740665.4 | K19: 0 | L19: 0 | M19: 200000 | N19: 740665.4 | Q19: 200000 | R19: 740665.4 | S19: -540665.4
... A22: 2-01-02-01-011 | B22: ACCURED EXPENSES | C22: 2-01-02-01-011-ACCURED EXPENSESETI | D22: Balance Sheet | E22: Current Liabilities | F22: Accrued, Payables And Other Liabilities | G22: Accrued Expenses | H22: ETI | I22: 0 | J22: 0 | K22: 0 | L22: 0 | M22: 0 | N22: 0 | Q22: 0 | R22: 0 | S22: 0
A23: 2-01-02-01-012 | B23: STAFF LOAN PAYABLE | C23: 2-01-02-01-012- STAFF LOAN PAYABLE | D23: Balance Sheet | E23: Current Liabilities | F23: Accrued, Payables And Other Liabilities | G23: Accrued Expenses | I23: 45000 | J23: 45000 | M23: 45000 | N23: 45000 | Q23: 45000 | R23: 45000 | S23: 0
A24: 2-01-02-01-011 | B24: ACCURED EXPENSES | C24: 2-01-02-01-011-ACCURED EXPENSESGRC | D24: Balance Sheet | E24: Current Liabilities | F24: Accrued, Payables And Other Liabilities | G24: Accrued Expenses | H24: GRC | I24: 0 | J24: 1735920 | K24: 566028 | L24: 0 | M24: 566028 | N24: 1735920 | Q24: 566028 | R24: 1735920 | S24: -1169892
A25: 1-02-02-07-004 | B25: AMMORTIZATION OF SOFTWARE LICS | C25: 1-02-02-07-004-AMMORTIZATION OF SOFTWARE LICSPILER | D25: Balance Sheet | E25: Non Current Assets | F25: Intangible | G25: Accumulated Amortisation | H25: PILER | I25: 7487 | J25: 458860.67 | K25: 0 | L25: 115326 | M25: 7487 | N25: 574186.67 | O25: 115326 | Q25: 122813 | R25: 574186.67 | S25: -451373.67
A26: 1-02-02-07-004 | B26: AMMORTIZATION OF SOFTWARE LICS | C26: Ammortization Of Software Lics | D26: Balance Sheet | E26: Non Current Assets | F26: Intangible | G26: Accumulated Amortisation | H26: ETI | I26: 0 | J26: 0 | K26: 0 | L26: 0 | M26: 0 | N26: 0 | Q26: 0 | R26: 0 | S26: 0
A27: 1-01-02-03-003 | B27: ADVANCE TO GOHAR ALI | C27: 1-01-02-03-003-ADVANCE TO GOHAR ALIPILER | D27: Balance Sheet | E27: Current Assets | F27: Loans, Advances, Deposits, Prepayments And Receivables | G27: Advance Against Activities | H27: PILER | I27: 2450 | J27: 0 | K27: 0 | L27: 0 | M27: 2450 | N27: 0 | Q27: 2450 | R27: 0 | S27: 2450
A28: 1-01-02-03-003 | B28: ADVANCE TO GOHAR ALI | C28: 1-01-02-03-003-ADVANCE TO GOHAR ALITDH | D28: Balance Sheet | E28: Current Assets | F28: Loans, Advances, Deposits, Prepayments And Receivables | G28: Advance Against Activities | H28: TDH | I28: 0 | J28: 2450 | K28: 0 | L28: 0 | M28: 0 | N28: 2450 | Q28: 0 | R28: 2450 | S28: -2450
A29: 1-01-02-03-008 | B29: ADVANCE TO KHADIM HUSSAIN | C29: 1-01-02-03-008-ADVANCE TO KHADIM HUSSAINPILER | D29: Balance Sheet | E29: Current Assets | F29: Loans, Advances, Deposits, Prepayments And Receivables | G29: Advance Against Activities | H29: PILER | I29: 2406928 | J29: 2436928 | K29: 2317470 | L29: 2317470 | M29: 4724398 | N29: 4754398 | O29: 30000 | Q29: 4754398 | R29: 4754398 | S29: 0
A30: 1-01-02-03-008 | B30: ADVANCE TO KHADIM HUSSAIN | C30: 1-01-02-03-008-ADVANCE TO KHADIM HUSSAINICCO | D30: Balance Sheet | E30: Current Assets | F30: Loans, Advances, Deposits, Prepayments And Receivables | G30: Advance Against Activities | H30: ICCO | I30: 50200 | J30: 0 | K30: 0 | L30: 0 | M30: 50200 | N30: 0 | P30: 50200 | Q30: 50200 | R30: 50200 | S30: 0
A31: 1-01-02-03-008 | B31: ADVANCE TO KHADIM HUSSAIN | C31: 1-01-02-03-008-ADVANCE TO KHADIM HUSSAINSHORT PROJECTS | D31: Balance Sheet | E31: Current Assets | F31: Loans, Advances, Deposits, Prepayments And Receivables | G31: Advance Against Activities | H31: SHORT PROJECTS | I31: 303365 | J31: 227500 | K31: 0 | L31: 0 | M31: 303365 | N31: 227500 | P31: 75865 | Q31: 303365 | R31: 303365 | S31: 0
A32: 1-01-02-03-008 | B32: Advance To Khadim Hussain | C32: 1-01-02-03-008-Advance To Khadim HussainOpen Society | D32: Balance Sheet | E32: Current Assets | F32: Loans, Advances, Deposits, Prepayments And Receivables | G32: Advance Against Activities | H32: Open Society | I32: 98530 | J32: 98530 | M32: 98530 | N32: 98530 | Q32: 98530 | R32: 98530 | S32: 0
A33: 1-01-02-03-008 | B33: ADVANCE TO KHADIM HUSSAIN | C33: 1-01-02-03-008-ADVANCE TO KHADIM HUSSAINDAI | D33: Balance Sheet | E33: Current Assets | F33: Loans, Advances, Deposits, Prepayments And Receivables | G33: Advance Against Activities | H33: DAI | I33: 15150 | J33: 6000 | K33: 0 | L33: 0 | M33: 15150 | N33: 6000 | P33: 9150 | Q33: 15150 | R33: 15150 | S33: 0
A34: 1-01-02-03-008 | B34: ADVANCE TO KHADIM HUSSAIN | C34: 1-01-02-03-008-ADVANCE TO KHADIM HUSSAINGRC | D34: Balance Sheet | E34: Current Assets | F34: Loans, Advances, Deposits, Prepayments And Receivables | G34: Advance Against Activities | H34: GRC | I34: 350100 | J34: 350100 | K34: 330000 | L34: 310000 | M34: 680100 | N34: 660100 | P34: 20000 | Q34: 680100 | R34: 680100 | S34: 0
A35: 1-01-02-03-008 | B35: ADVANCE TO KHADIM HUSSAIN | C35: 1-01-02-03-008-ADVANCE TO KHADIM HUSSAINGRC Own | D35: Balance Sheet | E35: Current Assets | F35: Loans, Advances, Deposits, Prepayments And Receivables | G35: Advance Against Activities | H35: GRC Own | I35: 0 | J35: 0 | K35: 186000 | L35: 0 | M35: 186000 | N35: 0 | Q35: 186000 | R35: 0 | S35: 186000
A36: 1-01-02-03-020 | B36: ADVANCE TO ABBAS HAIDER | C36: 1-01-02-03-020-ADVANCE TO ABBAS HAIDERPILER | D36: Balance Sheet | E36: Current Assets | F36: Loans, Advances, Deposits, Prepayments And Receivables | G36: Advance Against Activities | H36: PILER | I36: 564350 | J36: 477300 | K36: 42000 | L36: 0 | M36: 606350 | N36: 477300 | P36: 87050 | Q36: 606350 | R36: 564350 | S36: 42000
A37: 1-01-02-03-020 | B37: ADVANCE TO ABBAS HAIDER | C37: 1-01-02-03-020-ADVANCE TO ABBAS HAIDERSHORT PROJECTS | D37: Balance Sheet | E37: Current Assets | F37: Loans, Advances, Deposits, Prepayments And Receivables | G37: Advance Against Activities | H37: SHORT PROJECTS | I37: 647000 | J37: 697000 | K37: 0 | L37: 0 | M37: 647000 | N37: 697000 | O37: 50000 | Q37: 697000 | R37: 697000 | S37: 0
A38: 1-01-02-03-020 | B38: ADVANCE TO ABBAS HAIDER | C38: 1-01-02-03-020-ADVANCE TO ABBAS HAIDERRRCCHR | D38: Balance Sheet | E38: Current Assets | F38: Loans, Advances, Deposits, Prepayments And Receivables | G38: Advance Against Activities | H38: RRCCHR | I38: 4000 | J38: 0 | K38: 0 | L38: 0 | M38: 4000 | N38: 0 | P38: 4000 | Q38: 4000 | R38: 4000 | S38: 0
A39: 1-01-02-03-041 | B39: ADVANCE TO M.RAFIQUE | C39: 1-01-02-03-041-ADVANCE TO M.RAFIQUETDH & MI | D39: Balance Sheet | E39: Current Assets | F39: Loans, Advances, Deposits, Prepayments And Receivables | G39: Advance Against Activities | H39: TDH & MI | I39: 300000 | J39: 5050 | K39: 0 | L39: 300000 | M39: 300000 | N39: 305050 | O39: 5050 | Q39: 305050 | R39: 305050 | S39: 0
A40: 1-01-02-03-116 | B40: Advance to Zameer Awan | C40: 1-01-02-03-116-Advance to Zameer AwanPILER | D40: Balance Sheet | E40: Current Assets | F40: Loans, Advances, Deposits, Prepayments And Receivables | G40: Advance Against Activities | H40: PILER | I40: 70000 | J40: 70000 | K40: 321000 | L40: 321000 | M40: 391000 | N40: 391000 | Q40: 391000 | R40: 391000 | S40: 0
A41: 1-01-02-03-123 | B41: Advance against Expenses | C41: 1-01-02-03-123Advance against Expenses | D41: Balance Sheet | E41: Current Assets | F41: Loans, Advances, Deposits, Prepayments And Receivables | G41: Advance Against Activities | H41: PILER | I41: 231282 | J41: 70000 | K41: 560500 | L41: 670500 | M41: 791782 | N41: 740500 | Q41: 791782 | R41: 740500 | S41: 51282
A42: 1-01-02-03-123 | B42: Advance against Expenses | C42: 1-01-02-03-123-Advance against ExpensesGRC | D42: Balance Sheet | E42: Current Assets | F42: Loans, Advances, Deposits, Prepayments And Receivables | G42: Advance Against Activities | H42: GRC | I42: 0 | J42: 0 | K42: 134750 | L42: 186032 | M42: 134750 | N42: 186032 | Q42: 134750 | R42: 186032 | S42: -51282
A43: 1-01-02-03-123 | B43: Advance against Expenses | C43: 1-01-02-03-123-Advance against ExpensesGRC Own | D43: Balance Sheet | E43: Current Assets | F43: Loans, Advances, Deposits, Prepayments And Receivables | G43: Advance Against Activities | H43: GRC Own | I43: 0 | J43: 0 | K43: 10000 | L43: 10000 | M43: 10000 | N43: 10000 | Q43: 10000 | R43: 10000 | S43: 0
A44: 1-01-02-04-005 | B44: Advance to hikmat ali | C44: 1-01-02-04-005-Advance to hikmat aliPILER | D44: Balance Sheet | E44: Current Assets | F44: Loans, Advances, Deposits, Prepayments And Receivables | G44: Advance Against Activities | H44: PILER | I44: 111000 | J44: 111000 | K44: 5000 | L44: 5000 | M44: 116000 | N44: 116000 | Q44: 116000 | R44: 116000 | S44: 0
A45: 1-01-02-03-124 | B45: Advance to Sajid Ali | C45: 1-01-02-03-124-Advance to Sajid Ali | D45: Balance Sheet | E45: Current Assets | F45: Loans, Advances, Deposits, Prepayments And Receivables | G45: Advance Against Activities | I45: 58000 | J45: 58000 | M45: 58000 | N45: 58000 | Q45: 58000 | R45: 58000 | S45: 0
A46: 1-01-02-03-122 | B46: Advance to Home Net Pakistan | C46: 1-01-02-03-122-Advance to Home Net Pakistan | D46: Balance Sheet | E46: Current Assets | F46: Loans, Advances, Deposits, Prepayments And Receivables | G46: Advance Against Activities | I46: 273000 | J46: 273000 | M46: 273000 | N46: 273000 | Q46: 273000 | R46: 273000 | S46: 0
A47: 1-01-02-03-068 | B47: ADVANCE TO ABIDA ALI | C47: 1-01-02-03-068-ADVANCE TO ABIDA ALISHORT | D47: Balance Sheet | E47: Current Assets | F47: Loans, Advances, Deposits, Prepayments And Receivables | G47: Advance Against Activities | H47: SHORT | I47: 344800 | J47: 344800 | M47: 344800 | N47: 344800 | Q47: 344800 | R47: 344800 | S47: 0
A48: 1-01-02-03-068 | B48: ADVANCE TO ABIDA ALI | C48: 1-01-02-03-068-ADVANCE TO ABIDA ALIPILER | D48: Balance Sheet | E48: Current Assets | F48: Loans, Advances, Deposits, Prepayments And Receivables | G48: Advance Against Activities | H48: PILER | I48: 131000 | J48: 131000 | M48: 131000 | N48: 131000 | Q48: 131000 | R48: 131000 | S48: 0
A49: 1-01-02-03-013 | B49: ADVANCE TO KARAMAT ALI | C49: 1-01-02-03-013-ADVANCE TO KARAMAT ALIPILER | D49: Balance Sheet | E49: Current Assets | F49: Loans, Advances, Deposits, Prepayments And Receivables | G49: Advance Against Activities | H49: PILER | I49: 200000 | J49: 200000 | M49: 200000 | N49: 200000 | Q49: 200000 | R49: 200000 | S49: 0
A50: 1-01-02-04-005 | B50: Advance To Hikmat Ali | C50: 1-01-02-04-005-Advance To Hikmat AliOpen Society | D50: Balance Sheet | E50: Current Assets | F50: Loans, Advances, Deposits, Prepayments And Receivables | G50: Advance Against Activities | H50: Open Society | I50: 15000 | J50: 15000 | M50: 15000 | N50: 15000 | Q50: 15000 | R50: 15000 | S50: 0
A51: 1-01-02-03-116 | B51: Advance To Zameer Awan | C51: 1-01-02-03-116-Advance To Zameer AwanSHORT PROJECTS | D51: Balance Sheet | E51: Current Assets | F51: Loans, Advances, Deposits, Prepayments And Receivables | G51: Advance Against Activities | H51: SHORT PROJECTS | I51: 225589 | J51: 225589 | M51: 225589 | N51: 225589 | Q51: 225589 | R51: 225589 | S51: 0
A52: 1-01-02-03-020 | B52: Advance To Abbas Haider | C52: 1-01-02-03-020-Advance To Abbas HaiderGRC | D52: Balance Sheet | E52: Current Assets | F52: Loans, Advances, Deposits, Prepayments And Receivables | G52: Advance Against Activities | H52: GRC | I52: 156000 | J52: 156000 | M52: 156000 | N52: 156000 | Q52: 156000 | R52: 156000 | S52: 0
A53: 1-01-02-03-017 | B53: Advance To Danish Siddiqui | C53: 1-01-02-03-017-Advance To Danish SiddiquiDAI | D53: Balance Sheet | E53: Current Assets | F53: Loans, Advances, Deposits, Prepayments And Receivables | G53: Advance Against Activities | H53: DAI | I53: 769000 | J53: 769000 | M53: 769000 | N53: 769000 | Q53: 769000 | R53: 769000 | S53: 0
A54: 1-01-02-03-015 | B54: Advance To Pervez | C54: 1-01-02-03-015-Advance To PervezDAI | D54: Balance Sheet | E54: Current Assets | F54: Loans, Advances, Deposits, Prepayments And Receivables | G54: Advance Against Activities | H54: DAI | I54: 1374205 | J54: 1374205 | M54: 1374205 | N54: 1374205 | Q54: 1374205 | R54: 1374205 | S54: 0
A55: 1-01-02-04-001 | B55: ADVANCE AGAINST SALARIES | C55: 1-01-02-04-001-ADVANCE AGAINST SALARIESPILER | D55: Balance Sheet | E55: Current Assets | F55: Loans, Advances, Deposits, Prepayments And Receivables | G55: Advance Against Salaries | H55: PILER | I55: 2732235 | J55: 2702235 | K55: 193947 | L55: 183947 | M55: 2926182 | N55: 2886182 | Q55: 2926182 | R55: 2886182 | S55: 40000
A56: 1-01-02-04-001 | B56: ADVANCE AGAINST SALARIES | C56: 1-01-02-04-001-ADVANCE AGAINST SALARIESSHORT PROJECTS | D56: Balance Sheet | E56: Current Assets | F56: Loans, Advances, Deposits, Prepayments And Receivables | G56: Advance Against Salaries | H56: SHORT PROJECTS | I56: 0 | J56: 0 | K56: 0 | L56: 0 | M56: 0 | N56: 0 | Q56: 0 | R56: 0 | S56: 0
A57: 1-01-02-04-001 | B57: ADVANCE AGAINST SALARIES | C57: Advance Against Salaries | D57: Balance Sheet | E57: Current Assets | F57: Loans, Advances, Deposits, Prepayments And Receivables | G57: Advance Against Salaries | H57: GRC | I57: 95000 | J57: 95000 | K57: 40000 | L57: 40000 | M57: 135000 | N57: 135000 | Q57: 135000 | R57: 135000 | S57: 0
A58: 1-01-02-04-001 | B58: ADVANCE AGAINST SALARIES | C58: 1-01-02-04-001-ADVANCE AGAINST SALARIESGRC Own | D58: Balance Sheet | E58: Current Assets | F58: Loans, Advances, Deposits, Prepayments And Receivables | G58: Advance Against Salaries | H58: GRC Own | I58: 0 | J58: 0 | K58: 80000 | L58: 30000 | M58: 80000 | N58: 30000 | Q58: 80000 | R58: 30000 | S58: 50000
A59: 1-02-02-09-001 | B59: BOOKS | C59: 1-02-02-09-001-BOOKSPILER | D59: Balance Sheet | E59: Non Current Assets | F59: Tangible | G59: Books | H59: PILER | I59: 308439 | J59: 0 | K59: 0 | L59: 0 | M59: 308439 | N59: 0 | Q59: 308439 | R59: 0 | S59: 308439
A60: 1-02-02-02-001 | B60: BUILDING LEASE HOLD LAND | C60: 1-02-02-02-001-BUILDING LEASE HOLD LANDPILER | D60: Balance Sheet | E60: Non Current Assets | F60: Tangible | G60: Building On Leasehold Land | H60: PILER | I60: 22763814 | J60: 0 | K60: 0 | L60: 0 | M60: 22763814 | N60: 0 | Q60: 22763814 | R60: 0 | S60: 22763814
A61: 1-01-01-01-001 | B61: CASH IN HAND | C61: 1-01-01-01-001-CASH IN HANDPILER | D61: Balance Sheet | E61: Current Assets | F61: Cash And Bank Balances | G61: Cash With Banks In Current/Pls Accounts | H61: PILER | I61: 3 | K61: 0 | L61: 0 | M61: 3 | N61: 0 | Q61: 3 | R61: 0 | S61: 3
A62: 1-01-01-01-001 | B62: CASH IN HAND | C62: 1-01-01-01-001-CASH IN HANDKarachi | D62: Balance Sheet | E62: Current Assets | F62: Cash And Bank Balances | G62: Cash With Banks In Current/Pls Accounts | H62: Karachi | I62: 0 | J62: 0 | K62: 0 | L62: 0 | M62: 0 | N62: 0 | Q62: 0 | R62: 0 | S62: 0
A63: 1-01-01-02-002 | B63: PILER OWN BAHL A/C. 818-04-2 | C63: 1-01-01-02-002-PILER OWN BAHL A/C. 818-04-2PILER | D63: Balance Sheet | E63: Current Assets | F63: Cash And Bank Balances | G63: Cash With Banks In Current/Pls Accounts | H63: PILER | I63: 143120 | J63: 0 | K63: 0 | L63: 0 | M63: 143120 | N63: 0 | Q63: 143120 | R63: 0 | S63: 143120
A64: 1-01-01-02-011 | B64: PILER TDH & MI BH A/C.818-09-7 | C64: 1-01-01-02-011-PILER TDH & MI BH A/C.818-09-7TDH & MI | D64: Balance Sheet | E64: Current Assets | F64: Cash And Bank Balances | G64: Cash With Banks In Current/Pls Accounts | H64: TDH & MI | I64: 0 | J64: 809205 | K64: 0 | L64: 0 | M64: 0 | N64: 809205 | Q64: 0 | R64: 809205 | S64: -809205
A65: 1-01-01-02-011 | B65: PILER TDH & MI BH A/C.818-09-7 | C65: 1-01-01-02-011-PILER TDH & MI BH A/C.818-09-7TDH | D65: Balance Sheet | E65: Current Assets | F65: Cash And Bank Balances | G65: Cash With Banks In Current/Pls Accounts | H65: TDH | I65: 581067 | J65: 0 | K65: 0 | L65: 0 | M65: 581067 | N65: 0 | Q65: 581067 | R65: 0 | S65: 581067
A66: 1-01-01-02-012 | B66: PILER UBL-012-1940-6 | C66: 1-01-01-02-012-PILER UBL-012-1940-6PILER | D66: Balance Sheet | E66: Current Assets | F66: Cash And Bank Balances | G66: Cash With Banks In Current/Pls Accounts | H66: PILER | I66: 62500 | J66: 0 | K66: 0 | L66: 0 | M66: 62500 | N66: 0 | Q66: 62500 | R66: 0 | S66: 62500
A67: 1-01-01-02-013 | B67: PILER UBL-012-1707-3 | C67: 1-01-01-02-013-PILER UBL-012-1707-3PILER | D67: Balance Sheet | E67: Current Assets | F67: Cash And Bank Balances | G67: Cash With Banks In Current/Pls Accounts | H67: PILER | I67: 51853 | J67: 0 | K67: 0 | L67: 0 | M67: 51853 | N67: 0 | Q67: 51853 | R67: 0 | S67: 51853
A68: 1-01-01-02-015 | B68: PILER FNV PROJECT 06-0 | C68: 1-01-01-02-015-PILER FNV PROJECT 06-0PILER | D68: Balance Sheet | E68: Current Assets | F68: Cash And Bank Balances | G68: Cash With Banks In Current/Pls Accounts | H68: PILER | I68: 15489 | J68: 0 | K68: 0 | L68: 0 | M68: 15489 | N68: 0 | Q68: 15489 | R68: 0 | S68: 15489
A69: 1-01-01-02-016 | B69: PILER EU PROJECT BAHL-GJ 06-2 | C69: 1-01-01-02-016-PILER EU PROJECT BAHL-GJ 06-2PILER | D69: Balance Sheet | E69: Current Assets | F69: Cash And Bank Balances | G69: Cash With Banks In Current/Pls Accounts | H69: PILER | I69: 29198 | J69: 0 | K69: 0 | L69: 0 | M69: 29198 | N69: 0 | Q69: 29198 | R69: 0 | S69: 29198
A70: 1-01-01-02-020 | B70: PILER BAH-A/C.0081-004762-01-0 | C70: 1-01-01-02-020-PILER BAH-A/C.0081-004762-01-0PILER | D70: Balance Sheet | E70: Current Assets | F70: Cash And Bank Balances | G70: Cash With Banks In Current/Pls Accounts | H70: PILER | I70: 42086429 | J70: 40166118 | K70: 24208666 | L70: 20796993 | M70: 66295095 | N70: 60963111 | Q70: 66295095 | R70: 60963111 | S70: 5331984
A71: 1-01-01-02-021 | B71: PILER TAF BAH-0081-004762-02-1 | C71: 1-01-01-02-021-PILER TAF BAH-0081-004762-02-1TAF | D71: Balance Sheet | E71: Current Assets | F71: Cash And Bank Balances | G71: Cash With Banks In Current/Pls Accounts | H71: TAF | I71: 381581.2 | J71: 79.1 | K71: 0 | L71: 0 | M71: 381581.2 | N71: 79.1 | Q71: 381581.2 | R71: 79.1 | S71: 381502.1
A72: 1-01-01-02-021 | B72: PILER TAF BAH-0081-004762-02-1 | C72: 1-01-01-02-021-PILER TAF BAH-0081-004762-02-1ETI | D72: Balance Sheet | E72: Current Assets | F72: Cash And Bank Balances | G72: Cash With Banks In Current/Pls Accounts | H72: ETI | I72: 239707 | J72: 621187.48 | K72: 0 | L72: 21.62 | M72: 239707 | N72: 621209.1 | Q72: 239707 | R72: 621209.1 | S72: -381502.1
A73: 1-01-01-02-022 | B73: BANK UNICEF-0081-004762-04-3 | C73: 1-01-01-02-022-BANK UNICEF-0081-004762-04-3PILER | D73: Balance Sheet | E73: Current Assets | F73: Cash And Bank Balances | G73: Cash With Banks In Current/Pls Accounts | H73: PILER | I73: 351956.05 | J73: 347588.4 | K73: 0 | L73: 0 | M73: 351956.05 | N73: 347588.4 | Q73: 351956.05 | R73: 347588.4 | S73: 4367.65
... A94: 1-01-01-02-031 | B94: BANK SMALL PR-0081-004762-07-6 | C94: Bank Small Pr-0081-004762-07-6 | D94: Balance Sheet | E94: Current Assets | F94: Cash And Bank Balances | G94: Cash With Banks In Current/Pls Accounts | H94: DAI | I94: 0 | J94: 180000 | K94: 0 | L94: 0 | M94: 0 | N94: 180000 | Q94: 0 | R94: 180000 | S94: -180000
A95: 1-02-02-07-001 | B95: COMPUTER & LAPTOPS | C95: 1-02-02-07-001-COMPUTER & LAPTOPSPILER | D95: Balance Sheet | E95: Non Current Assets | F95: Tangible | G95: Computer Equipments | H95: PILER | I95: 2903533 | J95: 0 | K95: 0 | L95: 0 | M95: 2903533 | N95: 0 | O95: 0 | Q95: 2903533 | R95: 0 | S95: 2903533
A96: 1-02-02-07-003 | B96: COMPUTER SOFTWARE | C96: 1-02-02-07-003-COMPUTER SOFTWAREPILER | D96: Balance Sheet | E96: Non Current Assets | F96: Intangible | G96: Cost | H96: PILER | I96: 549421 | J96: 89325 | K96: 337290 | L96: 0 | M96: 886711 | N96: 89325 | P96: 340197 | Q96: 886711 | R96: 429522 | S96: 457189
A97: 1-02-02-04-001 | B97: ELECTRICAL INSTALLATIONS | C97: 1-02-02-04-001-ELECTRICAL INSTALLATIONSPILER | D97: Balance Sheet | E97: Non Current Assets | F97: Tangible | G97: Electrical Installations | H97: PILER | I97: 4945458 | J97: 0 | K97: 25000 | L97: 0 | M97: 4970458 | N97: 0 | Q97: 4970458 | R97: 0 | S97: 4970458
A98: 1-02-02-04-001 | B98: Electrical Installations | C98: 1-02-02-04-001-Electrical InstallationsGRC | D98: Balance Sheet | E98: Non Current Assets | F98: Tangible | G98: Electrical Installations | H98: GRC | I98: 147330 | J98: 147330 | M98: 147330 | N98: 147330 | Q98: 147330 | R98: 147330 | S98: 0
A99: 3-01-01-01-001 | B99: FUND BALANCE | C99: 3-01-01-01-001-FUND BALANCEPILER | D99: Balance Sheet | E99: Fund Balance | F99: Fund Balance | G99: Fund Balance | H99: PILER | I99: 73356131 | J99: 0 | K99: 0 | L99: 0 | M99: 73356131 | N99: 0 | Q99: 73356131 | R99: 0 | S99: 73356131
A100: 3-01-01-01-009 | B100: DEZAIRE FUND BALANCE | C100: 3-01-01-01-009-DEZAIRE FUND BALANCEDeezire | D100: Balance Sheet | E100: Fund Balance | F100: Fund Balance | G100: Fund Balance | H100: Deezire | I100: 0 | J100: 1641568 | K100: 0 | L100: 0 | M100: 0 | N100: 1641568 | Q100: 0 | R100: 1641568 | S100: -1641568
A101: 3-01-01-01-013 | B101: RCCHR FUND BALANCE | C101: 3-01-01-01-013-RCCHR FUND BALANCE | D101: Balance Sheet | E101: Fund Balance | F101: Fund Balance | G101: Fund Balance | I101: 0 | J101: 0 | K101: 0 | L101: 0 | M101: 0 | N101: 0 | Q101: 0 | R101: 0 | S101: 0
A102: 3-01-01-01-012 | B102: Osf-Fund Balance | C102: 3-01-01-01-012-Osf-Fund BalanceOpen Society | D102: Balance Sheet | E102: Fund Balance | F102: Fund Balance | G102: Fund Balance | H102: Open Society | I102: 13192587 | J102: 39801207 | M102: 13192587 | N102: 39801207 | Q102: 13192587 | R102: 39801207 | S102: -26608620
A103: 3-01-01-01-011 | B103: Tdh Fund Balance | C103: 3-01-01-01-011-Tdh Fund BalanceTDH | D103: Balance Sheet | E103: Fund Balance | F103: Fund Balance | G103: Fund Balance | H103: TDH | I103: 0 | J103: 197501 | M103: 0 | N103: 197501 | Q103: 0 | R103: 197501 | S103: -197501
A104: 3-01-01-01-010 | B104: Short Term Fund Balance | C104: 3-01-01-01-010-Short Term Fund BalanceSHORT PROJECTS | D104: Balance Sheet | E104: Fund Balance | F104: Fund Balance | G104: Fund Balance | H104: SHORT PROJECTS | I104: 0 | J104: 7009823.8 | M104: 0 | N104: 7009823.8 | Q104: 0 | R104: 7009823.8 | S104: -7009823.8
A105: 3-01-01-01-008 | B105: Icco Project Fund Balance | C105: 3-01-01-01-008-Icco Project Fund BalanceICCO | D105: Balance Sheet | E105: Fund Balance | F105: Fund Balance | G105: Fund Balance | H105: ICCO | I105: 40031.77 | J105: 0 | M105: 40031.77 | N105: 0 | Q105: 40031.77 | R105: 0 | S105: 40031.77
A106: 3-01-01-01-007 | B106: Taf Fund Balance | C106: 3-01-01-01-007-Taf Fund BalanceTAF | D106: Balance Sheet | E106: Fund Balance | F106: Fund Balance | G106: Fund Balance | H106: TAF | I106: 0 | J106: 143742 | M106: 0 | N106: 143742 | Q106: 0 | R106: 143742 | S106: -143742
A107: 3-01-01-01-006 | B107: Icco Pak Fund Balance | C107: 3-01-01-01-006-Icco Pak Fund BalanceICCO Pak | D107: Balance Sheet | E107: Fund Balance | F107: Fund Balance | G107: Fund Balance | H107: ICCO Pak | I107: 0 | J107: 232 | M107: 0 | N107: 232 | Q107: 0 | R107: 232 | S107: -232
A108: 3-01-01-01-005 | B108: Tdh Pak Fund Balance | C108: 3-01-01-01-005-Tdh Pak Fund BalanceTDH Pak | D108: Balance Sheet | E108: Fund Balance | F108: Fund Balance | G108: Fund Balance | H108: TDH Pak | I108: 0 | J108: 160 | M108: 0 | N108: 160 | Q108: 0 | R108: 160 | S108: -160
A109: 3-01-01-01-004 | B109: Trocaire Fund Balance | C109: 3-01-01-01-004-Trocaire Fund BalanceTrocaire | D109: Balance Sheet | E109: Fund Balance | F109: Fund Balance | G109: Fund Balance | H109: Trocaire | I109: 131573.38 | M109: 131573.38 | N109: 0 | Q109: 131573.38 | R109: 0 | S109: 131573.38
A110: 3-01-01-01-003 | B110: Tdh-Mi Fund Balance | C110: 3-01-01-01-003-Tdh-Mi Fund BalanceTDH & MI | D110: Balance Sheet | E110: Fund Balance | F110: Fund Balance | G110: Fund Balance | H110: TDH & MI | J110: 1059129 | M110: 0 | N110: 1059129 | Q110: 0 | R110: 1059129 | S110: -1059129
A111: 3-01-01-01-002 | B111: Promoting Fund Balance | C111: 3-01-01-01-002-Promoting Fund BalanceRRCCHR | D111: Balance Sheet | E111: Fund Balance | F111: Fund Balance | G111: Fund Balance | H111: RRCCHR | I111: 15118.65 | J111: 18934.35 | M111: 15118.65 | N111: 18934.35 | Q111: 15118.65 | R111: 18934.35 | S111: -3815.7
A112: 3-01-01-01-002 | B112: Promoting Fund Balance | C112: 3-01-01-01-002-Promoting Fund BalanceUNICEF-3 | D112: Balance Sheet | E112: Fund Balance | F112: Fund Balance | G112: Fund Balance | H112: UNICEF-3 | I112: 0 | J112: 113902 | M112: 0 | N112: 113902 | Q112: 0 | R112: 113902 | S112: -113902
A113: 3-01-01-01-002 | B113: Promoting Fund Balance | C113: 3-01-01-01-002-Promoting Fund BalanceUNICEF-2 | D113: Balance Sheet | E113: Fund Balance | F113: Fund Balance | G113: Fund Balance | H113: UNICEF-2 | I113: 0 | J113: 19686 | M113: 0 | N113: 19686 | Q113: 0 | R113: 19686 | S113: -19686
A114: 3-01-01-01-002 | B114: Promoting Fund Balance | C114: 3-01-01-01-002-Promoting Fund BalanceUnicef | D114: Balance Sheet | E114: Fund Balance | F114: Fund Balance | G114: Fund Balance | H114: Unicef | I114: 340760 | J114: 0 | M114: 340760 | N114: 0 | Q114: 340760 | R114: 0 | S114: 340760
A115: 3-01-01-01-001 | B115: Fund Balance | C115: 3-01-01-01-001-Fund BalanceDAI | D115: Balance Sheet | E115: Fund Balance | F115: Fund Balance | G115: Fund Balance | H115: DAI | I115: 63863.55 | J115: 3539881.5 | M115: 63863.55 | N115: 3539881.5 | Q115: 63863.55 | R115: 3539881.5 | S115: -3476017.9
A116: 3-01-01-01-001 | B116: Fund Balance | C116: 3-01-01-01-001-Fund BalanceFOSI | D116: Balance Sheet | E116: Fund Balance | F116: Fund Balance | G116: Fund Balance | H116: FOSI | I116: 0 | J116: 1 | M116: 0 | N116: 1 | Q116: 0 | R116: 1 | S116: -1
A117: 3-01-01-01-001 | B117: Fund Balance | C117: 3-01-01-01-001-Fund BalanceFNV | D117: Balance Sheet | E117: Fund Balance | F117: Fund Balance | G117: Fund Balance | H117: FNV | I117: 0 | J117: 1321436.4 | M117: 0 | N117: 1321436.4 | Q117: 0 | R117: 1321436.4 | S117: -1321436.4
A118: 3-01-01-01-001 | B118: Fund Balance | C118: 3-01-01-01-001-Fund BalanceETI | D118: Balance Sheet | E118: Fund Balance | F118: Fund Balance | G118: Fund Balance | H118: ETI | I118: 0 | J118: 1847601.5 | M118: 0 | N118: 1847601.5 | Q118: 0 | R118: 1847601.5 | S118: -1847601.5
A119: 1-02-02-06-001 | B119: Furniture & Fixtures | C119: 1-02-02-06-001-Furniture & FixturesGRC | D119: Balance Sheet | E119: Non Current Assets | F119: Tangible | G119: Furniture And Fixture | H119: GRC | I119: 170000 | J119: 170000 | M119: 170000 | N119: 170000 | Q119: 170000 | R119: 170000 | S119: 0
A120: 1-02-02-06-001 | B120: FURNITURE & FIXTURES | C120: 1-02-02-06-001-FURNITURE & FIXTURESPILER | D120: Balance Sheet | E120: Non Current Assets | F120: Tangible | G120: Furniture And Fixture | H120: PILER | I120: 868377 | J120: 0 | K120: 0 | L120: 0 | M120: 868377 | N120: 0 | Q120: 868377 | R120: 0 | S120: 868377
A121: 1-02-02-03-001 | B121: GENERATORS | C121: 1-02-02-03-001-GENERATORSPILER | D121: Balance Sheet | E121: Non Current Assets | F121: Tangible | G121: Generator | H121: PILER | I121: 1244075 | J121: 0 | K121: 0 | L121: 0 | M121: 1244075 | N121: 0 | Q121: 1244075 | R121: 0 | S121: 1244075
A122: 2-02-01-01-02 | B122: Payable to Indus Solar Intl | C122: 2-02-01-01-02-Payable to Indus Solar IntlPILER | D122: Balance Sheet | E122: Non Current Liabilities | F122: Liabilities Against Assets Subject To Finance Lease | G122: Lease Payable | H122: PILER | I122: 105750 | J122: 615750 | K122: 0 | L122: 0 | M122: 105750 | N122: 615750 | Q122: 105750 | R122: 615750 | S122: -510000
...

Sheet Pivot 2025
A3: Row Labels | B3: Sum of Debit5 | C3: Sum of Credit5 | D3: Sum of Amount
A4: - | B4: 1.0794097e+08 | C4: 1.0794097e+08 | D4: 0.47
A5: Inter Project Balances | B5: 1.0794097e+08 | C5: 1.0794097e+08 | D5: 0.47
A6: Inter Project Balances | B6: 1.0794097e+08 | C6: 1.0794097e+08 | D6: 0.47
A7: Inter Project Balances | B7: 1.0794097e+08 | C7: 1.0794097e+08 | D7: 0.47
A8: Balance Sheet | B8: 4.065747e+08 | C8: 4.0319681e+08 | D8: 3377886.1
A9: Current Assets | B9: 1.8015129e+08 | C9: 1.7190403e+08 | D9: 8247263.5
A10: Current Liabilities | B10: 98013100 | C10: 1.4809864e+08 | D10: -50085538
A11: Accrued, Payables And Other Liabilities | B11: 45186488 | C11: 54481011 | D11: -9294522.9
A12: Accrued Expenses | B12: 37889061 | C12: 43990714 | D12: -6101652.6
A13: Other Liabilities | B13: 7297427 | C13: 10490297 | D13: -3192870.3
A14: Provision for taxation | B14: 0 | C14: 0 | D14: 0
A15: Short Term Liabilities | B15: 52826612 | C15: 93617627 | D15: -40791015
... A210: Grand Total | B210: 5.6205653e+08 | C210: 5.6205653e+08 | D210: 0.85163715

Sheet Trial Balance June 2025
A1: Pakistan Inst. of Labour Edu & Research | AD1: 5-01-02-74-004
A2: Six Column Trial Balance | J2: =J3-J4 -> 16140068 | AD2: 5-01-02-74-005
A3: For the year ended June 30, 2023 | I3: . | J3: 16140069 | AD3: 2-01-01-02-033
J4: =+I5-J5 -> 0.82163721 | L4: =+K5-L5 -> 0.029999986 | N4: =+M5-N5 -> 0.85163724 | P4: =+O5-P5 -> 0 | R4: =+Q5-R5 -> 0.85163736 | U4: =U5-S5 -> 15418234
I5: =SUBTOTAL(9,I9:I522) -> 4.4686625e+08 | J5: =SUBTOTAL(9,J9:J522) -> 4.4686625e+08 | K5: =SUBTOTAL(9,K9:K522) -> 1.1032708e+08 | L5: =SUBTOTAL(9,L9:L522) -> 1.1032708e+08 | M5: =SUBTOTAL(9,M9:M522) -> 5.5719334e+08 | N5: =SUBTOTAL(9,N9:N522) -> 5.5719333e+08 | O5: =SUBTOTAL(9,O9:O522) -> 4863198.3 | P5: =SUBTOTAL(9,P9:P522) -> 4863198.3 | ... S5: =SUBTOTAL(9,S9:S522) -> 0.85163716 | U5: 15418235
W6: =+V7-W7 -> 21386082 | Y6: =+X7-Y7 -> -34593.96 | AA6: =+Z7-AA7 -> -1.86 | AC6: =+AB7-AC7 -> 356829.1 | AE6: =+AD7-AE7 -> 8568.63 | AG6: =+AF7-AG7 -> -286659.63 | AI6: =+AH7-AI7 -> 20000 | AK6: =+AJ7-AK7 -> 1179824.2 | AM6: =+AL7-AM7 -> 0 | AO6: =+AN7-AO7 -> -247794.3 | AQ6: =+AP7-AQ7 -> -19.09 | AS6: =+AR7-AS7 -> 171767.25 | AU6: =+AT7-AU7 -> 70335.04 | AW6: =+AV7-AW7 -> -20757003 | AY6: =+AX7-AY7 -> 100.1 | BA6: =+AZ7-BA7 -> -4039.55 | BC6: =+BB7-BC7 -> -753174.34 | BE6: =+BD7-BE7 -> -50200.23 | BG6: =+BF7-BG7 -> 1674159
A7: Account Code | B7: Account Description | C7: Title | D7: FSL1 | E7: FSL2 | F7: Accrued, Payables And Other Liabilities | G7: FSL 4 | H7: Cost center | I7: Opening Balance | K7: Current Activity | M7: Closing Balance | O7: Adjustments | Q7: Adjusted Closing Balance | S7: Net balance | V7: =SUBTOTAL(9,V9:V522) -> 3.281445e+08 | W7: =SUBTOTAL(9,W9:W522) -> 3.0675842e+08 | X7: =SUBTOTAL(9,X9:X522) -> 2155230 | Y7: =SUBTOTAL(9,Y9:Y522) -> 2189824 | Z7: =SUBTOTAL(9,Z9:Z522) -> 5377732.1 | AA7: =SUBTOTAL(9,AA9:AA522) -> 5377734 | AB7: =SUBTOTAL(9,AB9:AB522) -> 793328.2 | AC7: =SUBTOTAL(9,AC9:AC522) -> 436499.1 | ... BG7: =SUBTOTAL(9,BG9:BG522) -> 2642556
A8: Account Code | B8: Account Description | C8: Title | D8: FSL1 | E8: FSL2 | F8: FSL3 | G8: FSL 4 | H8: Cost center | I8: Debit | J8: Credit | K8: Debit | L8: Credit | M8: Debit | N8: Credit | O8: Debit | P8: Credit | Q8: Debit | R8: Credit | S8: Amount | V8: PILER | X8: TDH & MI | Z8: TDH | AB8: TAF | AD8: ETI | AF8: UNICEF-2 | AH8: UNICEF-3 | AJ8: Trocaire | AL8: FOSI | AN8: DAI | AP8: Deezire | AR8: FNV | AT8: ICCO Pak | AV8: Open Society | AX8: TDH Pak | AZ8: RRCCHR | BB8: SHORT PROJECTS | BD8: ICCO | BF8: Unicef
A9: 1-01-01-01-001 | B9: CASH IN HAND | C9: 1-01-01-01-001-CASH IN HANDPILER | D9: Balance Sheet | E9: Current Assets | F9: Cash And Bank Balances | G9: Cash With Banks In Current/Pls Accounts | H9: PILER | I9: 3 | K9: 0 | L9: 0 | M9: =+I9+K9 -> 3 | N9: =+J9+L9 -> 0 | Q9: =+M9+O9 -> 3 | R9: =+N9+P9 -> 0 | S9: =+Q9-R9 -> 3 | V9: =IF($V$8=$H9,$Q9,0) -> 3 | W9: =IF($V$8=$H9,$R9,0) -> 0 | X9: =IF($X$8=$H9,$Q9,0) -> 0 | Y9: =IF($X$8=$H9,$R9,0) -> 0 | Z9: =IF($Z$8=$H9,$Q9,0) -> 0 | AA9: =IF($Z$8=$H9,$R9,0) -> 0 | AB9: =IF($AB$8=$H9,$Q9,0) -> 0 | AC9: =IF($AB$8=$H9,$R9,0) -> 0 | AD9: =IF($AD$8=$H9,$Q9,0) -> 0 | AE9: =IF($AD$8=$H9,$R9,0) -> 0 | AF9: =IF($AF$8=$H9,$Q9,0) -> 0 | AG9: =IF($AF$8=$H9,$R9,0) -> 0 | AH9: =IF($AH$8=$H9,$Q9,0) -> 0 | AI9: =IF($AH$8=$H9,$R9,0) -> 0 | AJ9: =IF($AJ$8=$H9,$Q9,0) -> 0 | AK9: =IF($AJ$8=$H9,$R9,0) -> 0 | AL9: =IF($AL$8=$H9,$Q9,0) -> 0 | AM9: =IF($AL$8=$H9,$R9,0) -> 0 | AN9: =IF($AN$8=$H9,$Q9,0) -> 0 | AO9: =IF($AN$8=$H9,$R9,0) -> 0 | AP9: =IF($AP$8=$H9,$Q9,0) -> 0 | AQ9: =IF($AP$8=$H9,$R9,0) -> 0 | AR9: =IF($AR$8=$H9,$Q9,0) -> 0 | AS9: =IF($AR$8=$H9,$R9,0) -> 0 | AT9: =IF($AT$8=$H9,$Q9,0) -> 0 | AU9: =IF($AT$8=$H9,$R9,0) -> 0 | AV9: =IF($AV$8=$H9,$Q9,0) -> 0 | AW9: =IF($AV$8=$H9,$R9,0) -> 0 | AX9: =IF($AX$8=$H9,$Q9,0) -> 0 | AY9: =IF($AX$8=$H9,$R9,0) -> 0 | AZ9: =IF($AZ$8=$H9,$Q9,0) -> 0 | BA9: =IF($AZ$8=$H9,$R9,0) -> 0 | BB9: =IF($BB$8=$H9,$Q9,0) -> 0 | BC9: =IF($BB$8=$H9,$R9,0) -> 0 | BD9: =IF($BD$8=$H9,$Q9,0) -> 0 | BE9: =IF($BD$8=$H9,$R9,0) -> 0 | BF9: =IF($BF$8=$H9,$Q9,0) -> 0 | BG9: =IF($BF$8=$H9,$R9,0) -> 0
A10: 1-01-01-01-001 | B10: CASH IN HAND | C10: 1-01-01-01-001-CASH IN HANDKarachi | D10: Balance Sheet | E10: Current Assets | F10: Cash And Bank Balances | G10: Cash With Banks In Current/Pls Accounts | H10: Karachi | I10: 0 | J10: 0 | K10: 0 | L10: 0 | M10: =+I10+K10 -> 0 | N10: =+J10+L10 -> 0 | Q10: =+M10+O10 -> 0 | R10: =+N10+P10 -> 0 | S10: =+Q10-R10 -> 0 | V10: =IF($V$8=$H10,$Q10,0) -> 0 | W10: =IF($V$8=$H10,$R10,0) -> 0 | X10: =IF($X$8=$H10,$Q10,0) -> 0 | Y10: =IF($X$8=$H10,$R10,0) -> 0 | Z10: =IF($Z$8=$H10,$Q10,0) -> 0 | AA10: =IF($Z$8=$H10,$R10,0) -> 0 | AB10: =IF($AB$8=$H10,$Q10,0) -> 0 | AC10: =IF($AB$8=$H10,$R10,0) -> 0 | AD10: =IF($AD$8=$H10,$Q10,0) -> 0 | AE10: =IF($AD$8=$H10,$R10,0) -> 0 | AF10: =IF($AF$8=$H10,$Q10,0) -> 0 | AG10: =IF($AF$8=$H10,$R10,0) -> 0 | AH10: =IF($AH$8=$H10,$Q10,0) -> 0 | AI10: =IF($AH$8=$H10,$R10,0) -> 0 | AJ10: =IF($AJ$8=$H10,$Q10,0) -> 0 | AK10: =IF($AJ$8=$H10,$R10,0) -> 0 | AL10: =IF($AL$8=$H10,$Q10,0) -> 0 | AM10: =IF($AL$8=$H10,$R10,0) -> 0 | AN10: =IF($AN$8=$H10,$Q10,0) -> 0 | AO10: =IF($AN$8=$H10,$R10,0) -> 0 | AP10: =IF($AP$8=$H10,$Q10,0) -> 0 | AQ10: =IF($AP$8=$H10,$R10,0) -> 0 | AR10: =IF($AR$8=$H10,$Q10,0) -> 0 | AS10: =IF($AR$8=$H10,$R10,0) -> 0 | AT10: =IF($AT$8=$H10,$Q10,0) -> 0 | AU10: =IF($AT$8=$H10,$R10,0) -> 0 | AV10: =IF($AV$8=$H10,$Q10,0) -> 0 | AW10: =IF($AV$8=$H10,$R10,0) -> 0 | AX10: =IF($AX$8=$H10,$Q10,0) -> 0 | AY10: =IF($AX$8=$H10,$R10,0) -> 0 | AZ10: =IF($AZ$8=$H10,$Q10,0) -> 0 | BA10: =IF($AZ$8=$H10,$R10,0) -> 0 | BB10: =IF($BB$8=$H10,$Q10,0) -> 0 | BC10: =IF($BB$8=$H10,$R10,0) -> 0 | BD10: =IF($BD$8=$H10,$Q10,0) -> 0 | BE10: =IF($BD$8=$H10,$R10,0) -> 0 | BF10: =IF($BF$8=$H10,$Q10,0) -> 0 | BG10: =IF($BF$8=$H10,$R10,0) -> 0
A11: 1-01-01-02-002 | B11: PILER OWN BAHL A/C. 818-04-2 | C11: 1-01-01-02-002-PILER OWN BAHL A/C. 818-04-2PILER | D11: Balance Sheet | E11: Current Assets | F11: Cash And Bank Balances | G11: Cash With Banks In Current/Pls Accounts | H11: PILER | I11: 143120 | J11: 0 | K11: 0 | L11: 0 | M11: =+I11+K11 -> 143120 | N11: =+J11+L11 -> 0 | Q11: =+M11+O11 -> 143120 | R11: =+N11+P11 -> 0 | S11: =+Q11-R11 -> 143120 | V11: =IF($V$8=$H11,$Q11,0) -> 143120 | W11: =IF($V$8=$H11,$R11,0) -> 0 | X11: =IF($X$8=$H11,$Q11,0) -> 0 | Y11: =IF($X$8=$H11,$R11,0) -> 0 | Z11: =IF($Z$8=$H11,$Q11,0) -> 0 | AA11: =IF($Z$8=$H11,$R11,0) -> 0 | AB11: =IF($AB$8=$H11,$Q11,0) -> 0 | AC11: =IF($AB$8=$H11,$R11,0) -> 0 | AD11: =IF($AD$8=$H11,$Q11,0) -> 0 | AE11: =IF($AD$8=$H11,$R11,0) -> 0 | AF11: =IF($AF$8=$H11,$Q11,0) -> 0 | AG11: =IF($AF$8=$H11,$R11,0) -> 0 | AH11: =IF($AH$8=$H11,$Q11,0) -> 0 | AI11: =IF($AH$8=$H11,$R11,0) -> 0 | AJ11: =IF($AJ$8=$H11,$Q11,0) -> 0 | AK11: =IF($AJ$8=$H11,$R11,0) -> 0 | AL11: =IF($AL$8=$H11,$Q11,0) -> 0 | AM11: =IF($AL$8=$H11,$R11,0) -> 0 | AN11: =IF($AN$8=$H11,$Q11,0) -> 0 | AO11: =IF($AN$8=$H11,$R11,0) -> 0 | AP11: =IF($AP$8=$H11,$Q11,0) -> 0 | AQ11: =IF($AP$8=$H11,$R11,0) -> 0 | AR11: =IF($AR$8=$H11,$Q11,0) -> 0 | AS11: =IF($AR$8=$H11,$R11,0) -> 0 | AT11: =IF($AT$8=$H11,$Q11,0) -> 0 | AU11: =IF($AT$8=$H11,$R11,0) -> 0 | AV11: =IF($AV$8=$H11,$Q11,0) -> 0 | AW11: =IF($AV$8=$H11,$R11,0) -> 0 | AX11: =IF($AX$8=$H11,$Q11,0) -> 0 | AY11: =IF($AX$8=$H11,$R11,0) -> 0 | AZ11: =IF($AZ$8=$H11,$Q11,0) -> 0 | BA11: =IF($AZ$8=$H11,$R11,0) -> 0 | BB11: =IF($BB$8=$H11,$Q11,0) -> 0 | BC11: =IF($BB$8=$H11,$R11,0) -> 0 | BD11: =IF($BD$8=$H11,$Q11,0) -> 0 | BE11: =IF($BD$8=$H11,$R11,0) -> 0 | BF11: =IF($BF$8=$H11,$Q11,0) -> 0 | BG11: =IF($BF$8=$H11,$R11,0) -> 0
A12: 1-01-01-02-011 | B12: PILER TDH & MI BH A/C.818-09-7 | C12: 1-01-01-02-011-PILER TDH & MI BH A/C.818-09-7TDH & MI | D12: Balance Sheet | E12: Current Assets | F12: Cash And Bank Balances | G12: Cash With Banks In Current/Pls Accounts | H12: TDH & MI | I12: 0 | J12: 809205 | K12: 0 | L12: 0 | M12: =+I12+K12 -> 0 | N12: =+J12+L12 -> 809205 | Q12: =+M12+O12 -> 0 | R12: =+N12+P12 -> 809205 | S12: =+Q12-R12 -> -809205 | V12: =IF($V$8=$H12,$Q12,0) -> 0 | W12: =IF($V$8=$H12,$R12,0) -> 0 | X12: =IF($X$8=$H12,$Q12,0) -> 0 | Y12: =IF($X$8=$H12,$R12,0) -> 809205 | Z12: =IF($Z$8=$H12,$Q12,0) -> 0 | AA12: =IF($Z$8=$H12,$R12,0) -> 0 | AB12: =IF($AB$8=$H12,$Q12,0) -> 0 | AC12: =IF($AB$8=$H12,$R12,0) -> 0 | AD12: =IF($AD$8=$H12,$Q12,0) -> 0 | AE12: =IF($AD$8=$H12,$R12,0) -> 0 | AF12: =IF($AF$8=$H12,$Q12,0) -> 0 | AG12: =IF($AF$8=$H12,$R12,0) -> 0 | AH12: =IF($AH$8=$H12,$Q12,0) -> 0 | AI12: =IF($AH$8=$H12,$R12,0) -> 0 | AJ12: =IF($AJ$8=$H12,$Q12,0) -> 0 | AK12: =IF($AJ$8=$H12,$R12,0) -> 0 | AL12: =IF($AL$8=$H12,$Q12,0) -> 0 | AM12: =IF($AL$8=$H12,$R12,0) -> 0 | AN12: =IF($AN$8=$H12,$Q12,0) -> 0 | AO12: =IF($AN$8=$H12,$R12,0) -> 0 | AP12: =IF($AP$8=$H12,$Q12,0) -> 0 | AQ12: =IF($AP$8=$H12,$R12,0) -> 0 | AR12: =IF($AR$8=$H12,$Q12,0) -> 0 | AS12: =IF($AR$8=$H12,$R12,0) -> 0 | AT12: =IF($AT$8=$H12,$Q12,0) -> 0 | AU12: =IF($AT$8=$H12,$R12,0) -> 0 | AV12: =IF($AV$8=$H12,$Q12,0) -> 0 | AW12: =IF($AV$8=$H12,$R12,0) -> 0 | AX12: =IF($AX$8=$H12,$Q12,0) -> 0 | AY12: =IF($AX$8=$H12,$R12,0) -> 0 | AZ12: =IF($AZ$8=$H12,$Q12,0) -> 0 | BA12: =IF($AZ$8=$H12,$R12,0) -> 0 | BB12: =IF($BB$8=$H12,$Q12,0) -> 0 | BC12: =IF($BB$8=$H12,$R12,0) -> 0 | BD12: =IF($BD$8=$H12,$Q12,0) -> 0 | BE12: =IF($BD$8=$H12,$R12,0) -> 0 | BF12: =IF($BF$8=$H12,$Q12,0) -> 0 | BG12: =IF($BF$8=$H12,$R12,0) -> 0
A13: 1-01-01-02-011 | B13: PILER TDH & MI BH A/C.818-09-7 | C13: 1-01-01-02-011-PILER TDH & MI BH A/C.818-09-7TDH | D13: Balance Sheet | E13: Current Assets | F13: Cash And Bank Balances | G13: Cash With Banks In Current/Pls Accounts | H13: TDH | I13: 581067 | J13: 0 | K13: 0 | L13: 0 | M13: =+I13+K13 -> 581067 | N13: =+J13+L13 -> 0 | Q13: =+M13+O13 -> 581067 | R13: =+N13+P13 -> 0 | S13: =+Q13-R13 -> 581067 | V13: =IF($V$8=$H13,$Q13,0) -> 0 | W13: =IF($V$8=$H13,$R13,0) -> 0 | X13: =IF($X$8=$H13,$Q13,0) -> 0 | Y13: =IF($X$8=$H13,$R13,0) -> 0 | Z13: =IF($Z$8=$H13,$Q13,0) -> 581067 | AA13: =IF($Z$8=$H13,$R13,0) -> 0 | AB13: =IF($AB$8=$H13,$Q13,0) -> 0 | AC13: =IF($AB$8=$H13,$R13,0) -> 0 | AD13: =IF($AD$8=$H13,$Q13,0) -> 0 | AE13: =IF($AD$8=$H13,$R13,0) -> 0 | AF13: =IF($AF$8=$H13,$Q13,0) -> 0 | AG13: =IF($AF$8=$H13,$R13,0) -> 0 | AH13: =IF($AH$8=$H13,$Q13,0) -> 0 | AI13: =IF($AH$8=$H13,$R13,0) -> 0 | AJ13: =IF($AJ$8=$H13,$Q13,0) -> 0 | AK13: =IF($AJ$8=$H13,$R13,0) -> 0 | AL13: =IF($AL$8=$H13,$Q13,0) -> 0 | AM13: =IF($AL$8=$H13,$R13,0) -> 0 | AN13: =IF($AN$8=$H13,$Q13,0) -> 0 | AO13: =IF($AN$8=$H13,$R13,0) -> 0 | AP13: =IF($AP$8=$H13,$Q13,0) -> 0 | AQ13: =IF($AP$8=$H13,$R13,0) -> 0 | AR13: =IF($AR$8=$H13,$Q13,0) -> 0 | AS13: =IF($AR$8=$H13,$R13,0) -> 0 | AT13: =IF($AT$8=$H13,$Q13,0) -> 0 | AU13: =IF($AT$8=$H13,$R13,0) -> 0 | AV13: =IF($AV$8=$H13,$Q13,0) -> 0 | AW13: =IF($AV$8=$H13,$R13,0) -> 0 | AX13: =IF($AX$8=$H13,$Q13,0) -> 0 | AY13: =IF($AX$8=$H13,$R13,0) -> 0 | AZ13: =IF($AZ$8=$H13,$Q13,0) -> 0 | BA13: =IF($AZ$8=$H13,$R13,0) -> 0 | BB13: =IF($BB$8=$H13,$Q13,0) -> 0 | BC13: =IF($BB$8=$H13,$R13,0) -> 0 | BD13: =IF($BD$8=$H13,$Q13,0) -> 0 | BE13: =IF($BD$8=$H13,$R13,0) -> 0 | BF13: =IF($BF$8=$H13,$Q13,0) -> 0 | BG13: =IF($BF$8=$H13,$R13,0) -> 0
A14: 1-01-01-02-012 | B14: PILER UBL-012-1940-6 | C14: 1-01-01-02-012-PILER UBL-012-1940-6PILER | D14: Balance Sheet | E14: Current Assets | F14: Cash And Bank Balances | G14: Cash With Banks In Current/Pls Accounts | H14: PILER | I14: 62500 | J14: 0 | K14: 0 | L14: 0 | M14: =+I14+K14 -> 62500 | N14: =+J14+L14 -> 0 | Q14: =+M14+O14 -> 62500 | R14: =+N14+P14 -> 0 | S14: =+Q14-R14 -> 62500 | V14: =IF($V$8=$H14,$Q14,0) -> 62500 | W14: =IF($V$8=$H14,$R14,0) -> 0 | X14: =IF($X$8=$H14,$Q14,0) -> 0 | Y14: =IF($X$8=$H14,$R14,0) -> 0 | Z14: =IF($Z$8=$H14,$Q14,0) -> 0 | AA14: =IF($Z$8=$H14,$R14,0) -> 0 | AB14: =IF($AB$8=$H14,$Q14,0) -> 0 | AC14: =IF($AB$8=$H14,$R14,0) -> 0 | AD14: =IF($AD$8=$H14,$Q14,0) -> 0 | AE14: =IF($AD$8=$H14,$R14,0) -> 0 | AF14: =IF($AF$8=$H14,$Q14,0) -> 0 | AG14: =IF($AF$8=$H14,$R14,0) -> 0 | AH14: =IF($AH$8=$H14,$Q14,0) -> 0 | AI14: =IF($AH$8=$H14,$R14,0) -> 0 | AJ14: =IF($AJ$8=$H14,$Q14,0) -> 0 | AK14: =IF($AJ$8=$H14,$R14,0) -> 0 | AL14: =IF($AL$8=$H14,$Q14,0) -> 0 | AM14: =IF($AL$8=$H14,$R14,0) -> 0 | AN14: =IF($AN$8=$H14,$Q14,0) -> 0 | AO14: =IF($AN$8=$H14,$R14,0) -> 0 | AP14: =IF($AP$8=$H14,$Q14,0) -> 0 | AQ14: =IF($AP$8=$H14,$R14,0) -> 0 | AR14: =IF($AR$8=$H14,$Q14,0) -> 0 | AS14: =IF($AR$8=$H14,$R14,0) -> 0 | AT14: =IF($AT$8=$H14,$Q14,0) -> 0 | AU14: =IF($AT$8=$H14,$R14,0) -> 0 | AV14: =IF($AV$8=$H14,$Q14,0) -> 0 | AW14: =IF($AV$8=$H14,$R14,0) -> 0 | AX14: =IF($AX$8=$H14,$Q14,0) -> 0 | AY14: =IF($AX$8=$H14,$R14,0) -> 0 | AZ14: =IF($AZ$8=$H14,$Q14,0) -> 0 | BA14: =IF($AZ$8=$H14,$R14,0) -> 0 | BB14: =IF($BB$8=$H14,$Q14,0) -> 0 | BC14: =IF($BB$8=$H14,$R14,0) -> 0 | BD14: =IF($BD$8=$H14,$Q14,0) -> 0 | BE14: =IF($BD$8=$H14,$R14,0) -> 0 | BF14: =IF($BF$8=$H14,$Q14,0) -> 0 | BG14: =IF($BF$8=$H14,$R14,0) -> 0
A15: 1-01-01-02-013 | B15: PILER UBL-012-1707-3 | C15: 1-01-01-02-013-PILER UBL-012-1707-3PILER | D15: Balance Sheet | E15: Current Assets | F15: Cash And Bank Balances | G15: Cash With Banks In Current/Pls Accounts | H15: PILER | I15: 51853 | J15: 0 | K15: 0 | L15: 0 | M15: =+I15+K15 -> 51853 | N15: =+J15+L15 -> 0 | Q15: =+M15+O15 -> 51853 | R15: =+N15+P15 -> 0 | S15: =+Q15-R15 -> 51853 | V15: =IF($V$8=$H15,$Q15,0) -> 51853 | W15: =IF($V$8=$H15,$R15,0) -> 0 | X15: =IF($X$8=$H15,$Q15,0) -> 0 | Y15: =IF($X$8=$H15,$R15,0) -> 0 | Z15: =IF($Z$8=$H15,$Q15,0) -> 0 | AA15: =IF($Z$8=$H15,$R15,0) -> 0 | AB15: =IF($AB$8=$H15,$Q15,0) -> 0 | AC15: =IF($AB$8=$H15,$R15,0) -> 0 | AD15: =IF($AD$8=$H15,$Q15,0) -> 0 | AE15: =IF($AD$8=$H15,$R15,0) -> 0 | AF15: =IF($AF$8=$H15,$Q15,0) -> 0 | AG15: =IF($AF$8=$H15,$R15,0) -> 0 | AH15: =IF($AH$8=$H15,$Q15,0) -> 0 | AI15: =IF($AH$8=$H15,$R15,0) -> 0 | AJ15: =IF($AJ$8=$H15,$Q15,0) -> 0 | AK15: =IF($AJ$8=$H15,$R15,0) -> 0 | AL15: =IF($AL$8=$H15,$Q15,0) -> 0 | AM15: =IF($AL$8=$H15,$R15,0) -> 0 | AN15: =IF($AN$8=$H15,$Q15,0) -> 0 | AO15: =IF($AN$8=$H15,$R15,0) -> 0 | AP15: =IF($AP$8=$H15,$Q15,0) -> 0 | AQ15: =IF($AP$8=$H15,$R15,0) -> 0 | AR15: =IF($AR$8=$H15,$Q15,0) -> 0 | AS15: =IF($AR$8=$H15,$R15,0) -> 0 | AT15: =IF($AT$8=$H15,$Q15,0) -> 0 | AU15: =IF($AT$8=$H15,$R15,0) -> 0 | AV15: =IF($AV$8=$H15,$Q15,0) -> 0 | AW15: =IF($AV$8=$H15,$R15,0) -> 0 | AX15: =IF($AX$8=$H15,$Q15,0) -> 0 | AY15: =IF($AX$8=$H15,$R15,0) -> 0 | AZ15: =IF($AZ$8=$H15,$Q15,0) -> 0 | BA15: =IF($AZ$8=$H15,$R15,0) -> 0 | BB15: =IF($BB$8=$H15,$Q15,0) -> 0 | BC15: =IF($BB$8=$H15,$R15,0) -> 0 | BD15: =IF($BD$8=$H15,$Q15,0) -> 0 | BE15: =IF($BD$8=$H15,$R15,0) -> 0 | BF15: =IF($BF$8=$H15,$Q15,0) -> 0 | BG15: =IF($BF$8=$H15,$R15,0) -> 0
A16: 1-01-01-02-015 | B16: PILER FNV PROJECT 06-0 | C16: 1-01-01-02-015-PILER FNV PROJECT 06-0PILER | D16: Balance Sheet | E16: Current Assets | F16: Cash And Bank Balances | G16: Cash With Banks In Current/Pls Accounts | H16: PILER | I16: 15489 | J16: 0 | K16: 0 | L16: 0 | M16: =+I16+K16 -> 15489 | N16: =+J16+L16 -> 0 | Q16: =+M16+O16 -> 15489 | R16: =+N16+P16 -> 0 | S16: =+Q16-R16 -> 15489 | V16: =IF($V$8=$H16,$Q16,0) -> 15489 | W16: =IF($V$8=$H16,$R16,0) -> 0 | X16: =IF($X$8=$H16,$Q16,0) -> 0 | Y16: =IF($X$8=$H16,$R16,0) -> 0 | Z16: =IF($Z$8=$H16,$Q16,0) -> 0 | AA16: =IF($Z$8=$H16,$R16,0) -> 0 | AB16: =IF($AB$8=$H16,$Q16,0) -> 0 | AC16: =IF($AB$8=$H16,$R16,0) -> 0 | AD16: =IF($AD$8=$H16,$Q16,0) -> 0 | AE16: =IF($AD$8=$H16,$R16,0) -> 0 | AF16: =IF($AF$8=$H16,$Q16,0) -> 0 | AG16: =IF($AF$8=$H16,$R16,0) -> 0 | AH16: =IF($AH$8=$H16,$Q16,0) -> 0 | AI16: =IF($AH$8=$H16,$R16,0) -> 0 | AJ16: =IF($AJ$8=$H16,$Q16,0) -> 0 | AK16: =IF($AJ$8=$H16,$R16,0) -> 0 | AL16: =IF($AL$8=$H16,$Q16,0) -> 0 | AM16: =IF($AL$8=$H16,$R16,0) -> 0 | AN16: =IF($AN$8=$H16,$Q16,0) -> 0 | AO16: =IF($AN$8=$H16,$R16,0) -> 0 | AP16: =IF($AP$8=$H16,$Q16,0) -> 0 | AQ16: =IF($AP$8=$H16,$R16,0) -> 0 | AR16: =IF($AR$8=$H16,$Q16,0) -> 0 | AS16: =IF($AR$8=$H16,$R16,0) -> 0 | AT16: =IF($AT$8=$H16,$Q16,0) -> 0 | AU16: =IF($AT$8=$H16,$R16,0) -> 0 | AV16: =IF($AV$8=$H16,$Q16,0) -> 0 | AW16: =IF($AV$8=$H16,$R16,0) -> 0 | AX16: =IF($AX$8=$H16,$Q16,0) -> 0 | AY16: =IF($AX$8=$H16,$R16,0) -> 0 | AZ16: =IF($AZ$8=$H16,$Q16,0) -> 0 | BA16: =IF($AZ$8=$H16,$R16,0) -> 0 | BB16: =IF($BB$8=$H16,$Q16,0) -> 0 | BC16: =IF($BB$8=$H16,$R16,0) -> 0 | BD16: =IF($BD$8=$H16,$Q16,0) -> 0 | BE16: =IF($BD$8=$H16,$R16,0) -> 0 | BF16: =IF($BF$8=$H16,$Q16,0) -> 0 | BG16: =IF($BF$8=$H16,$R16,0) -> 0
A17: 1-01-01-02-016 | B17: PILER EU PROJECT BAHL-GJ 06-2 | C17: 1-01-01-02-016-PILER EU PROJECT BAHL-GJ 06-2PILER | D17: Balance Sheet | E17: Current Assets | F17: Cash And Bank Balances | G17: Cash With Banks In Current/Pls Accounts | H17: PILER | I17: 29198 | J17: 0 | K17: 0 | L17: 0 | M17: =+I17+K17 -> 29198 | N17: =+J17+L17 -> 0 | Q17: =+M17+O17 -> 29198 | R17: =+N17+P17 -> 0 | S17: =+Q17-R17 -> 29198 | V17: =IF($V$8=$H17,$Q17,0) -> 29198 | W17: =IF($V$8=$H17,$R17,0) -> 0 | X17: =IF($X$8=$H17,$Q17,0) -> 0 | Y17: =IF($X$8=$H17,$R17,0) -> 0 | Z17: =IF($Z$8=$H17,$Q17,0) -> 0 | AA17: =IF($Z$8=$H17,$R17,0) -> 0 | AB17: =IF($AB$8=$H17,$Q17,0) -> 0 | AC17: =IF($AB$8=$H17,$R17,0) -> 0 | AD17: =IF($AD$8=$H17,$Q17,0) -> 0 | AE17: =IF($AD$8=$H17,$R17,0) -> 0 | AF17: =IF($AF$8=$H17,$Q17,0) -> 0 | AG17: =IF($AF$8=$H17,$R17,0) -> 0 | AH17: =IF($AH$8=$H17,$Q17,0) -> 0 | AI17: =IF($AH$8=$H17,$R17,0) -> 0 | AJ17: =IF($AJ$8=$H17,$Q17,0) -> 0 | AK17: =IF($AJ$8=$H17,$R17,0) -> 0 | AL17: =IF($AL$8=$H17,$Q17,0) -> 0 | AM17: =IF($AL$8=$H17,$R17,0) -> 0 | AN17: =IF($AN$8=$H17,$Q17,0) -> 0 | AO17: =IF($AN$8=$H17,$R17,0) -> 0 | AP17: =IF($AP$8=$H17,$Q17,0) -> 0 | AQ17: =IF($AP$8=$H17,$R17,0) -> 0 | AR17: =IF($AR$8=$H17,$Q17,0) -> 0 | AS17: =IF($AR$8=$H17,$R17,0) -> 0 | AT17: =IF($AT$8=$H17,$Q17,0) -> 0 | AU17: =IF($AT$8=$H17,$R17,0) -> 0 | AV17: =IF($AV$8=$H17,$Q17,0) -> 0 | AW17: =IF($AV$8=$H17,$R17,0) -> 0 | AX17: =IF($AX$8=$H17,$Q17,0) -> 0 | AY17: =IF($AX$8=$H17,$R17,0) -> 0 | AZ17: =IF($AZ$8=$H17,$Q17,0) -> 0 | BA17: =IF($AZ$8=$H17,$R17,0) -> 0 | BB17: =IF($BB$8=$H17,$Q17,0) -> 0 | BC17: =IF($BB$8=$H17,$R17,0) -> 0 | BD17: =IF($BD$8=$H17,$Q17,0) -> 0 | BE17: =IF($BD$8=$H17,$R17,0) -> 0 | BF17: =IF($BF$8=$H17,$Q17,0) -> 0 | BG17: =IF($BF$8=$H17,$R17,0) -> 0
A18: 1-01-01-02-020 | B18: PILER BAH-A/C.0081-004762-01-0 | C18: 1-01-01-02-020-PILER BAH-A/C.0081-004762-01-0PILER | D18: Balance Sheet | E18: Current Assets | F18: Cash And Bank Balances | G18: Cash With Banks In Current/Pls Accounts | H18: PILER | I18: 42086429 | J18: 40166118 | K18: 24208666 | L18: =20793992.87+3000 -> 20796993 | M18: =+I18+K18 -> 66295095 | N18: =+J18+L18 -> 60963111 | Q18: =+M18+O18 -> 66295095 | R18: =+N18+P18 -> 60963111 | S18: =+Q18-R18 -> 5331984 | V18: =IF($V$8=$H18,$Q18,0) -> 66295095 | W18: =IF($V$8=$H18,$R18,0) -> 60963111 | X18: =IF($X$8=$H18,$Q18,0) -> 0 | Y18: =IF($X$8=$H18,$R18,0) -> 0 | Z18: =IF($Z$8=$H18,$Q18,0) -> 0 | AA18: =IF($Z$8=$H18,$R18,0) -> 0 | AB18: =IF($AB$8=$H18,$Q18,0) -> 0 | AC18: =IF($AB$8=$H18,$R18,0) -> 0 | AD18: =IF($AD$8=$H18,$Q18,0) -> 0 | AE18: =IF($AD$8=$H18,$R18,0) -> 0 | AF18: =IF($AF$8=$H18,$Q18,0) -> 0 | AG18: =IF($AF$8=$H18,$R18,0) -> 0 | AH18: =IF($AH$8=$H18,$Q18,0) -> 0 | AI18: =IF($AH$8=$H18,$R18,0) -> 0 | AJ18: =IF($AJ$8=$H18,$Q18,0) -> 0 | AK18: =IF($AJ$8=$H18,$R18,0) -> 0 | AL18: =IF($AL$8=$H18,$Q18,0) -> 0 | AM18: =IF($AL$8=$H18,$R18,0) -> 0 | AN18: =IF($AN$8=$H18,$Q18,0) -> 0 | AO18: =IF($AN$8=$H18,$R18,0) -> 0 | AP18: =IF($AP$8=$H18,$Q18,0) -> 0 | AQ18: =IF($AP$8=$H18,$R18,0) -> 0 | AR18: =IF($AR$8=$H18,$Q18,0) -> 0 | AS18: =IF($AR$8=$H18,$R18,0) -> 0 | AT18: =IF($AT$8=$H18,$Q18,0) -> 0 | AU18: =IF($AT$8=$H18,$R18,0) -> 0 | AV18: =IF($AV$8=$H18,$Q18,0) -> 0 | AW18: =IF($AV$8=$H18,$R18,0) -> 0 | AX18: =IF($AX$8=$H18,$Q18,0) -> 0 | AY18: =IF($AX$8=$H18,$R18,0) -> 0 | AZ18: =IF($AZ$8=$H18,$Q18,0) -> 0 | BA18: =IF($AZ$8=$H18,$R18,0) -> 0 | BB18: =IF($BB$8=$H18,$Q18,0) -> 0 | BC18: =IF($BB$8=$H18,$R18,0) -> 0 | BD18: =IF($BD$8=$H18,$Q18,0) -> 0 | BE18: =IF($BD$8=$H18,$R18,0) -> 0 | BF18: =IF($BF$8=$H18,$Q18,0) -> 0 | BG18: =IF($BF$8=$H18,$R18,0) -> 0
A19: 1-01-01-02-021 | B19: PILER TAF BAH-0081-004762-02-1 | C19: 1-01-01-02-021-PILER TAF BAH-0081-004762-02-1TAF | D19: Balance Sheet | E19: Current Assets | F19: Cash And Bank Balances | G19: Cash With Banks In Current/Pls Accounts | H19: TAF | I19: 381581.2 | J19: 79.1 | K19: 0 | L19: 0 | M19: =+I19+K19 -> 381581.2 | N19: =+J19+L19 -> 79.1 | Q19: =+M19+O19 -> 381581.2 | R19: =+N19+P19 -> 79.1 | S19: =+Q19-R19 -> 381502.1 | V19: =IF($V$8=$H19,$Q19,0) -> 0 | W19: =IF($V$8=$H19,$R19,0) -> 0 | X19: =IF($X$8=$H19,$Q19,0) -> 0 | Y19: =IF($X$8=$H19,$R19,0) -> 0 | Z19: =IF($Z$8=$H19,$Q19,0) -> 0 | AA19: =IF($Z$8=$H19,$R19,0) -> 0 | AB19: =IF($AB$8=$H19,$Q19,0) -> 381581.2 | AC19: =IF($AB$8=$H19,$R19,0) -> 79.1 | AD19: =IF($AD$8=$H19,$Q19,0) -> 0 | AE19: =IF($AD$8=$H19,$R19,0) -> 0 | AF19: =IF($AF$8=$H19,$Q19,0) -> 0 | AG19: =IF($AF$8=$H19,$R19,0) -> 0 | AH19: =IF($AH$8=$H19,$Q19,0) -> 0 | AI19: =IF($AH$8=$H19,$R19,0) -> 0 | AJ19: =IF($AJ$8=$H19,$Q19,0) -> 0 | AK19: =IF($AJ$8=$H19,$R19,0) -> 0 | AL19: =IF($AL$8=$H19,$Q19,0) -> 0 | AM19: =IF($AL$8=$H19,$R19,0) -> 0 | AN19: =IF($AN$8=$H19,$Q19,0) -> 0 | AO19: =IF($AN$8=$H19,$R19,0) -> 0 | AP19: =IF($AP$8=$H19,$Q19,0) -> 0 | AQ19: =IF($AP$8=$H19,$R19,0) -> 0 | AR19: =IF($AR$8=$H19,$Q19,0) -> 0 | AS19: =IF($AR$8=$H19,$R19,0) -> 0 | AT19: =IF($AT$8=$H19,$Q19,0) -> 0 | AU19: =IF($AT$8=$H19,$R19,0) -> 0 | AV19: =IF($AV$8=$H19,$Q19,0) -> 0 | AW19: =IF($AV$8=$H19,$R19,0) -> 0 | AX19: =IF($AX$8=$H19,$Q19,0) -> 0 | AY19: =IF($AX$8=$H19,$R19,0) -> 0 | AZ19: =IF($AZ$8=$H19,$Q19,0) -> 0 | BA19: =IF($AZ$8=$H19,$R19,0) -> 0 | BB19: =IF($BB$8=$H19,$Q19,0) -> 0 | BC19: =IF($BB$8=$H19,$R19,0) -> 0 | BD19: =IF($BD$8=$H19,$Q19,0) -> 0 | BE19: =IF($BD$8=$H19,$R19,0) -> 0 | BF19: =IF($BF$8=$H19,$Q19,0) -> 0 | BG19: =IF($BF$8=$H19,$R19,0) -> 0
A20: 1-01-01-02-021 | B20: PILER TAF BAH-0081-004762-02-1 | C20: 1-01-01-02-021-PILER TAF BAH-0081-004762-02-1ETI | D20: Balance Sheet | E20: Current Assets | F20: Cash And Bank Balances | G20: Cash With Banks In Current/Pls Accounts | H20: ETI | I20: 239707 | J20: 621187.48 | K20: 0 | L20: 21.62 | M20: =+I20+K20 -> 239707 | N20: =+J20+L20 -> 621209.1 | Q20: =+M20+O20 -> 239707 | R20: =+N20+P20 -> 621209.1 | S20: =+Q20-R20 -> -381502.1 | V20: =IF($V$8=$H20,$Q20,0) -> 0 | W20: =IF($V$8=$H20,$R20,0) -> 0 | X20: =IF($X$8=$H20,$Q20,0) -> 0 | Y20: =IF($X$8=$H20,$R20,0) -> 0 | Z20: =IF($Z$8=$H20,$Q20,0) -> 0 | AA20: =IF($Z$8=$H20,$R20,0) -> 0 | AB20: =IF($AB$8=$H20,$Q20,0) -> 0 | AC20: =IF($AB$8=$H20,$R20,0) -> 0 | AD20: =IF($AD$8=$H20,$Q20,0) -> 239707 | AE20: =IF($AD$8=$H20,$R20,0) -> 621209.1 | AF20: =IF($AF$8=$H20,$Q20,0) -> 0 | AG20: =IF($AF$8=$H20,$R20,0) -> 0 | AH20: =IF($AH$8=$H20,$Q20,0) -> 0 | AI20: =IF($AH$8=$H20,$R20,0) -> 0 | AJ20: =IF($AJ$8=$H20,$Q20,0) -> 0 | AK20: =IF($AJ$8=$H20,$R20,0) -> 0 | AL20: =IF($AL$8=$H20,$Q20,0) -> 0 | AM20: =IF($AL$8=$H20,$R20,0) -> 0 | AN20: =IF($AN$8=$H20,$Q20,0) -> 0 | AO20: =IF($AN$8=$H20,$R20,0) -> 0 | AP20: =IF($AP$8=$H20,$Q20,0) -> 0 | AQ20: =IF($AP$8=$H20,$R20,0) -> 0 | AR20: =IF($AR$8=$H20,$Q20,0) -> 0 | AS20: =IF($AR$8=$H20,$R20,0) -> 0 | AT20: =IF($AT$8=$H20,$Q20,0) -> 0 | AU20: =IF($AT$8=$H20,$R20,0) -> 0 | AV20: =IF($AV$8=$H20,$Q20,0) -> 0 | AW20: =IF($AV$8=$H20,$R20,0) -> 0 | AX20: =IF($AX$8=$H20,$Q20,0) -> 0 | AY20: =IF($AX$8=$H20,$R20,0) -> 0 | AZ20: =IF($AZ$8=$H20,$Q20,0) -> 0 | BA20: =IF($AZ$8=$H20,$R20,0) -> 0 | BB20: =IF($BB$8=$H20,$Q20,0) -> 0 | BC20: =IF($BB$8=$H20,$R20,0) -> 0 | BD20: =IF($BD$8=$H20,$Q20,0) -> 0 | BE20: =IF($BD$8=$H20,$R20,0) -> 0 | BF20: =IF($BF$8=$H20,$Q20,0) -> 0 | BG20: =IF($BF$8=$H20,$R20,0) -> 0
A21: 1-01-01-02-022 | B21: BANK UNICEF-0081-004762-04-3 | C21: 1-01-01-02-022-BANK UNICEF-0081-004762-04-3PILER | D21: Balance Sheet | E21: Current Assets | F21: Cash And Bank Balances | G21: Cash With Banks In Current/Pls Accounts | H21: PILER | I21: 351956.05 | J21: 347588.4 | K21: 0 | L21: 0 | M21: =+I21+K21 -> 351956.05 | N21: =+J21+L21 -> 347588.4 | Q21: =+M21+O21 -> 351956.05 | R21: =+N21+P21 -> 347588.4 | S21: =+Q21-R21 -> 4367.65 | V21: =IF($V$8=$H21,$Q21,0) -> 351956.05 | W21: =IF($V$8=$H21,$R21,0) -> 347588.4 | X21: =IF($X$8=$H21,$Q21,0) -> 0 | Y21: =IF($X$8=$H21,$R21,0) -> 0 | Z21: =IF($Z$8=$H21,$Q21,0) -> 0 | AA21: =IF($Z$8=$H21,$R21,0) -> 0 | AB21: =IF($AB$8=$H21,$Q21,0) -> 0 | AC21: =IF($AB$8=$H21,$R21,0) -> 0 | AD21: =IF($AD$8=$H21,$Q21,0) -> 0 | AE21: =IF($AD$8=$H21,$R21,0) -> 0 | AF21: =IF($AF$8=$H21,$Q21,0) -> 0 | AG21: =IF($AF$8=$H21,$R21,0) -> 0 | AH21: =IF($AH$8=$H21,$Q21,0) -> 0 | AI21: =IF($AH$8=$H21,$R21,0) -> 0 | AJ21: =IF($AJ$8=$H21,$Q21,0) -> 0 | AK21: =IF($AJ$8=$H21,$R21,0) -> 0 | AL21: =IF($AL$8=$H21,$Q21,0) -> 0 | AM21: =IF($AL$8=$H21,$R21,0) -> 0 | AN21: =IF($AN$8=$H21,$Q21,0) -> 0 | AO21: =IF($AN$8=$H21,$R21,0) -> 0 | AP21: =IF($AP$8=$H21,$Q21,0) -> 0 | AQ21: =IF($AP$8=$H21,$R21,0) -> 0 | AR21: =IF($AR$8=$H21,$Q21,0) -> 0 | AS21: =IF($AR$8=$H21,$R21,0) -> 0 | AT21: =IF($AT$8=$H21,$Q21,0) -> 0 | AU21: =IF($AT$8=$H21,$R21,0) -> 0 | AV21: =IF($AV$8=$H21,$Q21,0) -> 0 | AW21: =IF($AV$8=$H21,$R21,0) -> 0 | AX21: =IF($AX$8=$H21,$Q21,0) -> 0 | AY21: =IF($AX$8=$H21,$R21,0) -> 0 | AZ21: =IF($AZ$8=$H21,$Q21,0) -> 0 | BA21: =IF($AZ$8=$H21,$R21,0) -> 0 | BB21: =IF($BB$8=$H21,$Q21,0) -> 0 | BC21: =IF($BB$8=$H21,$R21,0) -> 0 | BD21: =IF($BD$8=$H21,$Q21,0) -> 0 | BE21: =IF($BD$8=$H21,$R21,0) -> 0 | BF21: =IF($BF$8=$H21,$Q21,0) -> 0 | BG21: =IF($BF$8=$H21,$R21,0) -> 0
A22: 1-01-01-02-022 | B22: BANK UNICEF-0081-004762-04-3 | C22: 1-01-01-02-022-BANK UNICEF-0081-004762-04-3UNICEF-2 | D22: Balance Sheet | E22: Current Assets | F22: Cash And Bank Balances | G22: Cash With Banks In Current/Pls Accounts | H22: UNICEF-2 | I22: 73944.37 | J22: 0 | K22: 0 | L22: 0 | M22: =+I22+K22 -> 73944.37 | N22: =+J22+L22 -> 0 | Q22: =+M22+O22 -> 73944.37 | R22: =+N22+P22 -> 0 | S22: =+Q22-R22 -> 73944.37 | V22: =IF($V$8=$H22,$Q22,0) -> 0 | W22: =IF($V$8=$H22,$R22,0) -> 0 | X22: =IF($X$8=$H22,$Q22,0) -> 0 | Y22: =IF($X$8=$H22,$R22,0) -> 0 | Z22: =IF($Z$8=$H22,$Q22,0) -> 0 | AA22: =IF($Z$8=$H22,$R22,0) -> 0 | AB22: =IF($AB$8=$H22,$Q22,0) -> 0 | AC22: =IF($AB$8=$H22,$R22,0) -> 0 | AD22: =IF($AD$8=$H22,$Q22,0) -> 0 | AE22: =IF($AD$8=$H22,$R22,0) -> 0 | AF22: =IF($AF$8=$H22,$Q22,0) -> 73944.37 | AG22: =IF($AF$8=$H22,$R22,0) -> 0 | AH22: =IF($AH$8=$H22,$Q22,0) -> 0 | AI22: =IF($AH$8=$H22,$R22,0) -> 0 | AJ22: =IF($AJ$8=$H22,$Q22,0) -> 0 | AK22: =IF($AJ$8=$H22,$R22,0) -> 0 | AL22: =IF($AL$8=$H22,$Q22,0) -> 0 | AM22: =IF($AL$8=$H22,$R22,0) -> 0 | AN22: =IF($AN$8=$H22,$Q22,0) -> 0 | AO22: =IF($AN$8=$H22,$R22,0) -> 0 | AP22: =IF($AP$8=$H22,$Q22,0) -> 0 | AQ22: =IF($AP$8=$H22,$R22,0) -> 0 | AR22: =IF($AR$8=$H22,$Q22,0) -> 0 | AS22: =IF($AR$8=$H22,$R22,0) -> 0 | AT22: =IF($AT$8=$H22,$Q22,0) -> 0 | AU22: =IF($AT$8=$H22,$R22,0) -> 0 | AV22: =IF($AV$8=$H22,$Q22,0) -> 0 | AW22: =IF($AV$8=$H22,$R22,0) -> 0 | AX22: =IF($AX$8=$H22,$Q22,0) -> 0 | AY22: =IF($AX$8=$H22,$R22,0) -> 0 | AZ22: =IF($AZ$8=$H22,$Q22,0) -> 0 | BA22: =IF($AZ$8=$H22,$R22,0) -> 0 | BB22: =IF($BB$8=$H22,$Q22,0) -> 0 | BC22: =IF($BB$8=$H22,$R22,0) -> 0 | BD22: =IF($BD$8=$H22,$Q22,0) -> 0 | BE22: =IF($BD$8=$H22,$R22,0) -> 0 | BF22: =IF($BF$8=$H22,$Q22,0) -> 0 | BG22: =IF($BF$8=$H22,$R22,0) -> 0
A23: 1-01-01-02-022 | B23: BANK UNICEF-0081-004762-04-3 | C23: 1-01-01-02-022-BANK UNICEF-0081-004762-04-3UNICEF-3 | D23: Balance Sheet | E23: Current Assets | F23: Cash And Bank Balances | G23: Cash With Banks In Current/Pls Accounts | H23: UNICEF-3 | I23: 0 | J23: 73924.7 | K23: 0 | L23: 0 | M23: =+I23+K23 -> 0 | N23: =+J23+L23 -> 73924.7 | Q23: =+M23+O23 -> 0 | R23: =+N23+P23 -> 73924.7 | S23: =+Q23-R23 -> -73924.7 | V23: =IF($V$8=$H23,$Q23,0) -> 0 | W23: =IF($V$8=$H23,$R23,0) -> 0 | X23: =IF($X$8=$H23,$Q23,0) -> 0 | Y23: =IF($X$8=$H23,$R23,0) -> 0 | Z23: =IF($Z$8=$H23,$Q23,0) -> 0 | AA23: =IF($Z$8=$H23,$R23,0) -> 0 | AB23: =IF($AB$8=$H23,$Q23,0) -> 0 | AC23: =IF($AB$8=$H23,$R23,0) -> 0 | AD23: =IF($AD$8=$H23,$Q23,0) -> 0 | AE23: =IF($AD$8=$H23,$R23,0) -> 0 | AF23: =IF($AF$8=$H23,$Q23,0) -> 0 | AG23: =IF($AF$8=$H23,$R23,0) -> 0 | AH23: =IF($AH$8=$H23,$Q23,0) -> 0 | AI23: =IF($AH$8=$H23,$R23,0) -> 73924.7 | AJ23: =IF($AJ$8=$H23,$Q23,0) -> 0 | AK23: =IF($AJ$8=$H23,$R23,0) -> 0 | AL23: =IF($AL$8=$H23,$Q23,0) -> 0 | AM23: =IF($AL$8=$H23,$R23,0) -> 0 | AN23: =IF($AN$8=$H23,$Q23,0) -> 0 | AO23: =IF($AN$8=$H23,$R23,0) -> 0 | AP23: =IF($AP$8=$H23,$Q23,0) -> 0 | AQ23: =IF($AP$8=$H23,$R23,0) -> 0 | AR23: =IF($AR$8=$H23,$Q23,0) -> 0 | AS23: =IF($AR$8=$H23,$R23,0) -> 0 | AT23: =IF($AT$8=$H23,$Q23,0) -> 0 | AU23: =IF($AT$8=$H23,$R23,0) -> 0 | AV23: =IF($AV$8=$H23,$Q23,0) -> 0 | AW23: =IF($AV$8=$H23,$R23,0) -> 0 | AX23: =IF($AX$8=$H23,$Q23,0) -> 0 | AY23: =IF($AX$8=$H23,$R23,0) -> 0 | AZ23: =IF($AZ$8=$H23,$Q23,0) -> 0 | BA23: =IF($AZ$8=$H23,$R23,0) -> 0 | BB23: =IF($BB$8=$H23,$Q23,0) -> 0 | BC23: =IF($BB$8=$H23,$R23,0) -> 0 | BD23: =IF($BD$8=$H23,$Q23,0) -> 0 | BE23: =IF($BD$8=$H23,$R23,0) -> 0 | BF23: =IF($BF$8=$H23,$Q23,0) -> 0 | BG23: =IF($BF$8=$H23,$R23,0) -> 0
A24: 1-01-01-02-023 | B24: BANK TROCAIRE-0081-004762-06-5 | C24: 1-01-01-02-023-BANK TROCAIRE-0081-004762-06-5Trocaire | D24: Balance Sheet | E24: Current Assets | F24: Cash And Bank Balances | G24: Cash With Banks In Current/Pls Accounts | H24: Trocaire | I24: 100.6 | J24: 79.1 | K24: 0 | L24: 0 | M24: =+I24+K24 -> 100.6 | N24: =+J24+L24 -> 79.1 | Q24: =+M24+O24 -> 100.6 | R24: =+N24+P24 -> 79.1 | S24: =+Q24-R24 -> 21.5 | V24: =IF($V$8=$H24,$Q24,0) -> 0 | W24: =IF($V$8=$H24,$R24,0) -> 0 | X24: =IF($X$8=$H24,$Q24,0) -> 0 | Y24: =IF($X$8=$H24,$R24,0) -> 0 | Z24: =IF($Z$8=$H24,$Q24,0) -> 0 | AA24: =IF($Z$8=$H24,$R24,0) -> 0 | AB24: =IF($AB$8=$H24,$Q24,0) -> 0 | AC24: =IF($AB$8=$H24,$R24,0) -> 0 | AD24: =IF($AD$8=$H24,$Q24,0) -> 0 | AE24: =IF($AD$8=$H24,$R24,0) -> 0 | AF24: =IF($AF$8=$H24,$Q24,0) -> 0 | AG24: =IF($AF$8=$H24,$R24,0) -> 0 | AH24: =IF($AH$8=$H24,$Q24,0) -> 0 | AI24: =IF($AH$8=$H24,$R24,0) -> 0 | AJ24: =IF($AJ$8=$H24,$Q24,0) -> 100.6 | AK24: =IF($AJ$8=$H24,$R24,0) -> 79.1 | AL24: =IF($AL$8=$H24,$Q24,0) -> 0 | AM24: =IF($AL$8=$H24,$R24,0) -> 0 | AN24: =IF($AN$8=$H24,$Q24,0) -> 0 | AO24: =IF($AN$8=$H24,$R24,0) -> 0 | AP24: =IF($AP$8=$H24,$Q24,0) -> 0 | AQ24: =IF($AP$8=$H24,$R24,0) -> 0 | AR24: =IF($AR$8=$H24,$Q24,0) -> 0 | AS24: =IF($AR$8=$H24,$R24,0) -> 0 | AT24: =IF($AT$8=$H24,$Q24,0) -> 0 | AU24: =IF($AT$8=$H24,$R24,0) -> 0 | AV24: =IF($AV$8=$H24,$Q24,0) -> 0 | AW24: =IF($AV$8=$H24,$R24,0) -> 0 | AX24: =IF($AX$8=$H24,$Q24,0) -> 0 | AY24: =IF($AX$8=$H24,$R24,0) -> 0 | AZ24: =IF($AZ$8=$H24,$Q24,0) -> 0 | BA24: =IF($AZ$8=$H24,$R24,0) -> 0 | BB24: =IF($BB$8=$H24,$Q24,0) -> 0 | BC24: =IF($BB$8=$H24,$R24,0) -> 0 | BD24: =IF($BD$8=$H24,$Q24,0) -> 0 | BE24: =IF($BD$8=$H24,$R24,0) -> 0 | BF24: =IF($BF$8=$H24,$Q24,0) -> 0 | BG24: =IF($BF$8=$H24,$R24,0) -> 0
A25: 1-01-01-02-023 | B25: BANK TROCAIRE-0081-004762-06-5 | C25: 1-01-01-02-023-BANK TROCAIRE-0081-004762-06-5PILER | D25: Balance Sheet | E25: Current Assets | F25: Cash And Bank Balances | G25: Cash With Banks In Current/Pls Accounts | H25: PILER | I25: 780447.25 | J25: 0 | K25: 0 | L25: 20.99 | M25: =+I25+K25 -> 780447.25 | N25: =+J25+L25 -> 20.99 | Q25: =+M25+O25 -> 780447.25 | R25: =+N25+P25 -> 20.99 | S25: =+Q25-R25 -> 780426.26 | V25: =IF($V$8=$H25,$Q25,0) -> 780447.25 | W25: =IF($V$8=$H25,$R25,0) -> 20.99 | X25: =IF($X$8=$H25,$Q25,0) -> 0 | Y25: =IF($X$8=$H25,$R25,0) -> 0 | Z25: =IF($Z$8=$H25,$Q25,0) -> 0 | AA25: =IF($Z$8=$H25,$R25,0) -> 0 | AB25: =IF($AB$8=$H25,$Q25,0) -> 0 | AC25: =IF($AB$8=$H25,$R25,0) -> 0 | AD25: =IF($AD$8=$H25,$Q25,0) -> 0 | AE25: =IF($AD$8=$H25,$R25,0) -> 0 | AF25: =IF($AF$8=$H25,$Q25,0) -> 0 | AG25: =IF($AF$8=$H25,$R25,0) -> 0 | AH25: =IF($AH$8=$H25,$Q25,0) -> 0 | AI25: =IF($AH$8=$H25,$R25,0) -> 0 | AJ25: =IF($AJ$8=$H25,$Q25,0) -> 0 | AK25: =IF($AJ$8=$H25,$R25,0) -> 0 | AL25: =IF($AL$8=$H25,$Q25,0) -> 0 | AM25: =IF($AL$8=$H25,$R25,0) -> 0 | AN25: =IF($AN$8=$H25,$Q25,0) -> 0 | AO25: =IF($AN$8=$H25,$R25,0) -> 0 | AP25: =IF($AP$8=$H25,$Q25,0) -> 0 | AQ25: =IF($AP$8=$H25,$R25,0) -> 0 | AR25: =IF($AR$8=$H25,$Q25,0) -> 0 | AS25: =IF($AR$8=$H25,$R25,0) -> 0 | AT25: =IF($AT$8=$H25,$Q25,0) -> 0 | AU25: =IF($AT$8=$H25,$R25,0) -> 0 | AV25: =IF($AV$8=$H25,$Q25,0) -> 0 | AW25: =IF($AV$8=$H25,$R25,0) -> 0 | AX25: =IF($AX$8=$H25,$Q25,0) -> 0 | AY25: =IF($AX$8=$H25,$R25,0) -> 0 | AZ25: =IF($AZ$8=$H25,$Q25,0) -> 0 | BA25: =IF($AZ$8=$H25,$R25,0) -> 0 | BB25: =IF($BB$8=$H25,$Q25,0) -> 0 | BC25: =IF($BB$8=$H25,$R25,0) -> 0 | BD25: =IF($BD$8=$H25,$Q25,0) -> 0 | BE25: =IF($BD$8=$H25,$R25,0) -> 0 | BF25: =IF($BF$8=$H25,$Q25,0) -> 0 | BG25: =IF($BF$8=$H25,$R25,0) -> 0
A26: 1-01-01-02-023 | B26: BANK TROCAIRE-0081-004762-06-5 | C26: 1-01-01-02-023-BANK TROCAIRE-0081-004762-06-5FOSI | D26: Balance Sheet | E26: Current Assets | F26: Cash And Bank Balances | G26: Cash With Banks In Current/Pls Accounts | H26: FOSI | I26: 19147.19 | J26: 0 | K26: 0 | L26: 0 | M26: =+I26+K26 -> 19147.19 | N26: =+J26+L26 -> 0 | Q26: =+M26+O26 -> 19147.19 | R26: =+N26+P26 -> 0 | S26: =+Q26-R26 -> 19147.19 | V26: =IF($V$8=$H26,$Q26,0) -> 0 | W26: =IF($V$8=$H26,$R26,0) -> 0 | X26: =IF($X$8=$H26,$Q26,0) -> 0 | Y26: =IF($X$8=$H26,$R26,0) -> 0 | Z26: =IF($Z$8=$H26,$Q26,0) -> 0 | AA26: =IF($Z$8=$H26,$R26,0) -> 0 | AB26: =IF($AB$8=$H26,$Q26,0) -> 0 | AC26: =IF($AB$8=$H26,$R26,0) -> 0 | AD26: =IF($AD$8=$H26,$Q26,0) -> 0 | AE26: =IF($AD$8=$H26,$R26,0) -> 0 | AF26: =IF($AF$8=$H26,$Q26,0) -> 0 | AG26: =IF($AF$8=$H26,$R26,0) -> 0 | AH26: =IF($AH$8=$H26,$Q26,0) -> 0 | AI26: =IF($AH$8=$H26,$R26,0) -> 0 | AJ26: =IF($AJ$8=$H26,$Q26,0) -> 0 | AK26: =IF($AJ$8=$H26,$R26,0) -> 0 | AL26: =IF($AL$8=$H26,$Q26,0) -> 19147.19 | AM26: =IF($AL$8=$H26,$R26,0) -> 0 | AN26: =IF($AN$8=$H26,$Q26,0) -> 0 | AO26: =IF($AN$8=$H26,$R26,0) -> 0 | AP26: =IF($AP$8=$H26,$Q26,0) -> 0 | AQ26: =IF($AP$8=$H26,$R26,0) -> 0 | AR26: =IF($AR$8=$H26,$Q26,0) -> 0 | AS26: =IF($AR$8=$H26,$R26,0) -> 0 | AT26: =IF($AT$8=$H26,$Q26,0) -> 0 | AU26: =IF($AT$8=$H26,$R26,0) -> 0 | AV26: =IF($AV$8=$H26,$Q26,0) -> 0 | AW26: =IF($AV$8=$H26,$R26,0) -> 0 | AX26: =IF($AX$8=$H26,$Q26,0) -> 0 | AY26: =IF($AX$8=$H26,$R26,0) -> 0 | AZ26: =IF($AZ$8=$H26,$Q26,0) -> 0 | BA26: =IF($AZ$8=$H26,$R26,0) -> 0 | BB26: =IF($BB$8=$H26,$Q26,0) -> 0 | BC26: =IF($BB$8=$H26,$R26,0) -> 0 | BD26: =IF($BD$8=$H26,$Q26,0) -> 0 | BE26: =IF($BD$8=$H26,$R26,0) -> 0 | BF26: =IF($BF$8=$H26,$Q26,0) -> 0 | BG26: =IF($BF$8=$H26,$R26,0) -> 0
A27: 1-01-01-02-023 | B27: BANK TROCAIRE-0081-004762-06-5 | C27: 1-01-01-02-023-BANK TROCAIRE-0081-004762-06-5DAI | D27: Balance Sheet | E27: Current Assets | F27: Cash And Bank Balances | G27: Cash With Banks In Current/Pls Accounts | H27: DAI | I27: 5686929 | J27: 6486524 | K27: 0 | L27: 0 | M27: =+I27+K27 -> 5686929 | N27: =+J27+L27 -> 6486524 | Q27: =+M27+O27 -> 5686929 | R27: =+N27+P27 -> 6486524 | S27: =+Q27-R27 -> -799594.95 | V27: =IF($V$8=$H27,$Q27,0) -> 0 | W27: =IF($V$8=$H27,$R27,0) -> 0 | X27: =IF($X$8=$H27,$Q27,0) -> 0 | Y27: =IF($X$8=$H27,$R27,0) -> 0 | Z27: =IF($Z$8=$H27,$Q27,0) -> 0 | AA27: =IF($Z$8=$H27,$R27,0) -> 0 | AB27: =IF($AB$8=$H27,$Q27,0) -> 0 | AC27: =IF($AB$8=$H27,$R27,0) -> 0 | AD27: =IF($AD$8=$H27,$Q27,0) -> 0 | AE27: =IF($AD$8=$H27,$R27,0) -> 0 | AF27: =IF($AF$8=$H27,$Q27,0) -> 0 | AG27: =IF($AF$8=$H27,$R27,0) -> 0 | AH27: =IF($AH$8=$H27,$Q27,0) -> 0 | AI27: =IF($AH$8=$H27,$R27,0) -> 0 | AJ27: =IF($AJ$8=$H27,$Q27,0) -> 0 | AK27: =IF($AJ$8=$H27,$R27,0) -> 0 | AL27: =IF($AL$8=$H27,$Q27,0) -> 0 | AM27: =IF($AL$8=$H27,$R27,0) -> 0 | AN27: =IF($AN$8=$H27,$Q27,0) -> 5686929 | AO27: =IF($AN$8=$H27,$R27,0) -> 6486524 | AP27: =IF($AP$8=$H27,$Q27,0) -> 0 | AQ27: =IF($AP$8=$H27,$R27,0) -> 0 | AR27: =IF($AR$8=$H27,$Q27,0) -> 0 | AS27: =IF($AR$8=$H27,$R27,0) -> 0 | AT27: =IF($AT$8=$H27,$Q27,0) -> 0 | AU27: =IF($AT$8=$H27,$R27,0) -> 0 | AV27: =IF($AV$8=$H27,$Q27,0) -> 0 | AW27: =IF($AV$8=$H27,$R27,0) -> 0 | AX27: =IF($AX$8=$H27,$Q27,0) -> 0 | AY27: =IF($AX$8=$H27,$R27,0) -> 0 | AZ27: =IF($AZ$8=$H27,$Q27,0) -> 0 | BA27: =IF($AZ$8=$H27,$R27,0) -> 0 | BB27: =IF($BB$8=$H27,$Q27,0) -> 0 | BC27: =IF($BB$8=$H27,$R27,0) -> 0 | BD27: =IF($BD$8=$H27,$Q27,0) -> 0 | BE27: =IF($BD$8=$H27,$R27,0) -> 0 | BF27: =IF($BF$8=$H27,$Q27,0) -> 0 | BG27: =IF($BF$8=$H27,$R27,0) -> 0
A28: 1-01-01-02-024 | B28: BANK TDH-0081-004762-05-4 | C28: 1-01-01-02-024-BANK TDH-0081-004762-05-4Deezire | D28: Balance Sheet | E28: Current Assets | F28: Cash And Bank Balances | G28: Cash With Banks In Current/Pls Accounts | H28: Deezire | I28: 100 | J28: 1024795.8 | K28: 0 | L28: 0 | M28: =+I28+K28 -> 100 | N28: =+J28+L28 -> 1024795.8 | Q28: =+M28+O28 -> 100 | R28: =+N28+P28 -> 1024795.8 | S28: =+Q28-R28 -> -1024695.8 | V28: =IF($V$8=$H28,$Q28,0) -> 0 | W28: =IF($V$8=$H28,$R28,0) -> 0 | X28: =IF($X$8=$H28,$Q28,0) -> 0 | Y28: =IF($X$8=$H28,$R28,0) -> 0 | Z28: =IF($Z$8=$H28,$Q28,0) -> 0 | AA28: =IF($Z$8=$H28,$R28,0) -> 0 | AB28: =IF($AB$8=$H28,$Q28,0) -> 0 | AC28: =IF($AB$8=$H28,$R28,0) -> 0 | AD28: =IF($AD$8=$H28,$Q28,0) -> 0 | AE28: =IF($AD$8=$H28,$R28,0) -> 0 | AF28: =IF($AF$8=$H28,$Q28,0) -> 0 | AG28: =IF($AF$8=$H28,$R28,0) -> 0 | AH28: =IF($AH$8=$H28,$Q28,0) -> 0 | AI28: =IF($AH$8=$H28,$R28,0) -> 0 | AJ28: =IF($AJ$8=$H28,$Q28,0) -> 0 | AK28: =IF($AJ$8=$H28,$R28,0) -> 0 | AL28: =IF($AL$8=$H28,$Q28,0) -> 0 | AM28: =IF($AL$8=$H28,$R28,0) -> 0 | AN28: =IF($AN$8=$H28,$Q28,0) -> 0 | AO28: =IF($AN$8=$H28,$R28,0) -> 0 | AP28: =IF($AP$8=$H28,$Q28,0) -> 100 | AQ28: =IF($AP$8=$H28,$R28,0) -> 1024795.8 | AR28: =IF($AR$8=$H28,$Q28,0) -> 0 | AS28: =IF($AR$8=$H28,$R28,0) -> 0 | AT28: =IF($AT$8=$H28,$Q28,0) -> 0 | AU28: =IF($AT$8=$H28,$R28,0) -> 0 | AV28: =IF($AV$8=$H28,$Q28,0) -> 0 | AW28: =IF($AV$8=$H28,$R28,0) -> 0 | AX28: =IF($AX$8=$H28,$Q28,0) -> 0 | AY28: =IF($AX$8=$H28,$R28,0) -> 0 | AZ28: =IF($AZ$8=$H28,$Q28,0) -> 0 | BA28: =IF($AZ$8=$H28,$R28,0) -> 0 | BB28: =IF($BB$8=$H28,$Q28,0) -> 0 | BC28: =IF($BB$8=$H28,$R28,0) -> 0 | BD28: =IF($BD$8=$H28,$Q28,0) -> 0 | BE28: =IF($BD$8=$H28,$R28,0) -> 0 | BF28: =IF($BF$8=$H28,$Q28,0) -> 0 | BG28: =IF($BF$8=$H28,$R28,0) -> 0
A29: 1-01-01-02-024 | B29: BANK TDH-0081-004762-05-4 | C29: 1-01-01-02-024-BANK TDH-0081-004762-05-4PILER | D29: Balance Sheet | E29: Current Assets | F29: Cash And Bank Balances | G29: Cash With Banks In Current/Pls Accounts | H29: PILER | I29: 0 | J29: 118.65 | K29: 0 | L29: 21.06 | M29: =+I29+K29 -> 0 | N29: =+J29+L29 -> 139.71 | Q29: =+M29+O29 -> 0 | R29: =+N29+P29 -> 139.71 | S29: =+Q29-R29 -> -139.71 | V29: =IF($V$8=$H29,$Q29,0) -> 0 | W29: =IF($V$8=$H29,$R29,0) -> 139.71 | X29: =IF($X$8=$H29,$Q29,0) -> 0 | Y29: =IF($X$8=$H29,$R29,0) -> 0 | Z29: =IF($Z$8=$H29,$Q29,0) -> 0 | AA29: =IF($Z$8=$H29,$R29,0) -> 0 | AB29: =IF($AB$8=$H29,$Q29,0) -> 0 | AC29: =IF($AB$8=$H29,$R29,0) -> 0 | AD29: =IF($AD$8=$H29,$Q29,0) -> 0 | AE29: =IF($AD$8=$H29,$R29,0) -> 0 | AF29: =IF($AF$8=$H29,$Q29,0) -> 0 | AG29: =IF($AF$8=$H29,$R29,0) -> 0 | AH29: =IF($AH$8=$H29,$Q29,0) -> 0 | AI29: =IF($AH$8=$H29,$R29,0) -> 0 | AJ29: =IF($AJ$8=$H29,$Q29,0) -> 0 | AK29: =IF($AJ$8=$H29,$R29,0) -> 0 | AL29: =IF($AL$8=$H29,$Q29,0) -> 0 | AM29: =IF($AL$8=$H29,$R29,0) -> 0 | AN29: =IF($AN$8=$H29,$Q29,0) -> 0 | AO29: =IF($AN$8=$H29,$R29,0) -> 0 | AP29: =IF($AP$8=$H29,$Q29,0) -> 0 | AQ29: =IF($AP$8=$H29,$R29,0) -> 0 | AR29: =IF($AR$8=$H29,$Q29,0) -> 0 | AS29: =IF($AR$8=$H29,$R29,0) -> 0 | AT29: =IF($AT$8=$H29,$Q29,0) -> 0 | AU29: =IF($AT$8=$H29,$R29,0) -> 0 | AV29: =IF($AV$8=$H29,$Q29,0) -> 0 | AW29: =IF($AV$8=$H29,$R29,0) -> 0 | AX29: =IF($AX$8=$H29,$Q29,0) -> 0 | AY29: =IF($AX$8=$H29,$R29,0) -> 0 | AZ29: =IF($AZ$8=$H29,$Q29,0) -> 0 | BA29: =IF($AZ$8=$H29,$R29,0) -> 0 | BB29: =IF($BB$8=$H29,$Q29,0) -> 0 | BC29: =IF($BB$8=$H29,$R29,0) -> 0 | BD29: =IF($BD$8=$H29,$Q29,0) -> 0 | BE29: =IF($BD$8=$H29,$R29,0) -> 0 | BF29: =IF($BF$8=$H29,$Q29,0) -> 0 | BG29: =IF($BF$8=$H29,$R29,0) -> 0
A30: 1-01-01-02-024 | B30: BANK TDH-0081-004762-05-4 | C30: 1-01-01-02-024-BANK TDH-0081-004762-05-4TDH | D30: Balance Sheet | E30: Current Assets | F30: Cash And Bank Balances | G30: Cash With Banks In Current/Pls Accounts | H30: TDH | I30: 40198.14 | J30: 0 | K30: 0 | L30: 0 | M30: =+I30+K30 -> 40198.14 | N30: =+J30+L30 -> 0 | Q30: =+M30+O30 -> 40198.14 | R30: =+N30+P30 -> 0 | S30: =+Q30-R30 -> 40198.14 | V30: =IF($V$8=$H30,$Q30,0) -> 0 | W30: =IF($V$8=$H30,$R30,0) -> 0 | X30: =IF($X$8=$H30,$Q30,0) -> 0 | Y30: =IF($X$8=$H30,$R30,0) -> 0 | Z30: =IF($Z$8=$H30,$Q30,0) -> 40198.14 | AA30: =IF($Z$8=$H30,$R30,0) -> 0 | AB30: =IF($AB$8=$H30,$Q30,0) -> 0 | AC30: =IF($AB$8=$H30,$R30,0) -> 0 | AD30: =IF($AD$8=$H30,$Q30,0) -> 0 | AE30: =IF($AD$8=$H30,$R30,0) -> 0 | AF30: =IF($AF$8=$H30,$Q30,0) -> 0 | AG30: =IF($AF$8=$H30,$R30,0) -> 0 | AH30: =IF($AH$8=$H30,$Q30,0) -> 0 | AI30: =IF($AH$8=$H30,$R30,0) -> 0 | AJ30: =IF($AJ$8=$H30,$Q30,0) -> 0 | AK30: =IF($AJ$8=$H30,$R30,0) -> 0 | AL30: =IF($AL$8=$H30,$Q30,0) -> 0 | AM30: =IF($AL$8=$H30,$R30,0) -> 0 | AN30: =IF($AN$8=$H30,$Q30,0) -> 0 | AO30: =IF($AN$8=$H30,$R30,0) -> 0 | AP30: =IF($AP$8=$H30,$Q30,0) -> 0 | AQ30: =IF($AP$8=$H30,$R30,0) -> 0 | AR30: =IF($AR$8=$H30,$Q30,0) -> 0 | AS30: =IF($AR$8=$H30,$R30,0) -> 0 | AT30: =IF($AT$8=$H30,$Q30,0) -> 0 | AU30: =IF($AT$8=$H30,$R30,0) -> 0 | AV30: =IF($AV$8=$H30,$Q30,0) -> 0 | AW30: =IF($AV$8=$H30,$R30,0) -> 0 | AX30: =IF($AX$8=$H30,$Q30,0) -> 0 | AY30: =IF($AX$8=$H30,$R30,0) -> 0 | AZ30: =IF($AZ$8=$H30,$Q30,0) -> 0 | BA30: =IF($AZ$8=$H30,$R30,0) -> 0 | BB30: =IF($BB$8=$H30,$Q30,0) -> 0 | BC30: =IF($BB$8=$H30,$R30,0) -> 0 | BD30: =IF($BD$8=$H30,$Q30,0) -> 0 | BE30: =IF($BD$8=$H30,$R30,0) -> 0 | BF30: =IF($BF$8=$H30,$Q30,0) -> 0 | BG30: =IF($BF$8=$H30,$R30,0) -> 0
A31: 1-01-01-02-024 | B31: BANK TDH-0081-004762-05-4 | C31: 1-01-01-02-024-BANK TDH-0081-004762-05-4FNV | D31: Balance Sheet | E31: Current Assets | F31: Cash And Bank Balances | G31: Cash With Banks In Current/Pls Accounts | H31: FNV | I31: 1024932.6 | J31: 40295.3 | K31: 0 | L31: 0 | M31: =+I31+K31 -> 1024932.6 | N31: =+J31+L31 -> 40295.3 | Q31: =+M31+O31 -> 1024932.6 | R31: =+N31+P31 -> 40295.3 | S31: =+Q31-R31 -> 984637.33 | V31: =IF($V$8=$H31,$Q31,0) -> 0 | W31: =IF($V$8=$H31,$R31,0) -> 0 | X31: =IF($X$8=$H31,$Q31,0) -> 0 | Y31: =IF($X$8=$H31,$R31,0) -> 0 | Z31: =IF($Z$8=$H31,$Q31,0) -> 0 | AA31: =IF($Z$8=$H31,$R31,0) -> 0 | AB31: =IF($AB$8=$H31,$Q31,0) -> 0 | AC31: =IF($AB$8=$H31,$R31,0) -> 0 | AD31: =IF($AD$8=$H31,$Q31,0) -> 0 | AE31: =IF($AD$8=$H31,$R31,0) -> 0 | AF31: =IF($AF$8=$H31,$Q31,0) -> 0 | AG31: =IF($AF$8=$H31,$R31,0) -> 0 | AH31: =IF($AH$8=$H31,$Q31,0) -> 0 | AI31: =IF($AH$8=$H31,$R31,0) -> 0 | AJ31: =IF($AJ$8=$H31,$Q31,0) -> 0 | AK31: =IF($AJ$8=$H31,$R31,0) -> 0 | AL31: =IF($AL$8=$H31,$Q31,0) -> 0 | AM31: =IF($AL$8=$H31,$R31,0) -> 0 | AN31: =IF($AN$8=$H31,$Q31,0) -> 0 | AO31: =IF($AN$8=$H31,$R31,0) -> 0 | AP31: =IF($AP$8=$H31,$Q31,0) -> 0 | AQ31: =IF($AP$8=$H31,$R31,0) -> 0 | AR31: =IF($AR$8=$H31,$Q31,0) -> 1024932.6 | AS31: =IF($AR$8=$H31,$R31,0) -> 40295.3 | AT31: =IF($AT$8=$H31,$Q31,0) -> 0 | AU31: =IF($AT$8=$H31,$R31,0) -> 0 | AV31: =IF($AV$8=$H31,$Q31,0) -> 0 | AW31: =IF($AV$8=$H31,$R31,0) -> 0 | AX31: =IF($AX$8=$H31,$Q31,0) -> 0 | AY31: =IF($AX$8=$H31,$R31,0) -> 0 | AZ31: =IF($AZ$8=$H31,$Q31,0) -> 0 | BA31: =IF($AZ$8=$H31,$R31,0) -> 0 | BB31: =IF($BB$8=$H31,$Q31,0) -> 0 | BC31: =IF($BB$8=$H31,$R31,0) -> 0 | BD31: =IF($BD$8=$H31,$Q31,0) -> 0 | BE31: =IF($BD$8=$H31,$R31,0) -> 0 | BF31: =IF($BF$8=$H31,$Q31,0) -> 0 | BG31: =IF($BF$8=$H31,$R31,0) -> 0
A32: 1-01-01-02-025 | B32: BANK GRATUITY-0081-004762-09-8 | C32: 1-01-01-02-025-BANK GRATUITY-0081-004762-09-8PILER | D32: Balance Sheet | E32: Current Assets | F32: Cash And Bank Balances | G32: Cash With Banks In Current/Pls Accounts | H32: PILER | I32: 22826302 | J32: 23721004 | K32: 0 | L32: 0 | M32: =+I32+K32 -> 22826302 | N32: =+J32+L32 -> 23721004 | Q32: =+M32+O32 -> 22826302 | R32: =+N32+P32 -> 23721004 | S32: =+Q32-R32 -> -894702.48
A33: 1-01-01-02-025 | B33: BANK GRATUITY-0081-004762-09-8 | C33: 1-01-01-02-025-BANK GRATUITY-0081-004762-09-8SHORT | D33: Balance Sheet | E33: Current Assets | F33: Cash And Bank Balances | G33: Cash With Banks In Current/Pls Accounts | H33: SHORT | I33: 714000 | J33: 0 | K33: 0 | L33: 0 | M33: =+I33+K33 -> 714000 | N33: =+J33+L33 -> 0 | Q33: =+M33+O33 -> 714000 | R33: =+N33+P33 -> 0 | S33: =+Q33-R33 -> 714000
A34: 1-01-01-02-025 | B34: BANK GRATUITY-0081-004762-09-8 | C34: 1-01-01-02-025-BANK GRATUITY-0081-004762-09-8GRC | D34: Balance Sheet | E34: Current Assets | F34: Cash And Bank Balances | G34: Cash With Banks In Current/Pls Accounts | H34: GRC | I34: 10118959 | J34: 9249677.7 | K34: 13903195 | L34: 13259959 | M34: =+I34+K34 -> 24022155 | N34: =+J34+L34 -> 22509637 | Q34: =+M34+O34 -> 24022155 | R34: =+N34+P34 -> 22509637 | S34: =+Q34-R34 -> 1512517.8 | V34: =IF($V$8=$H34,$Q34,0) -> 0 | W34: =IF($V$8=$H34,$R34,0) -> 0 | X34: =IF($X$8=$H34,$Q34,0) -> 0 | Y34: =IF($X$8=$H34,$R34,0) -> 0 | Z34: =IF($Z$8=$H34,$Q34,0) -> 0 | AA34: =IF($Z$8=$H34,$R34,0) -> 0 | AB34: =IF($AB$8=$H34,$Q34,0) -> 0 | AC34: =IF($AB$8=$H34,$R34,0) -> 0 | AD34: =IF($AD$8=$H34,$Q34,0) -> 0 | AE34: =IF($AD$8=$H34,$R34,0) -> 0 | AF34: =IF($AF$8=$H34,$Q34,0) -> 0 | AG34: =IF($AF$8=$H34,$R34,0) -> 0 | AH34: =IF($AH$8=$H34,$Q34,0) -> 0 | AI34: =IF($AH$8=$H34,$R34,0) -> 0 | AJ34: =IF($AJ$8=$H34,$Q34,0) -> 0 | AK34: =IF($AJ$8=$H34,$R34,0) -> 0 | AL34: =IF($AL$8=$H34,$Q34,0) -> 0 | AM34: =IF($AL$8=$H34,$R34,0) -> 0 | AN34: =IF($AN$8=$H34,$Q34,0) -> 0 | AO34: =IF($AN$8=$H34,$R34,0) -> 0 | AP34: =IF($AP$8=$H34,$Q34,0) -> 0 | AQ34: =IF($AP$8=$H34,$R34,0) -> 0 | AR34: =IF($AR$8=$H34,$Q34,0) -> 0 | AS34: =IF($AR$8=$H34,$R34,0) -> 0 | AT34: =IF($AT$8=$H34,$Q34,0) -> 0 | AU34: =IF($AT$8=$H34,$R34,0) -> 0 | AV34: =IF($AV$8=$H34,$Q34,0) -> 0 | AW34: =IF($AV$8=$H34,$R34,0) -> 0 | AX34: =IF($AX$8=$H34,$Q34,0) -> 0 | AY34: =IF($AX$8=$H34,$R34,0) -> 0 | AZ34: =IF($AZ$8=$H34,$Q34,0) -> 0 | BA34: =IF($AZ$8=$H34,$R34,0) -> 0 | BB34: =IF($BB$8=$H34,$Q34,0) -> 0 | BC34: =IF($BB$8=$H34,$R34,0) -> 0 | BD34: =IF($BD$8=$H34,$Q34,0) -> 0 | BE34: =IF($BD$8=$H34,$R34,0) -> 0 | BF34: =IF($BF$8=$H34,$Q34,0) -> 0 | BG34: =IF($BF$8=$H34,$R34,0) -> 0
A35: 1-01-01-02-025 | B35: BANK GRATUITY-0081-004762-09-8 | C35: 1-01-01-02-025-BANK GRATUITY-0081-004762-09-8GRC Own | D35: Balance Sheet | E35: Current Assets | F35: Cash And Bank Balances | G35: Cash With Banks In Current/Pls Accounts | H35: GRC Own | I35: 0 | J35: 0 | K35: 9430038.6 | L35: 9551036.7 | M35: =+I35+K35 -> 9430038.6 | N35: =+J35+L35 -> 9551036.7 | Q35: =+M35+O35 -> 9430038.6 | R35: =+N35+P35 -> 9551036.7 | S35: =+Q35-R35 -> -120998.11 | V35: =IF($V$8=$H35,$Q35,0) -> 0 | W35: =IF($V$8=$H35,$R35,0) -> 0 | X35: =IF($X$8=$H35,$Q35,0) -> 0 | Y35: =IF($X$8=$H35,$R35,0) -> 0 | Z35: =IF($Z$8=$H35,$Q35,0) -> 0 | AA35: =IF($Z$8=$H35,$R35,0) -> 0 | AB35: =IF($AB$8=$H35,$Q35,0) -> 0 | AC35: =IF($AB$8=$H35,$R35,0) -> 0 | AD35: =IF($AD$8=$H35,$Q35,0) -> 0 | AE35: =IF($AD$8=$H35,$R35,0) -> 0 | AF35: =IF($AF$8=$H35,$Q35,0) -> 0 | AG35: =IF($AF$8=$H35,$R35,0) -> 0 | AH35: =IF($AH$8=$H35,$Q35,0) -> 0 | AI35: =IF($AH$8=$H35,$R35,0) -> 0 | AJ35: =IF($AJ$8=$H35,$Q35,0) -> 0 | AK35: =IF($AJ$8=$H35,$R35,0) -> 0 | AL35: =IF($AL$8=$H35,$Q35,0) -> 0 | AM35: =IF($AL$8=$H35,$R35,0) -> 0 | AN35: =IF($AN$8=$H35,$Q35,0) -> 0 | AO35: =IF($AN$8=$H35,$R35,0) -> 0 | AP35: =IF($AP$8=$H35,$Q35,0) -> 0 | AQ35: =IF($AP$8=$H35,$R35,0) -> 0 | AR35: =IF($AR$8=$H35,$Q35,0) -> 0 | AS35: =IF($AR$8=$H35,$R35,0) -> 0 | AT35: =IF($AT$8=$H35,$Q35,0) -> 0 | AU35: =IF($AT$8=$H35,$R35,0) -> 0 | AV35: =IF($AV$8=$H35,$Q35,0) -> 0 | AW35: =IF($AV$8=$H35,$R35,0) -> 0 | AX35: =IF($AX$8=$H35,$Q35,0) -> 0 | AY35: =IF($AX$8=$H35,$R35,0) -> 0 | AZ35: =IF($AZ$8=$H35,$Q35,0) -> 0 | BA35: =IF($AZ$8=$H35,$R35,0) -> 0 | BB35: =IF($BB$8=$H35,$Q35,0) -> 0 | BC35: =IF($BB$8=$H35,$R35,0) -> 0 | BD35: =IF($BD$8=$H35,$Q35,0) -> 0 | BE35: =IF($BD$8=$H35,$R35,0) -> 0 | BF35: =IF($BF$8=$H35,$Q35,0) -> 0 | BG35: =IF($BF$8=$H35,$R35,0) -> 0
A36: 1-01-01-02-027 | B36: BANK DOLLAR-0112-004762-10-9 | C36: 1-01-01-02-027-BANK DOLLAR-0112-004762-10-9PILER | D36: Balance Sheet | E36: Current Assets | F36: Cash And Bank Balances | G36: Cash With Banks In Current/Pls Accounts | H36: PILER | I36: 6261.86 | J36: 0 | K36: 0 | L36: 0 | M36: =+I36+K36 -> 6261.86 | N36: =+J36+L36 -> 0 | Q36: =+M36+O36 -> 6261.86 | R36: =+N36+P36 -> 0 | S36: =+Q36-R36 -> 6261.86 | V36: =IF($V$8=$H36,$Q36,0) -> 6261.86 | W36: =IF($V$8=$H36,$R36,0) -> 0 | X36: =IF($X$8=$H36,$Q36,0) -> 0 | Y36: =IF($X$8=$H36,$R36,0) -> 0 | Z36: =IF($Z$8=$H36,$Q36,0) -> 0 | AA36: =IF($Z$8=$H36,$R36,0) -> 0 | AB36: =IF($AB$8=$H36,$Q36,0) -> 0 | AC36: =IF($AB$8=$H36,$R36,0) -> 0 | AD36: =IF($AD$8=$H36,$Q36,0) -> 0 | AE36: =IF($AD$8=$H36,$R36,0) -> 0 | AF36: =IF($AF$8=$H36,$Q36,0) -> 0 | AG36: =IF($AF$8=$H36,$R36,0) -> 0 | AH36: =IF($AH$8=$H36,$Q36,0) -> 0 | AI36: =IF($AH$8=$H36,$R36,0) -> 0 | AJ36: =IF($AJ$8=$H36,$Q36,0) -> 0 | AK36: =IF($AJ$8=$H36,$R36,0) -> 0 | AL36: =IF($AL$8=$H36,$Q36,0) -> 0 | AM36: =IF($AL$8=$H36,$R36,0) -> 0 | AN36: =IF($AN$8=$H36,$Q36,0) -> 0 | AO36: =IF($AN$8=$H36,$R36,0) -> 0 | AP36: =IF($AP$8=$H36,$Q36,0) -> 0 | AQ36: =IF($AP$8=$H36,$R36,0) -> 0 | AR36: =IF($AR$8=$H36,$Q36,0) -> 0 | AS36: =IF($AR$8=$H36,$R36,0) -> 0 | AT36: =IF($AT$8=$H36,$Q36,0) -> 0 | AU36: =IF($AT$8=$H36,$R36,0) -> 0 | AV36: =IF($AV$8=$H36,$Q36,0) -> 0 | AW36: =IF($AV$8=$H36,$R36,0) -> 0 | AX36: =IF($AX$8=$H36,$Q36,0) -> 0 | AY36: =IF($AX$8=$H36,$R36,0) -> 0 | AZ36: =IF($AZ$8=$H36,$Q36,0) -> 0 | BA36: =IF($AZ$8=$H36,$R36,0) -> 0 | BB36: =IF($BB$8=$H36,$Q36,0) -> 0 | BC36: =IF($BB$8=$H36,$R36,0) -> 0 | BD36: =IF($BD$8=$H36,$Q36,0) -> 0 | BE36: =IF($BD$8=$H36,$R36,0) -> 0 | BF36: =IF($BF$8=$H36,$Q36,0) -> 0 | BG36: =IF($BF$8=$H36,$R36,0) -> 0
A37: 1-01-01-02-029 | B37: BANK ICCO PAK-0081-004762-08-7 | C37: 1-01-01-02-029-BANK ICCO PAK-0081-004762-08-7ICCO Pak | D37: Balance Sheet | E37: Current Assets | F37: Cash And Bank Balances | G37: Cash With Banks In Current/Pls Accounts | H37: ICCO Pak | I37: 70646.14 | J37: 79.1 | K37: 0 | L37: 0 | M37: =+I37+K37 -> 70646.14 | N37: =+J37+L37 -> 79.1 | Q37: =+M37+O37 -> 70646.14 | R37: =+N37+P37 -> 79.1 | S37: =+Q37-R37 -> 70567.04 | V37: =IF($V$8=$H37,$Q37,0) -> 0 | W37: =IF($V$8=$H37,$R37,0) -> 0 | X37: =IF($X$8=$H37,$Q37,0) -> 0 | Y37: =IF($X$8=$H37,$R37,0) -> 0 | Z37: =IF($Z$8=$H37,$Q37,0) -> 0 | AA37: =IF($Z$8=$H37,$R37,0) -> 0 | AB37: =IF($AB$8=$H37,$Q37,0) -> 0 | AC37: =IF($AB$8=$H37,$R37,0) -> 0 | AD37: =IF($AD$8=$H37,$Q37,0) -> 0 | AE37: =IF($AD$8=$H37,$R37,0) -> 0 | AF37: =IF($AF$8=$H37,$Q37,0) -> 0 | AG37: =IF($AF$8=$H37,$R37,0) -> 0 | AH37: =IF($AH$8=$H37,$Q37,0) -> 0 | AI37: =IF($AH$8=$H37,$R37,0) -> 0 | AJ37: =IF($AJ$8=$H37,$Q37,0) -> 0 | AK37: =IF($AJ$8=$H37,$R37,0) -> 0 | AL37: =IF($AL$8=$H37,$Q37,0) -> 0 | AM37: =IF($AL$8=$H37,$R37,0) -> 0 | AN37: =IF($AN$8=$H37,$Q37,0) -> 0 | AO37: =IF($AN$8=$H37,$R37,0) -> 0 | AP37: =IF($AP$8=$H37,$Q37,0) -> 0 | AQ37: =IF($AP$8=$H37,$R37,0) -> 0 | AR37: =IF($AR$8=$H37,$Q37,0) -> 0 | AS37: =IF($AR$8=$H37,$R37,0) -> 0 | AT37: =IF($AT$8=$H37,$Q37,0) -> 70646.14 | AU37: =IF($AT$8=$H37,$R37,0) -> 79.1 | AV37: =IF($AV$8=$H37,$Q37,0) -> 0 | AW37: =IF($AV$8=$H37,$R37,0) -> 0 | AX37: =IF($AX$8=$H37,$Q37,0) -> 0 | AY37: =IF($AX$8=$H37,$R37,0) -> 0 | AZ37: =IF($AZ$8=$H37,$Q37,0) -> 0 | BA37: =IF($AZ$8=$H37,$R37,0) -> 0 | BB37: =IF($BB$8=$H37,$Q37,0) -> 0 | BC37: =IF($BB$8=$H37,$R37,0) -> 0 | BD37: =IF($BD$8=$H37,$Q37,0) -> 0 | BE37: =IF($BD$8=$H37,$R37,0) -> 0 | BF37: =IF($BF$8=$H37,$Q37,0) -> 0 | BG37: =IF($BF$8=$H37,$R37,0) -> 0
A38: 1-01-01-02-029 | B38: BANK ICCO PAK-0081-004762-08-7 | C38: 1-01-01-02-029-BANK ICCO PAK-0081-004762-08-7Open Society | D38: Balance Sheet | E38: Current Assets | F38: Cash And Bank Balances | G38: Cash With Banks In Current/Pls Accounts | H38: Open Society | I38: 12334250 | J38: 12403022 | K38: 0 | L38: 0 | M38: =+I38+K38 -> 12334250 | N38: =+J38+L38 -> 12403022 | Q38: =+M38+O38 -> 12334250 | R38: =+N38+P38 -> 12403022 | S38: =+Q38-R38 -> -68772.71 | V38: =IF($V$8=$H38,$Q38,0) -> 0 | W38: =IF($V$8=$H38,$R38,0) -> 0 | X38: =IF($X$8=$H38,$Q38,0) -> 0 | Y38: =IF($X$8=$H38,$R38,0) -> 0 | Z38: =IF($Z$8=$H38,$Q38,0) -> 0 | AA38: =IF($Z$8=$H38,$R38,0) -> 0 | AB38: =IF($AB$8=$H38,$Q38,0) -> 0 | AC38: =IF($AB$8=$H38,$R38,0) -> 0 | AD38: =IF($AD$8=$H38,$Q38,0) -> 0 | AE38: =IF($AD$8=$H38,$R38,0) -> 0 | AF38: =IF($AF$8=$H38,$Q38,0) -> 0 | AG38: =IF($AF$8=$H38,$R38,0) -> 0 | AH38: =IF($AH$8=$H38,$Q38,0) -> 0 | AI38: =IF($AH$8=$H38,$R38,0) -> 0 | AJ38: =IF($AJ$8=$H38,$Q38,0) -> 0 | AK38: =IF($AJ$8=$H38,$R38,0) -> 0 | AL38: =IF($AL$8=$H38,$Q38,0) -> 0 | AM38: =IF($AL$8=$H38,$R38,0) -> 0 | AN38: =IF($AN$8=$H38,$Q38,0) -> 0 | AO38: =IF($AN$8=$H38,$R38,0) -> 0 | AP38: =IF($AP$8=$H38,$Q38,0) -> 0 | AQ38: =IF($AP$8=$H38,$R38,0) -> 0 | AR38: =IF($AR$8=$H38,$Q38,0) -> 0 | AS38: =IF($AR$8=$H38,$R38,0) -> 0 | AT38: =IF($AT$8=$H38,$Q38,0) -> 0 | AU38: =IF($AT$8=$H38,$R38,0) -> 0 | AV38: =IF($AV$8=$H38,$Q38,0) -> 12334250 | AW38: =IF($AV$8=$H38,$R38,0) -> 12403022 | AX38: =IF($AX$8=$H38,$Q38,0) -> 0 | AY38: =IF($AX$8=$H38,$R38,0) -> 0 | AZ38: =IF($AZ$8=$H38,$Q38,0) -> 0 | BA38: =IF($AZ$8=$H38,$R38,0) -> 0 | BB38: =IF($BB$8=$H38,$Q38,0) -> 0 | BC38: =IF($BB$8=$H38,$R38,0) -> 0 | BD38: =IF($BD$8=$H38,$Q38,0) -> 0 | BE38: =IF($BD$8=$H38,$R38,0) -> 0 | BF38: =IF($BF$8=$H38,$Q38,0) -> 0 | BG38: =IF($BF$8=$H38,$R38,0) -> 0
A39: 1-01-01-02-030 | B39: BANK TDH PAK-0081-004762-03-2 | C39: 1-01-01-02-030-BANK TDH PAK-0081-004762-03-2TDH Pak | D39: Balance Sheet | E39: Current Assets | F39: Cash And Bank Balances | G39: Cash With Banks In Current/Pls Accounts | H39: TDH Pak | I39: 260.1 | J39: 0 | K39: 0 | L39: 0 | M39: =+I39+K39 -> 260.1 | N39: =+J39+L39 -> 0 | Q39: =+M39+O39 -> 260.1 | R39: =+N39+P39 -> 0 | S39: =+Q39-R39 -> 260.1 | V39: =IF($V$8=$H39,$Q39,0) -> 0 | W39: =IF($V$8=$H39,$R39,0) -> 0 | X39: =IF($X$8=$H39,$Q39,0) -> 0 | Y39: =IF($X$8=$H39,$R39,0) -> 0 | Z39: =IF($Z$8=$H39,$Q39,0) -> 0 | AA39: =IF($Z$8=$H39,$R39,0) -> 0 | AB39: =IF($AB$8=$H39,$Q39,0) -> 0 | AC39: =IF($AB$8=$H39,$R39,0) -> 0 | AD39: =IF($AD$8=$H39,$Q39,0) -> 0 | AE39: =IF($AD$8=$H39,$R39,0) -> 0 | AF39: =IF($AF$8=$H39,$Q39,0) -> 0 | AG39: =IF($AF$8=$H39,$R39,0) -> 0 | AH39: =IF($AH$8=$H39,$Q39,0) -> 0 | AI39: =IF($AH$8=$H39,$R39,0) -> 0 | AJ39: =IF($AJ$8=$H39,$Q39,0) -> 0 | AK39: =IF($AJ$8=$H39,$R39,0) -> 0 | AL39: =IF($AL$8=$H39,$Q39,0) -> 0 | AM39: =IF($AL$8=$H39,$R39,0) -> 0 | AN39: =IF($AN$8=$H39,$Q39,0) -> 0 | AO39: =IF($AN$8=$H39,$R39,0) -> 0 | AP39: =IF($AP$8=$H39,$Q39,0) -> 0 | AQ39: =IF($AP$8=$H39,$R39,0) -> 0 | AR39: =IF($AR$8=$H39,$Q39,0) -> 0 | AS39: =IF($AR$8=$H39,$R39,0) -> 0 | AT39: =IF($AT$8=$H39,$Q39,0) -> 0 | AU39: =IF($AT$8=$H39,$R39,0) -> 0 | AV39: =IF($AV$8=$H39,$Q39,0) -> 0 | AW39: =IF($AV$8=$H39,$R39,0) -> 0 | AX39: =IF($AX$8=$H39,$Q39,0) -> 260.1 | AY39: =IF($AX$8=$H39,$R39,0) -> 0 | AZ39: =IF($AZ$8=$H39,$Q39,0) -> 0 | BA39: =IF($AZ$8=$H39,$R39,0) -> 0 | BB39: =IF($BB$8=$H39,$Q39,0) -> 0 | BC39: =IF($BB$8=$H39,$R39,0) -> 0 | BD39: =IF($BD$8=$H39,$Q39,0) -> 0 | BE39: =IF($BD$8=$H39,$R39,0) -> 0 | BF39: =IF($BF$8=$H39,$Q39,0) -> 0 | BG39: =IF($BF$8=$H39,$R39,0) -> 0
A40: 1-01-01-02-030 | B40: BANK TDH PAK-0081-004762-03-2 | C40: 1-01-01-02-030-BANK TDH PAK-0081-004762-03-2RRCCHR | D40: Balance Sheet | E40: Current Assets | F40: Cash And Bank Balances | G40: Cash With Banks In Current/Pls Accounts | H40: RRCCHR | I40: 0 | J40: 133.95 | K40: 0 | L40: 0 | M40: =+I40+K40 -> 0 | N40: =+J40+L40 -> 133.95 | Q40: =+M40+O40 -> 0 | R40: =+N40+P40 -> 133.95 | S40: =+Q40-R40 -> -133.95 | V40: =IF($V$8=$H40,$Q40,0) -> 0 | W40: =IF($V$8=$H40,$R40,0) -> 0 | X40: =IF($X$8=$H40,$Q40,0) -> 0 | Y40: =IF($X$8=$H40,$R40,0) -> 0 | Z40: =IF($Z$8=$H40,$Q40,0) -> 0 | AA40: =IF($Z$8=$H40,$R40,0) -> 0 | AB40: =IF($AB$8=$H40,$Q40,0) -> 0 | AC40: =IF($AB$8=$H40,$R40,0) -> 0 | AD40: =IF($AD$8=$H40,$Q40,0) -> 0 | AE40: =IF($AD$8=$H40,$R40,0) -> 0 | AF40: =IF($AF$8=$H40,$Q40,0) -> 0 | AG40: =IF($AF$8=$H40,$R40,0) -> 0 | AH40: =IF($AH$8=$H40,$Q40,0) -> 0 | AI40: =IF($AH$8=$H40,$R40,0) -> 0 | AJ40: =IF($AJ$8=$H40,$Q40,0) -> 0 | AK40: =IF($AJ$8=$H40,$R40,0) -> 0 | AL40: =IF($AL$8=$H40,$Q40,0) -> 0 | AM40: =IF($AL$8=$H40,$R40,0) -> 0 | AN40: =IF($AN$8=$H40,$Q40,0) -> 0 | AO40: =IF($AN$8=$H40,$R40,0) -> 0 | AP40: =IF($AP$8=$H40,$Q40,0) -> 0 | AQ40: =IF($AP$8=$H40,$R40,0) -> 0 | AR40: =IF($AR$8=$H40,$Q40,0) -> 0 | AS40: =IF($AR$8=$H40,$R40,0) -> 0 | AT40: =IF($AT$8=$H40,$Q40,0) -> 0 | AU40: =IF($AT$8=$H40,$R40,0) -> 0 | AV40: =IF($AV$8=$H40,$Q40,0) -> 0 | AW40: =IF($AV$8=$H40,$R40,0) -> 0 | AX40: =IF($AX$8=$H40,$Q40,0) -> 0 | AY40: =IF($AX$8=$H40,$R40,0) -> 0 | AZ40: =IF($AZ$8=$H40,$Q40,0) -> 0 | BA40: =IF($AZ$8=$H40,$R40,0) -> 133.95 | BB40: =IF($BB$8=$H40,$Q40,0) -> 0 | BC40: =IF($BB$8=$H40,$R40,0) -> 0 | BD40: =IF($BD$8=$H40,$Q40,0) -> 0 | BE40: =IF($BD$8=$H40,$R40,0) -> 0 | BF40: =IF($BF$8=$H40,$Q40,0) -> 0 | BG40: =IF($BF$8=$H40,$R40,0) -> 0
A41: 1-01-01-02-031 | B41: BANK SMALL PR-0081-004762-07-6 | C41: 1-01-01-02-031-BANK SMALL PR-0081-004762-07-6SHORT PROJECTS | D41: Balance Sheet | E41: Current Assets | F41: Cash And Bank Balances | G41: Cash With Banks In Current/Pls Accounts | H41: SHORT PROJECTS | I41: 13399790 | J41: 13189766 | K41: 0 | L41: 0 | M41: =+I41+K41 -> 13399790 | N41: =+J41+L41 -> 13189766 | Q41: =+M41+O41 -> 13399790 | R41: =+N41+P41 -> 13189766 | S41: =+Q41-R41 -> 210024.43 | V41: =IF($V$8=$H41,$Q41,0) -> 0 | W41: =IF($V$8=$H41,$R41,0) -> 0 | X41: =IF($X$8=$H41,$Q41,0) -> 0 | Y41: =IF($X$8=$H41,$R41,0) -> 0 | Z41: =IF($Z$8=$H41,$Q41,0) -> 0 | AA41: =IF($Z$8=$H41,$R41,0) -> 0 | AB41: =IF($AB$8=$H41,$Q41,0) -> 0 | AC41: =IF($AB$8=$H41,$R41,0) -> 0 | AD41: =IF($AD$8=$H41,$Q41,0) -> 0 | AE41: =IF($AD$8=$H41,$R41,0) -> 0 | AF41: =IF($AF$8=$H41,$Q41,0) -> 0 | AG41: =IF($AF$8=$H41,$R41,0) -> 0 | AH41: =IF($AH$8=$H41,$Q41,0) -> 0 | AI41: =IF($AH$8=$H41,$R41,0) -> 0 | AJ41: =IF($AJ$8=$H41,$Q41,0) -> 0 | AK41: =IF($AJ$8=$H41,$R41,0) -> 0 | AL41: =IF($AL$8=$H41,$Q41,0) -> 0 | AM41: =IF($AL$8=$H41,$R41,0) -> 0 | AN41: =IF($AN$8=$H41,$Q41,0) -> 0 | AO41: =IF($AN$8=$H41,$R41,0) -> 0 | AP41: =IF($AP$8=$H41,$Q41,0) -> 0 | AQ41: =IF($AP$8=$H41,$R41,0) -> 0 | AR41: =IF($AR$8=$H41,$Q41,0) -> 0 | AS41: =IF($AR$8=$H41,$R41,0) -> 0 | AT41: =IF($AT$8=$H41,$Q41,0) -> 0 | AU41: =IF($AT$8=$H41,$R41,0) -> 0 | AV41: =IF($AV$8=$H41,$Q41,0) -> 0 | AW41: =IF($AV$8=$H41,$R41,0) -> 0 | AX41: =IF($AX$8=$H41,$Q41,0) -> 0 | AY41: =IF($AX$8=$H41,$R41,0) -> 0 | AZ41: =IF($AZ$8=$H41,$Q41,0) -> 0 | BA41: =IF($AZ$8=$H41,$R41,0) -> 0 | BB41: =IF($BB$8=$H41,$Q41,0) -> 13399790 | BC41: =IF($BB$8=$H41,$R41,0) -> 13189766 | BD41: =IF($BD$8=$H41,$Q41,0) -> 0 | BE41: =IF($BD$8=$H41,$R41,0) -> 0 | BF41: =IF($BF$8=$H41,$Q41,0) -> 0 | BG41: =IF($BF$8=$H41,$R41,0) -> 0
A42: 1-01-01-02-031 | B42: BANK SMALL PR-0081-004762-07-6 | C42: Bank Small Pr-0081-004762-07-6 | D42: Balance Sheet | E42: Current Assets | F42: Cash And Bank Balances | G42: Cash With Banks In Current/Pls Accounts | H42: DAI | I42: 0 | J42: 180000 | K42: 0 | L42: 0 | M42: =+I42+K42 -> 0 | N42: =+J42+L42 -> 180000 | Q42: =+M42+O42 -> 0 | R42: =+N42+P42 -> 180000 | S42: =+Q42-R42 -> -180000 | V42: =IF($V$8=$H42,$Q42,0) -> 0 | W42: =IF($V$8=$H42,$R42,0) -> 0 | X42: =IF($X$8=$H42,$Q42,0) -> 0 | Y42: =IF($X$8=$H42,$R42,0) -> 0 | Z42: =IF($Z$8=$H42,$Q42,0) -> 0 | AA42: =IF($Z$8=$H42,$R42,0) -> 0 | AB42: =IF($AB$8=$H42,$Q42,0) -> 0 | AC42: =IF($AB$8=$H42,$R42,0) -> 0 | AD42: =IF($AD$8=$H42,$Q42,0) -> 0 | AE42: =IF($AD$8=$H42,$R42,0) -> 0 | AF42: =IF($AF$8=$H42,$Q42,0) -> 0 | AG42: =IF($AF$8=$H42,$R42,0) -> 0 | AH42: =IF($AH$8=$H42,$Q42,0) -> 0 | AI42: =IF($AH$8=$H42,$R42,0) -> 0 | AJ42: =IF($AJ$8=$H42,$Q42,0) -> 0 | AK42: =IF($AJ$8=$H42,$R42,0) -> 0 | AL42: =IF($AL$8=$H42,$Q42,0) -> 0 | AM42: =IF($AL$8=$H42,$R42,0) -> 0 | AN42: =IF($AN$8=$H42,$Q42,0) -> 0 | AO42: =IF($AN$8=$H42,$R42,0) -> 180000 | AP42: =IF($AP$8=$H42,$Q42,0) -> 0 | AQ42: =IF($AP$8=$H42,$R42,0) -> 0 | AR42: =IF($AR$8=$H42,$Q42,0) -> 0 | AS42: =IF($AR$8=$H42,$R42,0) -> 0 | AT42: =IF($AT$8=$H42,$Q42,0) -> 0 | AU42: =IF($AT$8=$H42,$R42,0) -> 0 | AV42: =IF($AV$8=$H42,$Q42,0) -> 0 | AW42: =IF($AV$8=$H42,$R42,0) -> 0 | AX42: =IF($AX$8=$H42,$Q42,0) -> 0 | AY42: =IF($AX$8=$H42,$R42,0) -> 0 | AZ42: =IF($AZ$8=$H42,$Q42,0) -> 0 | BA42: =IF($AZ$8=$H42,$R42,0) -> 0 | BB42: =IF($BB$8=$H42,$Q42,0) -> 0 | BC42: =IF($BB$8=$H42,$R42,0) -> 0 | BD42: =IF($BD$8=$H42,$Q42,0) -> 0 | BE42: =IF($BD$8=$H42,$R42,0) -> 0 | BF42: =IF($BF$8=$H42,$Q42,0) -> 0 | BG42: =IF($BF$8=$H42,$R42,0) -> 0
A43: 1-01-02-01-005 | B43: R/A-TDH-MI REBUILDING LIVE PRO | C43: 1-01-02-01-005-R/A-TDH-MI REBUILDING LIVE PRODeezire | D43: Balance Sheet | E43: Current Assets | F43: Loans, Advances, Deposits, Prepayments And Receivables | G43: Other Receivables | H43: Deezire | I43: 7638 | J43: 0 | K43: 0 | L43: 0 | M43: =+I43+K43 -> 7638 | N43: =+J43+L43 -> 0 | Q43: =+M43+O43 -> 7638 | R43: =+N43+P43 -> 0 | S43: =+Q43-R43 -> 7638 | V43: =IF($V$8=$H43,$Q43,0) -> 0 | W43: =IF($V$8=$H43,$R43,0) -> 0 | X43: =IF($X$8=$H43,$Q43,0) -> 0 | Y43: =IF($X$8=$H43,$R43,0) -> 0 | Z43: =IF($Z$8=$H43,$Q43,0) -> 0 | AA43: =IF($Z$8=$H43,$R43,0) -> 0 | AB43: =IF($AB$8=$H43,$Q43,0) -> 0 | AC43: =IF($AB$8=$H43,$R43,0) -> 0 | AD43: =IF($AD$8=$H43,$Q43,0) -> 0 | AE43: =IF($AD$8=$H43,$R43,0) -> 0 | AF43: =IF($AF$8=$H43,$Q43,0) -> 0 | AG43: =IF($AF$8=$H43,$R43,0) -> 0 | AH43: =IF($AH$8=$H43,$Q43,0) -> 0 | AI43: =IF($AH$8=$H43,$R43,0) -> 0 | AJ43: =IF($AJ$8=$H43,$Q43,0) -> 0 | AK43: =IF($AJ$8=$H43,$R43,0) -> 0 | AL43: =IF($AL$8=$H43,$Q43,0) -> 0 | AM43: =IF($AL$8=$H43,$R43,0) -> 0 | AN43: =IF($AN$8=$H43,$Q43,0) -> 0 | AO43: =IF($AN$8=$H43,$R43,0) -> 0 | AP43: =IF($AP$8=$H43,$Q43,0) -> 7638 | AQ43: =IF($AP$8=$H43,$R43,0) -> 0 | AR43: =IF($AR$8=$H43,$Q43,0) -> 0 | AS43: =IF($AR$8=$H43,$R43,0) -> 0 | AT43: =IF($AT$8=$H43,$Q43,0) -> 0 | AU43: =IF($AT$8=$H43,$R43,0) -> 0 | AV43: =IF($AV$8=$H43,$Q43,0) -> 0 | AW43: =IF($AV$8=$H43,$R43,0) -> 0 | AX43: =IF($AX$8=$H43,$Q43,0) -> 0 | AY43: =IF($AX$8=$H43,$R43,0) -> 0 | AZ43: =IF($AZ$8=$H43,$Q43,0) -> 0 | BA43: =IF($AZ$8=$H43,$R43,0) -> 0 | BB43: =IF($BB$8=$H43,$Q43,0) -> 0 | BC43: =IF($BB$8=$H43,$R43,0) -> 0 | BD43: =IF($BD$8=$H43,$Q43,0) -> 0 | BE43: =IF($BD$8=$H43,$R43,0) -> 0 | BF43: =IF($BF$8=$H43,$Q43,0) -> 0 | BG43: =IF($BF$8=$H43,$R43,0) -> 0
A44: 1-01-02-01-005 | B44: R/A-TDH-MI REBUILDING LIVE PRO | C44: 1-01-02-01-005-R/A-TDH-MI REBUILDING LIVE PROPILER | D44: Balance Sheet | E44: Current Assets | F44: Loans, Advances, Deposits, Prepayments And Receivables | G44: Other Receivables | H44: PILER | I44: 32238 | J44: 0 | K44: 0 | L44: 0 | M44: =+I44+K44 -> 32238 | N44: =+J44+L44 -> 0 | Q44: =+M44+O44 -> 32238 | R44: =+N44+P44 -> 0 | S44: =+Q44-R44 -> 32238 | V44: =IF($V$8=$H44,$Q44,0) -> 32238 | W44: =IF($V$8=$H44,$R44,0) -> 0 | X44: =IF($X$8=$H44,$Q44,0) -> 0 | Y44: =IF($X$8=$H44,$R44,0) -> 0 | Z44: =IF($Z$8=$H44,$Q44,0) -> 0 | AA44: =IF($Z$8=$H44,$R44,0) -> 0 | AB44: =IF($AB$8=$H44,$Q44,0) -> 0 | AC44: =IF($AB$8=$H44,$R44,0) -> 0 | AD44: =IF($AD$8=$H44,$Q44,0) -> 0 | AE44: =IF($AD$8=$H44,$R44,0) -> 0 | AF44: =IF($AF$8=$H44,$Q44,0) -> 0 | AG44: =IF($AF$8=$H44,$R44,0) -> 0 | AH44: =IF($AH$8=$H44,$Q44,0) -> 0 | AI44: =IF($AH$8=$H44,$R44,0) -> 0 | AJ44: =IF($AJ$8=$H44,$Q44,0) -> 0 | AK44: =IF($AJ$8=$H44,$R44,0) -> 0 | AL44: =IF($AL$8=$H44,$Q44,0) -> 0 | AM44: =IF($AL$8=$H44,$R44,0) -> 0 | AN44: =IF($AN$8=$H44,$Q44,0) -> 0 | AO44: =IF($AN$8=$H44,$R44,0) -> 0 | AP44: =IF($AP$8=$H44,$Q44,0) -> 0 | AQ44: =IF($AP$8=$H44,$R44,0) -> 0 | AR44: =IF($AR$8=$H44,$Q44,0) -> 0 | AS44: =IF($AR$8=$H44,$R44,0) -> 0 | AT44: =IF($AT$8=$H44,$Q44,0) -> 0 | AU44: =IF($AT$8=$H44,$R44,0) -> 0 | AV44: =IF($AV$8=$H44,$Q44,0) -> 0 | AW44: =IF($AV$8=$H44,$R44,0) -> 0 | AX44: =IF($AX$8=$H44,$Q44,0) -> 0 | AY44: =IF($AX$8=$H44,$R44,0) -> 0 | AZ44: =IF($AZ$8=$H44,$Q44,0) -> 0 | BA44: =IF($AZ$8=$H44,$R44,0) -> 0 | BB44: =IF($BB$8=$H44,$Q44,0) -> 0 | BC44: =IF($BB$8=$H44,$R44,0) -> 0 | BD44: =IF($BD$8=$H44,$Q44,0) -> 0 | BE44: =IF($BD$8=$H44,$R44,0) -> 0 | BF44: =IF($BF$8=$H44,$Q44,0) -> 0 | BG44: =IF($BF$8=$H44,$R44,0) -> 0
A45: 1-01-02-01-015 | B45: RECEIVABLE FROM IUF-QAMARULL | C45: 1-01-02-01-015-RECEIVABLE FROM IUF-QAMARULLPILER | D45: Balance Sheet | E45: Current Assets | F45: Loans, Advances, Deposits, Prepayments And Receivables | G45: Other Receivables | H45: PILER | I45: 8160 | J45: 0 | K45: 0 | L45: 0 | M45: =+I45+K45 -> 8160 | N45: =+J45+L45 -> 0 | Q45: =+M45+O45 -> 8160 | R45: =+N45+P45 -> 0 | S45: =+Q45-R45 -> 8160 | V45: =IF($V$8=$H45,$Q45,0) -> 8160 | W45: =IF($V$8=$H45,$R45,0) -> 0 | X45: =IF($X$8=$H45,$Q45,0) -> 0 | Y45: =IF($X$8=$H45,$R45,0) -> 0 | Z45: =IF($Z$8=$H45,$Q45,0) -> 0 | AA45: =IF($Z$8=$H45,$R45,0) -> 0 | AB45: =IF($AB$8=$H45,$Q45,0) -> 0 | AC45: =IF($AB$8=$H45,$R45,0) -> 0 | AD45: =IF($AD$8=$H45,$Q45,0) -> 0 | AE45: =IF($AD$8=$H45,$R45,0) -> 0 | AF45: =IF($AF$8=$H45,$Q45,0) -> 0 | AG45: =IF($AF$8=$H45,$R45,0) -> 0 | AH45: =IF($AH$8=$H45,$Q45,0) -> 0 | AI45: =IF($AH$8=$H45,$R45,0) -> 0 | AJ45: =IF($AJ$8=$H45,$Q45,0) -> 0 | AK45: =IF($AJ$8=$H45,$R45,0) -> 0 | AL45: =IF($AL$8=$H45,$Q45,0) -> 0 | AM45: =IF($AL$8=$H45,$R45,0) -> 0 | AN45: =IF($AN$8=$H45,$Q45,0) -> 0 | AO45: =IF($AN$8=$H45,$R45,0) -> 0 | AP45: =IF($AP$8=$H45,$Q45,0) -> 0 | AQ45: =IF($AP$8=$H45,$R45,0) -> 0 | AR45: =IF($AR$8=$H45,$Q45,0) -> 0 | AS45: =IF($AR$8=$H45,$R45,0) -> 0 | AT45: =IF($AT$8=$H45,$Q45,0) -> 0 | AU45: =IF($AT$8=$H45,$R45,0) -> 0 | AV45: =IF($AV$8=$H45,$Q45,0) -> 0 | AW45: =IF($AV$8=$H45,$R45,0) -> 0 | AX45: =IF($AX$8=$H45,$Q45,0) -> 0 | AY45: =IF($AX$8=$H45,$R45,0) -> 0 | AZ45: =IF($AZ$8=$H45,$Q45,0) -> 0 | BA45: =IF($AZ$8=$H45,$R45,0) -> 0 | BB45: =IF($BB$8=$H45,$Q45,0) -> 0 | BC45: =IF($BB$8=$H45,$R45,0) -> 0 | BD45: =IF($BD$8=$H45,$Q45,0) -> 0 | BE45: =IF($BD$8=$H45,$R45,0) -> 0 | BF45: =IF($BF$8=$H45,$Q45,0) -> 0 | BG45: =IF($BF$8=$H45,$R45,0) -> 0
... A70: 1-01-02-02-038 | B70: RECEIVABLE FROM SHUJAUDDIN | C70: 1-01-02-02-038-RECEIVABLE FROM SHUJAUDDINTrocaire | D70: Balance Sheet | E70: Current Assets | F70: Loans, Advances, Deposits, Prepayments And Receivables | G70: Other Receivables | H70: Trocaire | I70: 50 | J70: 0 | K70: 0 | L70: 0 | M70: =+I70+K70 -> 50 | N70: =+J70+L70 -> 0 | Q70: =+M70+O70 -> 50 | R70: =+N70+P70 -> 0 | S70: =+Q70-R70 -> 50 | V70: =IF($V$8=$H70,$Q70,0) -> 0 | W70: =IF($V$8=$H70,$R70,0) -> 0 | X70: =IF($X$8=$H70,$Q70,0) -> 0 | Y70: =IF($X$8=$H70,$R70,0) -> 0 | Z70: =IF($Z$8=$H70,$Q70,0) -> 0 | AA70: =IF($Z$8=$H70,$R70,0) -> 0 | AB70: =IF($AB$8=$H70,$Q70,0) -> 0 | AC70: =IF($AB$8=$H70,$R70,0) -> 0 | AD70: =IF($AD$8=$H70,$Q70,0) -> 0 | AE70: =IF($AD$8=$H70,$R70,0) -> 0 | AF70: =IF($AF$8=$H70,$Q70,0) -> 0 | AG70: =IF($AF$8=$H70,$R70,0) -> 0 | AH70: =IF($AH$8=$H70,$Q70,0) -> 0 | AI70: =IF($AH$8=$H70,$R70,0) -> 0 | AJ70: =IF($AJ$8=$H70,$Q70,0) -> 50 | AK70: =IF($AJ$8=$H70,$R70,0) -> 0 | AL70: =IF($AL$8=$H70,$Q70,0) -> 0 | AM70: =IF($AL$8=$H70,$R70,0) -> 0 | AN70: =IF($AN$8=$H70,$Q70,0) -> 0 | AO70: =IF($AN$8=$H70,$R70,0) -> 0 | AP70: =IF($AP$8=$H70,$Q70,0) -> 0 | AQ70: =IF($AP$8=$H70,$R70,0) -> 0 | AR70: =IF($AR$8=$H70,$Q70,0) -> 0 | AS70: =IF($AR$8=$H70,$R70,0) -> 0 | AT70: =IF($AT$8=$H70,$Q70,0) -> 0 | AU70: =IF($AT$8=$H70,$R70,0) -> 0 | AV70: =IF($AV$8=$H70,$Q70,0) -> 0 | AW70: =IF($AV$8=$H70,$R70,0) -> 0 | AX70: =IF($AX$8=$H70,$Q70,0) -> 0 | AY70: =IF($AX$8=$H70,$R70,0) -> 0 | AZ70: =IF($AZ$8=$H70,$Q70,0) -> 0 | BA70: =IF($AZ$8=$H70,$R70,0) -> 0 | BB70: =IF($BB$8=$H70,$Q70,0) -> 0 | BC70: =IF($BB$8=$H70,$R70,0) -> 0 | BD70: =IF($BD$8=$H70,$Q70,0) -> 0 | BE70: =IF($BD$8=$H70,$R70,0) -> 0 | BF70: =IF($BF$8=$H70,$Q70,0) -> 0 | BG70: =IF($BF$8=$H70,$R70,0) -> 0
A71: 1-01-02-02-038 | B71: RECEIVABLE FROM SHUJAUDDIN | C71: 1-01-02-02-038-RECEIVABLE FROM SHUJAUDDINPILER | D71: Balance Sheet | E71: Current Assets | F71: Loans, Advances, Deposits, Prepayments And Receivables | G71: Other Receivables | H71: PILER | I71: 129540 | J71: 0 | K71: 0 | L71: 0 | M71: =+I71+K71 -> 129540 | N71: =+J71+L71 -> 0 | Q71: =+M71+O71 -> 129540 | R71: =+N71+P71 -> 0 | S71: =+Q71-R71 -> 129540
A72: 1-01-02-02-040 | B72: RECEIVABLE FROM KARAMAT ALI | C72: 1-01-02-02-040-RECEIVABLE FROM KARAMAT ALIDeezire | D72: Balance Sheet | E72: Current Assets | F72: Loans, Advances, Deposits, Prepayments And Receivables | G72: Other Receivables | H72: Deezire | I72: 11780 | J72: 0 | K72: 0 | L72: 0 | M72: =+I72+K72 -> 11780 | N72: =+J72+L72 -> 0 | Q72: =+M72+O72 -> 11780 | R72: =+N72+P72 -> 0 | S72: =+Q72-R72 -> 11780 | V72: =IF($V$8=$H72,$Q72,0) -> 0 | W72: =IF($V$8=$H72,$R72,0) -> 0 | X72: =IF($X$8=$H72,$Q72,0) -> 0 | Y72: =IF($X$8=$H72,$R72,0) -> 0 | Z72: =IF($Z$8=$H72,$Q72,0) -> 0 | AA72: =IF($Z$8=$H72,$R72,0) -> 0 | AB72: =IF($AB$8=$H72,$Q72,0) -> 0 | AC72: =IF($AB$8=$H72,$R72,0) -> 0 | AD72: =IF($AD$8=$H72,$Q72,0) -> 0 | AE72: =IF($AD$8=$H72,$R72,0) -> 0 | AF72: =IF($AF$8=$H72,$Q72,0) -> 0 | AG72: =IF($AF$8=$H72,$R72,0) -> 0 | AH72: =IF($AH$8=$H72,$Q72,0) -> 0 | AI72: =IF($AH$8=$H72,$R72,0) -> 0 | AJ72: =IF($AJ$8=$H72,$Q72,0) -> 0 | AK72: =IF($AJ$8=$H72,$R72,0) -> 0 | AL72: =IF($AL$8=$H72,$Q72,0) -> 0 | AM72: =IF($AL$8=$H72,$R72,0) -> 0 | AN72: =IF($AN$8=$H72,$Q72,0) -> 0 | AO72: =IF($AN$8=$H72,$R72,0) -> 0 | AP72: =IF($AP$8=$H72,$Q72,0) -> 11780 | AQ72: =IF($AP$8=$H72,$R72,0) -> 0 | AR72: =IF($AR$8=$H72,$Q72,0) -> 0 | AS72: =IF($AR$8=$H72,$R72,0) -> 0 | AT72: =IF($AT$8=$H72,$Q72,0) -> 0 | AU72: =IF($AT$8=$H72,$R72,0) -> 0 | AV72: =IF($AV$8=$H72,$Q72,0) -> 0 | AW72: =IF($AV$8=$H72,$R72,0) -> 0 | AX72: =IF($AX$8=$H72,$Q72,0) -> 0 | AY72: =IF($AX$8=$H72,$R72,0) -> 0 | AZ72: =IF($AZ$8=$H72,$Q72,0) -> 0 | BA72: =IF($AZ$8=$H72,$R72,0) -> 0 | BB72: =IF($BB$8=$H72,$Q72,0) -> 0 | BC72: =IF($BB$8=$H72,$R72,0) -> 0 | BD72: =IF($BD$8=$H72,$Q72,0) -> 0 | BE72: =IF($BD$8=$H72,$R72,0) -> 0 | BF72: =IF($BF$8=$H72,$Q72,0) -> 0 | BG72: =IF($BF$8=$H72,$R72,0) -> 0
A73: 1-01-02-02-040 | B73: RECEIVABLE FROM KARAMAT ALI | C73: 1-01-02-02-040-RECEIVABLE FROM KARAMAT ALIPILER | D73: Balance Sheet | E73: Current Assets | F73: Loans, Advances, Deposits, Prepayments And Receivables | G73: Other Receivables | H73: PILER | I73: 38713 | J73: 0 | K73: 0 | L73: 0 | M73: =+I73+K73 -> 38713 | N73: =+J73+L73 -> 0 | Q73: =+M73+O73 -> 38713 | R73: =+N73+P73 -> 0 | S73: =+Q73-R73 -> 38713 | V73: =IF($V$8=$H73,$Q73,0) -> 38713 | W73: =IF($V$8=$H73,$R73,0) -> 0 | X73: =IF($X$8=$H73,$Q73,0) -> 0 | Y73: =IF($X$8=$H73,$R73,0) -> 0 | Z73: =IF($Z$8=$H73,$Q73,0) -> 0 | AA73: =IF($Z$8=$H73,$R73,0) -> 0 | AB73: =IF($AB$8=$H73,$Q73,0) -> 0 | AC73: =IF($AB$8=$H73,$R73,0) -> 0 | AD73: =IF($AD$8=$H73,$Q73,0) -> 0 | AE73: =IF($AD$8=$H73,$R73,0) -> 0 | AF73: =IF($AF$8=$H73,$Q73,0) -> 0 | AG73: =IF($AF$8=$H73,$R73,0) -> 0 | AH73: =IF($AH$8=$H73,$Q73,0) -> 0 | AI73: =IF($AH$8=$H73,$R73,0) -> 0 | AJ73: =IF($AJ$8=$H73,$Q73,0) -> 0 | AK73: =IF($AJ$8=$H73,$R73,0) -> 0 | AL73: =IF($AL$8=$H73,$Q73,0) -> 0 | AM73: =IF($AL$8=$H73,$R73,0) -> 0 | AN73: =IF($AN$8=$H73,$Q73,0) -> 0 | AO73: =IF($AN$8=$H73,$R73,0) -> 0 | AP73: =IF($AP$8=$H73,$Q73,0) -> 0 | AQ73: =IF($AP$8=$H73,$R73,0) -> 0 | AR73: =IF($AR$8=$H73,$Q73,0) -> 0 | AS73: =IF($AR$8=$H73,$R73,0) -> 0 | AT73: =IF($AT$8=$H73,$Q73,0) -> 0 | AU73: =IF($AT$8=$H73,$R73,0) -> 0 | AV73: =IF($AV$8=$H73,$Q73,0) -> 0 | AW73: =IF($AV$8=$H73,$R73,0) -> 0 | AX73: =IF($AX$8=$H73,$Q73,0) -> 0 | AY73: =IF($AX$8=$H73,$R73,0) -> 0 | AZ73: =IF($AZ$8=$H73,$Q73,0) -> 0 | BA73: =IF($AZ$8=$H73,$R73,0) -> 0 | BB73: =IF($BB$8=$H73,$Q73,0) -> 0 | BC73: =IF($BB$8=$H73,$R73,0) -> 0 | BD73: =IF($BD$8=$H73,$Q73,0) -> 0 | BE73: =IF($BD$8=$H73,$R73,0) -> 0 | BF73: =IF($BF$8=$H73,$Q73,0) -> 0 | BG73: =IF($BF$8=$H73,$R73,0) -> 0
A74: 1-01-02-02-042 | B74: RECEIVABLE FROM DANISH | C74: 1-01-02-02-042-RECEIVABLE FROM DANISHTrocaire | D74: Balance Sheet | E74: Current Assets | F74: Loans, Advances, Deposits, Prepayments And Receivables | G74: Other Receivables | H74: Trocaire | I74: 50 | J74: 0 | K74: 0 | L74: 0 | M74: =+I74+K74 -> 50 | N74: =+J74+L74 -> 0 | Q74: =+M74+O74 -> 50 | R74: =+N74+P74 -> 0 | S74: =+Q74-R74 -> 50 | V74: =IF($V$8=$H74,$Q74,0) -> 0 | W74: =IF($V$8=$H74,$R74,0) -> 0 | X74: =IF($X$8=$H74,$Q74,0) -> 0 | Y74: =IF($X$8=$H74,$R74,0) -> 0 | Z74: =IF($Z$8=$H74,$Q74,0) -> 0 | AA74: =IF($Z$8=$H74,$R74,0) -> 0 | AB74: =IF($AB$8=$H74,$Q74,0) -> 0 | AC74: =IF($AB$8=$H74,$R74,0) -> 0 | AD74: =IF($AD$8=$H74,$Q74,0) -> 0 | AE74: =IF($AD$8=$H74,$R74,0) -> 0 | AF74: =IF($AF$8=$H74,$Q74,0) -> 0 | AG74: =IF($AF$8=$H74,$R74,0) -> 0 | AH74: =IF($AH$8=$H74,$Q74,0) -> 0 | AI74: =IF($AH$8=$H74,$R74,0) -> 0 | AJ74: =IF($AJ$8=$H74,$Q74,0) -> 50 | AK74: =IF($AJ$8=$H74,$R74,0) -> 0 | AL74: =IF($AL$8=$H74,$Q74,0) -> 0 | AM74: =IF($AL$8=$H74,$R74,0) -> 0 | AN74: =IF($AN$8=$H74,$Q74,0) -> 0 | AO74: =IF($AN$8=$H74,$R74,0) -> 0 | AP74: =IF($AP$8=$H74,$Q74,0) -> 0 | AQ74: =IF($AP$8=$H74,$R74,0) -> 0 | AR74: =IF($AR$8=$H74,$Q74,0) -> 0 | AS74: =IF($AR$8=$H74,$R74,0) -> 0 | AT74: =IF($AT$8=$H74,$Q74,0) -> 0 | AU74: =IF($AT$8=$H74,$R74,0) -> 0 | AV74: =IF($AV$8=$H74,$Q74,0) -> 0 | AW74: =IF($AV$8=$H74,$R74,0) -> 0 | AX74: =IF($AX$8=$H74,$Q74,0) -> 0 | AY74: =IF($AX$8=$H74,$R74,0) -> 0 | AZ74: =IF($AZ$8=$H74,$Q74,0) -> 0 | BA74: =IF($AZ$8=$H74,$R74,0) -> 0 | BB74: =IF($BB$8=$H74,$Q74,0) -> 0 | BC74: =IF($BB$8=$H74,$R74,0) -> 0 | BD74: =IF($BD$8=$H74,$Q74,0) -> 0 | BE74: =IF($BD$8=$H74,$R74,0) -> 0 | BF74: =IF($BF$8=$H74,$Q74,0) -> 0 | BG74: =IF($BF$8=$H74,$R74,0) -> 0
A75: 1-01-02-02-042 | B75: RECEIVABLE FROM DANISH | C75: 1-01-02-02-042-RECEIVABLE FROM DANISHETI | D75: Balance Sheet | E75: Current Assets | F75: Loans, Advances, Deposits, Prepayments And Receivables | G75: Other Receivables | H75: ETI | I75: 90 | J75: 0 | K75: 0 | L75: 0 | M75: =+I75+K75 -> 90 | N75: =+J75+L75 -> 0 | Q75: =+M75+O75 -> 90 | R75: =+N75+P75 -> 0 | S75: =+Q75-R75 -> 90 | V75: =IF($V$8=$H75,$Q75,0) -> 0 | W75: =IF($V$8=$H75,$R75,0) -> 0 | X75: =IF($X$8=$H75,$Q75,0) -> 0 | Y75: =IF($X$8=$H75,$R75,0) -> 0 | Z75: =IF($Z$8=$H75,$Q75,0) -> 0 | AA75: =IF($Z$8=$H75,$R75,0) -> 0 | AB75: =IF($AB$8=$H75,$Q75,0) -> 0 | AC75: =IF($AB$8=$H75,$R75,0) -> 0 | AD75: =IF($AD$8=$H75,$Q75,0) -> 90 | AE75: =IF($AD$8=$H75,$R75,0) -> 0 | AF75: =IF($AF$8=$H75,$Q75,0) -> 0 | AG75: =IF($AF$8=$H75,$R75,0) -> 0 | AH75: =IF($AH$8=$H75,$Q75,0) -> 0 | AI75: =IF($AH$8=$H75,$R75,0) -> 0 | AJ75: =IF($AJ$8=$H75,$Q75,0) -> 0 | AK75: =IF($AJ$8=$H75,$R75,0) -> 0 | AL75: =IF($AL$8=$H75,$Q75,0) -> 0 | AM75: =IF($AL$8=$H75,$R75,0) -> 0 | AN75: =IF($AN$8=$H75,$Q75,0) -> 0 | AO75: =IF($AN$8=$H75,$R75,0) -> 0 | AP75: =IF($AP$8=$H75,$Q75,0) -> 0 | AQ75: =IF($AP$8=$H75,$R75,0) -> 0 | AR75: =IF($AR$8=$H75,$Q75,0) -> 0 | AS75: =IF($AR$8=$H75,$R75,0) -> 0 | AT75: =IF($AT$8=$H75,$Q75,0) -> 0 | AU75: =IF($AT$8=$H75,$R75,0) -> 0 | AV75: =IF($AV$8=$H75,$Q75,0) -> 0 | AW75: =IF($AV$8=$H75,$R75,0) -> 0 | AX75: =IF($AX$8=$H75,$Q75,0) -> 0 | AY75: =IF($AX$8=$H75,$R75,0) -> 0 | AZ75: =IF($AZ$8=$H75,$Q75,0) -> 0 | BA75: =IF($AZ$8=$H75,$R75,0) -> 0 | BB75: =IF($BB$8=$H75,$Q75,0) -> 0 | BC75: =IF($BB$8=$H75,$R75,0) -> 0 | BD75: =IF($BD$8=$H75,$Q75,0) -> 0 | BE75: =IF($BD$8=$H75,$R75,0) -> 0 | BF75: =IF($BF$8=$H75,$Q75,0) -> 0 | BG75: =IF($BF$8=$H75,$R75,0) -> 0
A76: 1-01-02-02-043 | B76: RECEIVABLE FROM PERVEZ AHMED | C76: 1-01-02-02-043-RECEIVABLE FROM PERVEZ AHMEDDeezire | D76: Balance Sheet | E76: Current Assets | F76: Loans, Advances, Deposits, Prepayments And Receivables | G76: Other Receivables | H76: Deezire | I76: 80 | J76: 0 | K76: 0 | L76: 0 | M76: =+I76+K76 -> 80 | N76: =+J76+L76 -> 0 | Q76: =+M76+O76 -> 80 | R76: =+N76+P76 -> 0 | S76: =+Q76-R76 -> 80 | V76: =IF($V$8=$H76,$Q76,0) -> 0 | W76: =IF($V$8=$H76,$R76,0) -> 0 | X76: =IF($X$8=$H76,$Q76,0) -> 0 | Y76: =IF($X$8=$H76,$R76,0) -> 0 | Z76: =IF($Z$8=$H76,$Q76,0) -> 0 | AA76: =IF($Z$8=$H76,$R76,0) -> 0 | AB76: =IF($AB$8=$H76,$Q76,0) -> 0 | AC76: =IF($AB$8=$H76,$R76,0) -> 0 | AD76: =IF($AD$8=$H76,$Q76,0) -> 0 | AE76: =IF($AD$8=$H76,$R76,0) -> 0 | AF76: =IF($AF$8=$H76,$Q76,0) -> 0 | AG76: =IF($AF$8=$H76,$R76,0) -> 0 | AH76: =IF($AH$8=$H76,$Q76,0) -> 0 | AI76: =IF($AH$8=$H76,$R76,0) -> 0 | AJ76: =IF($AJ$8=$H76,$Q76,0) -> 0 | AK76: =IF($AJ$8=$H76,$R76,0) -> 0 | AL76: =IF($AL$8=$H76,$Q76,0) -> 0 | AM76: =IF($AL$8=$H76,$R76,0) -> 0 | AN76: =IF($AN$8=$H76,$Q76,0) -> 0 | AO76: =IF($AN$8=$H76,$R76,0) -> 0 | AP76: =IF($AP$8=$H76,$Q76,0) -> 80 | AQ76: =IF($AP$8=$H76,$R76,0) -> 0 | AR76: =IF($AR$8=$H76,$Q76,0) -> 0 | AS76: =IF($AR$8=$H76,$R76,0) -> 0 | AT76: =IF($AT$8=$H76,$Q76,0) -> 0 | AU76: =IF($AT$8=$H76,$R76,0) -> 0 | AV76: =IF($AV$8=$H76,$Q76,0) -> 0 | AW76: =IF($AV$8=$H76,$R76,0) -> 0 | AX76: =IF($AX$8=$H76,$Q76,0) -> 0 | AY76: =IF($AX$8=$H76,$R76,0) -> 0 | AZ76: =IF($AZ$8=$H76,$Q76,0) -> 0 | BA76: =IF($AZ$8=$H76,$R76,0) -> 0 | BB76: =IF($BB$8=$H76,$Q76,0) -> 0 | BC76: =IF($BB$8=$H76,$R76,0) -> 0 | BD76: =IF($BD$8=$H76,$Q76,0) -> 0 | BE76: =IF($BD$8=$H76,$R76,0) -> 0 | BF76: =IF($BF$8=$H76,$Q76,0) -> 0 | BG76: =IF($BF$8=$H76,$R76,0) -> 0
A77: 1-01-02-02-043 | B77: RECEIVABLE FROM PERVEZ AHMED | C77: 1-01-02-02-043-RECEIVABLE FROM PERVEZ AHMEDPILER | D77: Balance Sheet | E77: Current Assets | F77: Loans, Advances, Deposits, Prepayments And Receivables | G77: Other Receivables | H77: PILER | I77: 5591 | J77: 0 | K77: 0 | L77: 0 | M77: =+I77+K77 -> 5591 | N77: =+J77+L77 -> 0 | Q77: =+M77+O77 -> 5591 | R77: =+N77+P77 -> 0 | S77: =+Q77-R77 -> 5591 | V77: =IF($V$8=$H77,$Q77,0) -> 5591 | W77: =IF($V$8=$H77,$R77,0) -> 0 | X77: =IF($X$8=$H77,$Q77,0) -> 0 | Y77: =IF($X$8=$H77,$R77,0) -> 0 | Z77: =IF($Z$8=$H77,$Q77,0) -> 0 | AA77: =IF($Z$8=$H77,$R77,0) -> 0 | AB77: =IF($AB$8=$H77,$Q77,0) -> 0 | AC77: =IF($AB$8=$H77,$R77,0) -> 0 | AD77: =IF($AD$8=$H77,$Q77,0) -> 0 | AE77: =IF($AD$8=$H77,$R77,0) -> 0 | AF77: =IF($AF$8=$H77,$Q77,0) -> 0 | AG77: =IF($AF$8=$H77,$R77,0) -> 0 | AH77: =IF($AH$8=$H77,$Q77,0) -> 0 | AI77: =IF($AH$8=$H77,$R77,0) -> 0 | AJ77: =IF($AJ$8=$H77,$Q77,0) -> 0 | AK77: =IF($AJ$8=$H77,$R77,0) -> 0 | AL77: =IF($AL$8=$H77,$Q77,0) -> 0 | AM77: =IF($AL$8=$H77,$R77,0) -> 0 | AN77: =IF($AN$8=$H77,$Q77,0) -> 0 | AO77: =IF($AN$8=$H77,$R77,0) -> 0 | AP77: =IF($AP$8=$H77,$Q77,0) -> 0 | AQ77: =IF($AP$8=$H77,$R77,0) -> 0 | AR77: =IF($AR$8=$H77,$Q77,0) -> 0 | AS77: =IF($AR$8=$H77,$R77,0) -> 0 | AT77: =IF($AT$8=$H77,$Q77,0) -> 0 | AU77: =IF($AT$8=$H77,$R77,0) -> 0 | AV77: =IF($AV$8=$H77,$Q77,0) -> 0 | AW77: =IF($AV$8=$H77,$R77,0) -> 0 | AX77: =IF($AX$8=$H77,$Q77,0) -> 0 | AY77: =IF($AX$8=$H77,$R77,0) -> 0 | AZ77: =IF($AZ$8=$H77,$Q77,0) -> 0 | BA77: =IF($AZ$8=$H77,$R77,0) -> 0 | BB77: =IF($BB$8=$H77,$Q77,0) -> 0 | BC77: =IF($BB$8=$H77,$R77,0) -> 0 | BD77: =IF($BD$8=$H77,$Q77,0) -> 0 | BE77: =IF($BD$8=$H77,$R77,0) -> 0 | BF77: =IF($BF$8=$H77,$Q77,0) -> 0 | BG77: =IF($BF$8=$H77,$R77,0) -> 0
A78: 1-01-02-02-043 | B78: RECEIVABLE FROM PERVEZ AHMED | C78: 1-01-02-02-043-RECEIVABLE FROM PERVEZ AHMEDSHORT PROJECTS | D78: Balance Sheet | E78: Current Assets | F78: Loans, Advances, Deposits, Prepayments And Receivables | G78: Other Receivables | H78: SHORT PROJECTS | I78: 22 | J78: 0 | K78: 0 | L78: 0 | M78: =+I78+K78 -> 22 | N78: =+J78+L78 -> 0 | Q78: =+M78+O78 -> 22 | R78: =+N78+P78 -> 0 | S78: =+Q78-R78 -> 22 | V78: =IF($V$8=$H78,$Q78,0) -> 0 | W78: =IF($V$8=$H78,$R78,0) -> 0 | X78: =IF($X$8=$H78,$Q78,0) -> 0 | Y78: =IF($X$8=$H78,$R78,0) -> 0 | Z78: =IF($Z$8=$H78,$Q78,0) -> 0 | AA78: =IF($Z$8=$H78,$R78,0) -> 0 | AB78: =IF($AB$8=$H78,$Q78,0) -> 0 | AC78: =IF($AB$8=$H78,$R78,0) -> 0 | AD78: =IF($AD$8=$H78,$Q78,0) -> 0 | AE78: =IF($AD$8=$H78,$R78,0) -> 0 | AF78: =IF($AF$8=$H78,$Q78,0) -> 0 | AG78: =IF($AF$8=$H78,$R78,0) -> 0 | AH78: =IF($AH$8=$H78,$Q78,0) -> 0 | AI78: =IF($AH$8=$H78,$R78,0) -> 0 | AJ78: =IF($AJ$8=$H78,$Q78,0) -> 0 | AK78: =IF($AJ$8=$H78,$R78,0) -> 0 | AL78: =IF($AL$8=$H78,$Q78,0) -> 0 | AM78: =IF($AL$8=$H78,$R78,0) -> 0 | AN78: =IF($AN$8=$H78,$Q78,0) -> 0 | AO78: =IF($AN$8=$H78,$R78,0) -> 0 | AP78: =IF($AP$8=$H78,$Q78,0) -> 0 | AQ78: =IF($AP$8=$H78,$R78,0) -> 0 | AR78: =IF($AR$8=$H78,$Q78,0) -> 0 | AS78: =IF($AR$8=$H78,$R78,0) -> 0 | AT78: =IF($AT$8=$H78,$Q78,0) -> 0 | AU78: =IF($AT$8=$H78,$R78,0) -> 0 | AV78: =IF($AV$8=$H78,$Q78,0) -> 0 | AW78: =IF($AV$8=$H78,$R78,0) -> 0 | AX78: =IF($AX$8=$H78,$Q78,0) -> 0 | AY78: =IF($AX$8=$H78,$R78,0) -> 0 | AZ78: =IF($AZ$8=$H78,$Q78,0) -> 0 | BA78: =IF($AZ$8=$H78,$R78,0) -> 0 | BB78: =IF($BB$8=$H78,$Q78,0) -> 22 | BC78: =IF($BB$8=$H78,$R78,0) -> 0 | BD78: =IF($BD$8=$H78,$Q78,0) -> 0 | BE78: =IF($BD$8=$H78,$R78,0) -> 0 | BF78: =IF($BF$8=$H78,$Q78,0) -> 0 | BG78: =IF($BF$8=$H78,$R78,0) -> 0
A79: 1-01-02-02-043 | B79: RECEIVABLE FROM PERVEZ AHMED | C79: 1-01-02-02-043-RECEIVABLE FROM PERVEZ AHMEDUNICEF-2 | D79: Balance Sheet | E79: Current Assets | F79: Loans, Advances, Deposits, Prepayments And Receivables | G79: Other Receivables | H79: UNICEF-2 | I79: 0 | J79: 240 | K79: 0 | L79: 0 | M79: =+I79+K79 -> 0 | N79: =+J79+L79 -> 240 | Q79: =+M79+O79 -> 0 | R79: =+N79+P79 -> 240 | S79: =+Q79-R79 -> -240 | V79: =IF($V$8=$H79,$Q79,0) -> 0 | W79: =IF($V$8=$H79,$R79,0) -> 0 | X79: =IF($X$8=$H79,$Q79,0) -> 0 | Y79: =IF($X$8=$H79,$R79,0) -> 0 | Z79: =IF($Z$8=$H79,$Q79,0) -> 0 | AA79: =IF($Z$8=$H79,$R79,0) -> 0 | AB79: =IF($AB$8=$H79,$Q79,0) -> 0 | AC79: =IF($AB$8=$H79,$R79,0) -> 0 | AD79: =IF($AD$8=$H79,$Q79,0) -> 0 | AE79: =IF($AD$8=$H79,$R79,0) -> 0 | AF79: =IF($AF$8=$H79,$Q79,0) -> 0 | AG79: =IF($AF$8=$H79,$R79,0) -> 240 | AH79: =IF($AH$8=$H79,$Q79,0) -> 0 | AI79: =IF($AH$8=$H79,$R79,0) -> 0 | AJ79: =IF($AJ$8=$H79,$Q79,0) -> 0 | AK79: =IF($AJ$8=$H79,$R79,0) -> 0 | AL79: =IF($AL$8=$H79,$Q79,0) -> 0 | AM79: =IF($AL$8=$H79,$R79,0) -> 0 | AN79: =IF($AN$8=$H79,$Q79,0) -> 0 | AO79: =IF($AN$8=$H79,$R79,0) -> 0 | AP79: =IF($AP$8=$H79,$Q79,0) -> 0 | AQ79: =IF($AP$8=$H79,$R79,0) -> 0 | AR79: =IF($AR$8=$H79,$Q79,0) -> 0 | AS79: =IF($AR$8=$H79,$R79,0) -> 0 | AT79: =IF($AT$8=$H79,$Q79,0) -> 0 | AU79: =IF($AT$8=$H79,$R79,0) -> 0 | AV79: =IF($AV$8=$H79,$Q79,0) -> 0 | AW79: =IF($AV$8=$H79,$R79,0) -> 0 | AX79: =IF($AX$8=$H79,$Q79,0) -> 0 | AY79: =IF($AX$8=$H79,$R79,0) -> 0 | AZ79: =IF($AZ$8=$H79,$Q79,0) -> 0 | BA79: =IF($AZ$8=$H79,$R79,0) -> 0 | BB79: =IF($BB$8=$H79,$Q79,0) -> 0 | BC79: =IF($BB$8=$H79,$R79,0) -> 0 | BD79: =IF($BD$8=$H79,$Q79,0) -> 0 | BE79: =IF($BD$8=$H79,$R79,0) -> 0 | BF79: =IF($BF$8=$H79,$Q79,0) -> 0 | BG79: =IF($BF$8=$H79,$R79,0) -> 0
A80: 1-01-02-02-043 | B80: RECEIVABLE FROM PERVEZ AHMED | C80: 1-01-02-02-043-RECEIVABLE FROM PERVEZ AHMEDFNV | D80: Balance Sheet | E80: Current Assets | F80: Loans, Advances, Deposits, Prepayments And Receivables | G80: Other Receivables | H80: FNV | I80: 80 | J80: 0 | K80: 0 | L80: 0 | M80: =+I80+K80 -> 80 | N80: =+J80+L80 -> 0 | Q80: =+M80+O80 -> 80 | R80: =+N80+P80 -> 0 | S80: =+Q80-R80 -> 80 | V80: =IF($V$8=$H80,$Q80,0) -> 0 | W80: =IF($V$8=$H80,$R80,0) -> 0 | X80: =IF($X$8=$H80,$Q80,0) -> 0 | Y80: =IF($X$8=$H80,$R80,0) -> 0 | Z80: =IF($Z$8=$H80,$Q80,0) -> 0 | AA80: =IF($Z$8=$H80,$R80,0) -> 0 | AB80: =IF($AB$8=$H80,$Q80,0) -> 0 | AC80: =IF($AB$8=$H80,$R80,0) -> 0 | AD80: =IF($AD$8=$H80,$Q80,0) -> 0 | AE80: =IF($AD$8=$H80,$R80,0) -> 0 | AF80: =IF($AF$8=$H80,$Q80,0) -> 0 | AG80: =IF($AF$8=$H80,$R80,0) -> 0 | AH80: =IF($AH$8=$H80,$Q80,0) -> 0 | AI80: =IF($AH$8=$H80,$R80,0) -> 0 | AJ80: =IF($AJ$8=$H80,$Q80,0) -> 0 | AK80: =IF($AJ$8=$H80,$R80,0) -> 0 | AL80: =IF($AL$8=$H80,$Q80,0) -> 0 | AM80: =IF($AL$8=$H80,$R80,0) -> 0 | AN80: =IF($AN$8=$H80,$Q80,0) -> 0 | AO80: =IF($AN$8=$H80,$R80,0) -> 0 | AP80: =IF($AP$8=$H80,$Q80,0) -> 0 | AQ80: =IF($AP$8=$H80,$R80,0) -> 0 | AR80: =IF($AR$8=$H80,$Q80,0) -> 80 | AS80: =IF($AR$8=$H80,$R80,0) -> 0 | AT80: =IF($AT$8=$H80,$Q80,0) -> 0 | AU80: =IF($AT$8=$H80,$R80,0) -> 0 | AV80: =IF($AV$8=$H80,$Q80,0) -> 0 | AW80: =IF($AV$8=$H80,$R80,0) -> 0 | AX80: =IF($AX$8=$H80,$Q80,0) -> 0 | AY80: =IF($AX$8=$H80,$R80,0) -> 0 | AZ80: =IF($AZ$8=$H80,$Q80,0) -> 0 | BA80: =IF($AZ$8=$H80,$R80,0) -> 0 | BB80: =IF($BB$8=$H80,$Q80,0) -> 0 | BC80: =IF($BB$8=$H80,$R80,0) -> 0 | BD80: =IF($BD$8=$H80,$Q80,0) -> 0 | BE80: =IF($BD$8=$H80,$R80,0) -> 0 | BF80: =IF($BF$8=$H80,$Q80,0) -> 0 | BG80: =IF($BF$8=$H80,$R80,0) -> 0
A81: 1-01-02-02-047 | B81: RECEIVABLE FROM GHULAM ASGHAR | C81: 1-01-02-02-047-RECEIVABLE FROM GHULAM ASGHARTAF | D81: Balance Sheet | E81: Current Assets | F81: Loans, Advances, Deposits, Prepayments And Receivables | G81: Other Receivables | H81: TAF | I81: 50 | J81: 0 | K81: 0 | L81: 0 | M81: =+I81+K81 -> 50 | N81: =+J81+L81 -> 0 | Q81: =+M81+O81 -> 50 | R81: =+N81+P81 -> 0 | S81: =+Q81-R81 -> 50 | V81: =IF($V$8=$H81,$Q81,0) -> 0 | W81: =IF($V$8=$H81,$R81,0) -> 0 | X81: =IF($X$8=$H81,$Q81,0) -> 0 | Y81: =IF($X$8=$H81,$R81,0) -> 0 | Z81: =IF($Z$8=$H81,$Q81,0) -> 0 | AA81: =IF($Z$8=$H81,$R81,0) -> 0 | AB81: =IF($AB$8=$H81,$Q81,0) -> 50 | AC81: =IF($AB$8=$H81,$R81,0) -> 0 | AD81: =IF($AD$8=$H81,$Q81,0) -> 0 | AE81: =IF($AD$8=$H81,$R81,0) -> 0 | AF81: =IF($AF$8=$H81,$Q81,0) -> 0 | AG81: =IF($AF$8=$H81,$R81,0) -> 0 | AH81: =IF($AH$8=$H81,$Q81,0) -> 0 | AI81: =IF($AH$8=$H81,$R81,0) -> 0 | AJ81: =IF($AJ$8=$H81,$Q81,0) -> 0 | AK81: =IF($AJ$8=$H81,$R81,0) -> 0 | AL81: =IF($AL$8=$H81,$Q81,0) -> 0 | AM81: =IF($AL$8=$H81,$R81,0) -> 0 | AN81: =IF($AN$8=$H81,$Q81,0) -> 0 | AO81: =IF($AN$8=$H81,$R81,0) -> 0 | AP81: =IF($AP$8=$H81,$Q81,0) -> 0 | AQ81: =IF($AP$8=$H81,$R81,0) -> 0 | AR81: =IF($AR$8=$H81,$Q81,0) -> 0 | AS81: =IF($AR$8=$H81,$R81,0) -> 0 | AT81: =IF($AT$8=$H81,$Q81,0) -> 0 | AU81: =IF($AT$8=$H81,$R81,0) -> 0 | AV81: =IF($AV$8=$H81,$Q81,0) -> 0 | AW81: =IF($AV$8=$H81,$R81,0) -> 0 | AX81: =IF($AX$8=$H81,$Q81,0) -> 0 | AY81: =IF($AX$8=$H81,$R81,0) -> 0 | AZ81: =IF($AZ$8=$H81,$Q81,0) -> 0 | BA81: =IF($AZ$8=$H81,$R81,0) -> 0 | BB81: =IF($BB$8=$H81,$Q81,0) -> 0 | BC81: =IF($BB$8=$H81,$R81,0) -> 0 | BD81: =IF($BD$8=$H81,$Q81,0) -> 0 | BE81: =IF($BD$8=$H81,$R81,0) -> 0 | BF81: =IF($BF$8=$H81,$Q81,0) -> 0 | BG81: =IF($BF$8=$H81,$R81,0) -> 0
A82: 1-01-02-02-048 | B82: RECEIVABLE FROM MAHER ALI | C82: 1-01-02-02-048-RECEIVABLE FROM MAHER ALITAF | D82: Balance Sheet | E82: Current Assets | F82: Loans, Advances, Deposits, Prepayments And Receivables | G82: Other Receivables | H82: TAF | I82: 50 | J82: 0 | K82: 0 | L82: 0 | M82: =+I82+K82 -> 50 | N82: =+J82+L82 -> 0 | Q82: =+M82+O82 -> 50 | R82: =+N82+P82 -> 0 | S82: =+Q82-R82 -> 50 | V82: =IF($V$8=$H82,$Q82,0) -> 0 | W82: =IF($V$8=$H82,$R82,0) -> 0 | X82: =IF($X$8=$H82,$Q82,0) -> 0 | Y82: =IF($X$8=$H82,$R82,0) -> 0 | Z82: =IF($Z$8=$H82,$Q82,0) -> 0 | AA82: =IF($Z$8=$H82,$R82,0) -> 0 | AB82: =IF($AB$8=$H82,$Q82,0) -> 50 | AC82: =IF($AB$8=$H82,$R82,0) -> 0 | AD82: =IF($AD$8=$H82,$Q82,0) -> 0 | AE82: =IF($AD$8=$H82,$R82,0) -> 0 | AF82: =IF($AF$8=$H82,$Q82,0) -> 0 | AG82: =IF($AF$8=$H82,$R82,0) -> 0 | AH82: =IF($AH$8=$H82,$Q82,0) -> 0 | AI82: =IF($AH$8=$H82,$R82,0) -> 0 | AJ82: =IF($AJ$8=$H82,$Q82,0) -> 0 | AK82: =IF($AJ$8=$H82,$R82,0) -> 0 | AL82: =IF($AL$8=$H82,$Q82,0) -> 0 | AM82: =IF($AL$8=$H82,$R82,0) -> 0 | AN82: =IF($AN$8=$H82,$Q82,0) -> 0 | AO82: =IF($AN$8=$H82,$R82,0) -> 0 | AP82: =IF($AP$8=$H82,$Q82,0) -> 0 | AQ82: =IF($AP$8=$H82,$R82,0) -> 0 | AR82: =IF($AR$8=$H82,$Q82,0) -> 0 | AS82: =IF($AR$8=$H82,$R82,0) -> 0 | AT82: =IF($AT$8=$H82,$Q82,0) -> 0 | AU82: =IF($AT$8=$H82,$R82,0) -> 0 | AV82: =IF($AV$8=$H82,$Q82,0) -> 0 | AW82: =IF($AV$8=$H82,$R82,0) -> 0 | AX82: =IF($AX$8=$H82,$Q82,0) -> 0 | AY82: =IF($AX$8=$H82,$R82,0) -> 0 | AZ82: =IF($AZ$8=$H82,$Q82,0) -> 0 | BA82: =IF($AZ$8=$H82,$R82,0) -> 0 | BB82: =IF($BB$8=$H82,$Q82,0) -> 0 | BC82: =IF($BB$8=$H82,$R82,0) -> 0 | BD82: =IF($BD$8=$H82,$Q82,0) -> 0 | BE82: =IF($BD$8=$H82,$R82,0) -> 0 | BF82: =IF($BF$8=$H82,$Q82,0) -> 0 | BG82: =IF($BF$8=$H82,$R82,0) -> 0
A83: 1-01-02-02-050 | B83: RECEIVABLE FROM SHAKEEL AHMED | C83: 1-01-02-02-050-RECEIVABLE FROM SHAKEEL AHMEDTrocaire | D83: Balance Sheet | E83: Current Assets | F83: Loans, Advances, Deposits, Prepayments And Receivables | G83: Other Receivables | H83: Trocaire | I83: 50 | J83: 0 | K83: 0 | L83: 0 | M83: =+I83+K83 -> 50 | N83: =+J83+L83 -> 0 | Q83: =+M83+O83 -> 50 | R83: =+N83+P83 -> 0 | S83: =+Q83-R83 -> 50 | V83: =IF($V$8=$H83,$Q83,0) -> 0 | W83: =IF($V$8=$H83,$R83,0) -> 0 | X83: =IF($X$8=$H83,$Q83,0) -> 0 | Y83: =IF($X$8=$H83,$R83,0) -> 0 | Z83: =IF($Z$8=$H83,$Q83,0) -> 0 | AA83: =IF($Z$8=$H83,$R83,0) -> 0 | AB83: =IF($AB$8=$H83,$Q83,0) -> 0 | AC83: =IF($AB$8=$H83,$R83,0) -> 0 | AD83: =IF($AD$8=$H83,$Q83,0) -> 0 | AE83: =IF($AD$8=$H83,$R83,0) -> 0 | AF83: =IF($AF$8=$H83,$Q83,0) -> 0 | AG83: =IF($AF$8=$H83,$R83,0) -> 0 | AH83: =IF($AH$8=$H83,$Q83,0) -> 0 | AI83: =IF($AH$8=$H83,$R83,0) -> 0 | AJ83: =IF($AJ$8=$H83,$Q83,0) -> 50 | AK83: =IF($AJ$8=$H83,$R83,0) -> 0 | AL83: =IF($AL$8=$H83,$Q83,0) -> 0 | AM83: =IF($AL$8=$H83,$R83,0) -> 0 | AN83: =IF($AN$8=$H83,$Q83,0) -> 0 | AO83: =IF($AN$8=$H83,$R83,0) -> 0 | AP83: =IF($AP$8=$H83,$Q83,0) -> 0 | AQ83: =IF($AP$8=$H83,$R83,0) -> 0 | AR83: =IF($AR$8=$H83,$Q83,0) -> 0 | AS83: =IF($AR$8=$H83,$R83,0) -> 0 | AT83: =IF($AT$8=$H83,$Q83,0) -> 0 | AU83: =IF($AT$8=$H83,$R83,0) -> 0 | AV83: =IF($AV$8=$H83,$Q83,0) -> 0 | AW83: =IF($AV$8=$H83,$R83,0) -> 0 | AX83: =IF($AX$8=$H83,$Q83,0) -> 0 | AY83: =IF($AX$8=$H83,$R83,0) -> 0 | AZ83: =IF($AZ$8=$H83,$Q83,0) -> 0 | BA83: =IF($AZ$8=$H83,$R83,0) -> 0 | BB83: =IF($BB$8=$H83,$Q83,0) -> 0 | BC83: =IF($BB$8=$H83,$R83,0) -> 0 | BD83: =IF($BD$8=$H83,$Q83,0) -> 0 | BE83: =IF($BD$8=$H83,$R83,0) -> 0 | BF83: =IF($BF$8=$H83,$Q83,0) -> 0 | BG83: =IF($BF$8=$H83,$R83,0) -> 0
... A86: 1-01-02-02-053 | B86: RECEIVABLE FROM ABBAS HAIDER | C86: 1-01-02-02-053-RECEIVABLE FROM ABBAS HAIDERDeezire | D86: Balance Sheet | E86: Current Assets | F86: Loans, Advances, Deposits, Prepayments And Receivables | G86: Other Receivables | H86: Deezire | I86: 0 | J86: 240 | K86: 0 | L86: 0 | M86: =+I86+K86 -> 0 | N86: =+J86+L86 -> 240 | Q86: =+M86+O86 -> 0 | R86: =+N86+P86 -> 240 | S86: =+Q86-R86 -> -240 | V86: =IF($V$8=$H86,$Q86,0) -> 0 | W86: =IF($V$8=$H86,$R86,0) -> 0 | X86: =IF($X$8=$H86,$Q86,0) -> 0 | Y86: =IF($X$8=$H86,$R86,0) -> 0 | Z86: =IF($Z$8=$H86,$Q86,0) -> 0 | AA86: =IF($Z$8=$H86,$R86,0) -> 0 | AB86: =IF($AB$8=$H86,$Q86,0) -> 0 | AC86: =IF($AB$8=$H86,$R86,0) -> 0 | AD86: =IF($AD$8=$H86,$Q86,0) -> 0 | AE86: =IF($AD$8=$H86,$R86,0) -> 0 | AF86: =IF($AF$8=$H86,$Q86,0) -> 0 | AG86: =IF($AF$8=$H86,$R86,0) -> 0 | AH86: =IF($AH$8=$H86,$Q86,0) -> 0 | AI86: =IF($AH$8=$H86,$R86,0) -> 0 | AJ86: =IF($AJ$8=$H86,$Q86,0) -> 0 | AK86: =IF($AJ$8=$H86,$R86,0) -> 0 | AL86: =IF($AL$8=$H86,$Q86,0) -> 0 | AM86: =IF($AL$8=$H86,$R86,0) -> 0 | AN86: =IF($AN$8=$H86,$Q86,0) -> 0 | AO86: =IF($AN$8=$H86,$R86,0) -> 0 | AP86: =IF($AP$8=$H86,$Q86,0) -> 0 | AQ86: =IF($AP$8=$H86,$R86,0) -> 240 | AR86: =IF($AR$8=$H86,$Q86,0) -> 0 | AS86: =IF($AR$8=$H86,$R86,0) -> 0 | AT86: =IF($AT$8=$H86,$Q86,0) -> 0 | AU86: =IF($AT$8=$H86,$R86,0) -> 0 | AV86: =IF($AV$8=$H86,$Q86,0) -> 0 | AW86: =IF($AV$8=$H86,$R86,0) -> 0 | AX86: =IF($AX$8=$H86,$Q86,0) -> 0 | AY86: =IF($AX$8=$H86,$R86,0) -> 0 | AZ86: =IF($AZ$8=$H86,$Q86,0) -> 0 | BA86: =IF($AZ$8=$H86,$R86,0) -> 0 | BB86: =IF($BB$8=$H86,$Q86,0) -> 0 | BC86: =IF($BB$8=$H86,$R86,0) -> 0 | BD86: =IF($BD$8=$H86,$Q86,0) -> 0 | BE86: =IF($BD$8=$H86,$R86,0) -> 0 | BF86: =IF($BF$8=$H86,$Q86,0) -> 0 | BG86: =IF($BF$8=$H86,$R86,0) -> 0
A87: 1-01-02-02-053 | B87: RECEIVABLE FROM ABBAS HAIDER | C87: 1-01-02-02-053-RECEIVABLE FROM ABBAS HAIDERPILER | D87: Balance Sheet | E87: Current Assets | F87: Loans, Advances, Deposits, Prepayments And Receivables | G87: Other Receivables | H87: PILER | I87: 84 | J87: 0 | K87: 10247 | L87: 10247 | M87: =+I87+K87 -> 10331 | N87: =+J87+L87 -> 10247 | P87: ='Adjustments 2025'!F23 -> 10247 | Q87: =+M87+O87 -> 10331 | R87: =+N87+P87 -> 20494 | S87: =+Q87-R87 -> -10163
A88: 1-01-02-02-053 | B88: RECEIVABLE FROM ABBAS HAIDER | C88: 1-01-02-02-053-RECEIVABLE FROM ABBAS HAIDERUNICEF-2 | D88: Balance Sheet | E88: Current Assets | F88: Loans, Advances, Deposits, Prepayments And Receivables | G88: Other Receivables | H88: UNICEF-2 | I88: 50 | J88: 0 | K88: 0 | L88: 0 | M88: =+I88+K88 -> 50 | N88: =+J88+L88 -> 0 | Q88: =+M88+O88 -> 50 | R88: =+N88+P88 -> 0 | S88: =+Q88-R88 -> 50 | V88: =IF($V$8=$H88,$Q88,0) -> 0 | W88: =IF($V$8=$H88,$R88,0) -> 0 | X88: =IF($X$8=$H88,$Q88,0) -> 0 | Y88: =IF($X$8=$H88,$R88,0) -> 0 | Z88: =IF($Z$8=$H88,$Q88,0) -> 0 | AA88: =IF($Z$8=$H88,$R88,0) -> 0 | AB88: =IF($AB$8=$H88,$Q88,0) -> 0 | AC88: =IF($AB$8=$H88,$R88,0) -> 0 | AD88: =IF($AD$8=$H88,$Q88,0) -> 0 | AE88: =IF($AD$8=$H88,$R88,0) -> 0 | AF88: =IF($AF$8=$H88,$Q88,0) -> 50 | AG88: =IF($AF$8=$H88,$R88,0) -> 0 | AH88: =IF($AH$8=$H88,$Q88,0) -> 0 | AI88: =IF($AH$8=$H88,$R88,0) -> 0 | AJ88: =IF($AJ$8=$H88,$Q88,0) -> 0 | AK88: =IF($AJ$8=$H88,$R88,0) -> 0 | AL88: =IF($AL$8=$H88,$Q88,0) -> 0 | AM88: =IF($AL$8=$H88,$R88,0) -> 0 | AN88: =IF($AN$8=$H88,$Q88,0) -> 0 | AO88: =IF($AN$8=$H88,$R88,0) -> 0 | AP88: =IF($AP$8=$H88,$Q88,0) -> 0 | AQ88: =IF($AP$8=$H88,$R88,0) -> 0 | AR88: =IF($AR$8=$H88,$Q88,0) -> 0 | AS88: =IF($AR$8=$H88,$R88,0) -> 0 | AT88: =IF($AT$8=$H88,$Q88,0) -> 0 | AU88: =IF($AT$8=$H88,$R88,0) -> 0 | AV88: =IF($AV$8=$H88,$Q88,0) -> 0 | AW88: =IF($AV$8=$H88,$R88,0) -> 0 | AX88: =IF($AX$8=$H88,$Q88,0) -> 0 | AY88: =IF($AX$8=$H88,$R88,0) -> 0 | AZ88: =IF($AZ$8=$H88,$Q88,0) -> 0 | BA88: =IF($AZ$8=$H88,$R88,0) -> 0 | BB88: =IF($BB$8=$H88,$Q88,0) -> 0 | BC88: =IF($BB$8=$H88,$R88,0) -> 0 | BD88: =IF($BD$8=$H88,$Q88,0) -> 0 | BE88: =IF($BD$8=$H88,$R88,0) -> 0 | BF88: =IF($BF$8=$H88,$Q88,0) -> 0 | BG88: =IF($BF$8=$H88,$R88,0) -> 0
A89: 1-01-02-02-053 | B89: RECEIVABLE FROM ABBAS HAIDER | C89: 1-01-02-02-053-RECEIVABLE FROM ABBAS HAIDERGRC | D89: Balance Sheet | E89: Current Assets | F89: Loans, Advances, Deposits, Prepayments And Receivables | G89: Other Receivables | H89: GRC | I89: 0 | J89: 0 | K89: 1000000 | L89: 1000000 | M89: =+I89+K89 -> 1000000 | N89: =+J89+L89 -> 1000000 | Q89: =+M89+O89 -> 1000000 | R89: =+N89+P89 -> 1000000 | S89: =+Q89-R89 -> 0 | V89: =IF($V$8=$H89,$Q89,0) -> 0 | W89: =IF($V$8=$H89,$R89,0) -> 0 | X89: =IF($X$8=$H89,$Q89,0) -> 0 | Y89: =IF($X$8=$H89,$R89,0) -> 0 | Z89: =IF($Z$8=$H89,$Q89,0) -> 0 | AA89: =IF($Z$8=$H89,$R89,0) -> 0 | AB89: =IF($AB$8=$H89,$Q89,0) -> 0 | AC89: =IF($AB$8=$H89,$R89,0) -> 0 | AD89: =IF($AD$8=$H89,$Q89,0) -> 0 | AE89: =IF($AD$8=$H89,$R89,0) -> 0 | AF89: =IF($AF$8=$H89,$Q89,0) -> 0 | AG89: =IF($AF$8=$H89,$R89,0) -> 0 | AH89: =IF($AH$8=$H89,$Q89,0) -> 0 | AI89: =IF($AH$8=$H89,$R89,0) -> 0 | AJ89: =IF($AJ$8=$H89,$Q89,0) -> 0 | AK89: =IF($AJ$8=$H89,$R89,0) -> 0 | AL89: =IF($AL$8=$H89,$Q89,0) -> 0 | AM89: =IF($AL$8=$H89,$R89,0) -> 0 | AN89: =IF($AN$8=$H89,$Q89,0) -> 0 | AO89: =IF($AN$8=$H89,$R89,0) -> 0 | AP89: =IF($AP$8=$H89,$Q89,0) -> 0 | AQ89: =IF($AP$8=$H89,$R89,0) -> 0 | AR89: =IF($AR$8=$H89,$Q89,0) -> 0 | AS89: =IF($AR$8=$H89,$R89,0) -> 0 | AT89: =IF($AT$8=$H89,$Q89,0) -> 0 | AU89: =IF($AT$8=$H89,$R89,0) -> 0 | AV89: =IF($AV$8=$H89,$Q89,0) -> 0 | AW89: =IF($AV$8=$H89,$R89,0) -> 0 | AX89: =IF($AX$8=$H89,$Q89,0) -> 0 | AY89: =IF($AX$8=$H89,$R89,0) -> 0 | AZ89: =IF($AZ$8=$H89,$Q89,0) -> 0 | BA89: =IF($AZ$8=$H89,$R89,0) -> 0 | BB89: =IF($BB$8=$H89,$Q89,0) -> 0 | BC89: =IF($BB$8=$H89,$R89,0) -> 0 | BD89: =IF($BD$8=$H89,$Q89,0) -> 0 | BE89: =IF($BD$8=$H89,$R89,0) -> 0 | BF89: =IF($BF$8=$H89,$Q89,0) -> 0 | BG89: =IF($BF$8=$H89,$R89,0) -> 0
A90: 1-01-02-02-054 | B90: RECEIVABLE FROM ABIDA SHARAFAT | C90: 1-01-02-02-054-RECEIVABLE FROM ABIDA SHARAFATUNICEF-2 | D90: Balance Sheet | E90: Current Assets | F90: Loans, Advances, Deposits, Prepayments And Receivables | G90: Other Receivables | H90: UNICEF-2 | I90: 50 | J90: 0 | K90: 0 | L90: 0 | M90: =+I90+K90 -> 50 | N90: =+J90+L90 -> 0 | Q90: =+M90+O90 -> 50 | R90: =+N90+P90 -> 0 | S90: =+Q90-R90 -> 50 | V90: =IF($V$8=$H90,$Q90,0) -> 0 | W90: =IF($V$8=$H90,$R90,0) -> 0 | X90: =IF($X$8=$H90,$Q90,0) -> 0 | Y90: =IF($X$8=$H90,$R90,0) -> 0 | Z90: =IF($Z$8=$H90,$Q90,0) -> 0 | AA90: =IF($Z$8=$H90,$R90,0) -> 0 | AB90: =IF($AB$8=$H90,$Q90,0) -> 0 | AC90: =IF($AB$8=$H90,$R90,0) -> 0 | AD90: =IF($AD$8=$H90,$Q90,0) -> 0 | AE90: =IF($AD$8=$H90,$R90,0) -> 0 | AF90: =IF($AF$8=$H90,$Q90,0) -> 50 | AG90: =IF($AF$8=$H90,$R90,0) -> 0 | AH90: =IF($AH$8=$H90,$Q90,0) -> 0 | AI90: =IF($AH$8=$H90,$R90,0) -> 0 | AJ90: =IF($AJ$8=$H90,$Q90,0) -> 0 | AK90: =IF($AJ$8=$H90,$R90,0) -> 0 | AL90: =IF($AL$8=$H90,$Q90,0) -> 0 | AM90: =IF($AL$8=$H90,$R90,0) -> 0 | AN90: =IF($AN$8=$H90,$Q90,0) -> 0 | AO90: =IF($AN$8=$H90,$R90,0) -> 0 | AP90: =IF($AP$8=$H90,$Q90,0) -> 0 | AQ90: =IF($AP$8=$H90,$R90,0) -> 0 | AR90: =IF($AR$8=$H90,$Q90,0) -> 0 | AS90: =IF($AR$8=$H90,$R90,0) -> 0 | AT90: =IF($AT$8=$H90,$Q90,0) -> 0 | AU90: =IF($AT$8=$H90,$R90,0) -> 0 | AV90: =IF($AV$8=$H90,$Q90,0) -> 0 | AW90: =IF($AV$8=$H90,$R90,0) -> 0 | AX90: =IF($AX$8=$H90,$Q90,0) -> 0 | AY90: =IF($AX$8=$H90,$R90,0) -> 0 | AZ90: =IF($AZ$8=$H90,$Q90,0) -> 0 | BA90: =IF($AZ$8=$H90,$R90,0) -> 0 | BB90: =IF($BB$8=$H90,$Q90,0) -> 0 | BC90: =IF($BB$8=$H90,$R90,0) -> 0 | BD90: =IF($BD$8=$H90,$Q90,0) -> 0 | BE90: =IF($BD$8=$H90,$R90,0) -> 0 | BF90: =IF($BF$8=$H90,$Q90,0) -> 0 | BG90: =IF($BF$8=$H90,$R90,0) -> 0
A91: 1-01-02-02-055 | B91: RECEIVABLE FROM MIR MULADAD | C91: 1-01-02-02-055-RECEIVABLE FROM MIR MULADADUNICEF-2 | D91: Balance Sheet | E91: Current Assets | F91: Loans, Advances, Deposits, Prepayments And Receivables | G91: Other Receivables | H91: UNICEF-2 | I91: 50 | J91: 0 | K91: 0 | L91: 0 | M91: =+I91+K91 -> 50 | N91: =+J91+L91 -> 0 | Q91: =+M91+O91 -> 50 | R91: =+N91+P91 -> 0 | S91: =+Q91-R91 -> 50 | V91: =IF($V$8=$H91,$Q91,0) -> 0 | W91: =IF($V$8=$H91,$R91,0) -> 0 | X91: =IF($X$8=$H91,$Q91,0) -> 0 | Y91: =IF($X$8=$H91,$R91,0) -> 0 | Z91: =IF($Z$8=$H91,$Q91,0) -> 0 | AA91: =IF($Z$8=$H91,$R91,0) -> 0 | AB91: =IF($AB$8=$H91,$Q91,0) -> 0 | AC91: =IF($AB$8=$H91,$R91,0) -> 0 | AD91: =IF($AD$8=$H91,$Q91,0) -> 0 | AE91: =IF($AD$8=$H91,$R91,0) -> 0 | AF91: =IF($AF$8=$H91,$Q91,0) -> 50 | AG91: =IF($AF$8=$H91,$R91,0) -> 0 | AH91: =IF($AH$8=$H91,$Q91,0) -> 0 | AI91: =IF($AH$8=$H91,$R91,0) -> 0 | AJ91: =IF($AJ$8=$H91,$Q91,0) -> 0 | AK91: =IF($AJ$8=$H91,$R91,0) -> 0 | AL91: =IF($AL$8=$H91,$Q91,0) -> 0 | AM91: =IF($AL$8=$H91,$R91,0) -> 0 | AN91: =IF($AN$8=$H91,$Q91,0) -> 0 | AO91: =IF($AN$8=$H91,$R91,0) -> 0 | AP91: =IF($AP$8=$H91,$Q91,0) -> 0 | AQ91: =IF($AP$8=$H91,$R91,0) -> 0 | AR91: =IF($AR$8=$H91,$Q91,0) -> 0 | AS91: =IF($AR$8=$H91,$R91,0) -> 0 | AT91: =IF($AT$8=$H91,$Q91,0) -> 0 | AU91: =IF($AT$8=$H91,$R91,0) -> 0 | AV91: =IF($AV$8=$H91,$Q91,0) -> 0 | AW91: =IF($AV$8=$H91,$R91,0) -> 0 | AX91: =IF($AX$8=$H91,$Q91,0) -> 0 | AY91: =IF($AX$8=$H91,$R91,0) -> 0 | AZ91: =IF($AZ$8=$H91,$Q91,0) -> 0 | BA91: =IF($AZ$8=$H91,$R91,0) -> 0 | BB91: =IF($BB$8=$H91,$Q91,0) -> 0 | BC91: =IF($BB$8=$H91,$R91,0) -> 0 | BD91: =IF($BD$8=$H91,$Q91,0) -> 0 | BE91: =IF($BD$8=$H91,$R91,0) -> 0 | BF91: =IF($BF$8=$H91,$Q91,0) -> 0 | BG91: =IF($BF$8=$H91,$R91,0) -> 0
